Workbook

Sheet Resumo
A1: PLANILHA DE ESTIMATIVA DE HORAS PARA PROJETOS DE IMPLANTAÇÃO CLOVER CRM
B2: Parâmetros Gerais: | J2: Formato dos Treinamentos: | R2: Nome do Cliente:
B3: Número total de usuários licenciados | C3: 25 | J3: Treinamento Adm, Configuração e Simulações: | N3: Presencial | R3: <Digite o nome do cliente aqui>
B4: Fator p/ Gestão de Projeto | C4: 0.08 | J4: Treinamento Operacional e Go-Live: | N4: Presencial
B5: ERP do cliente | C5: ALIARE - SOLUTION | J5: Número de administradores: | N5: 1
B6: Método de integração do Aliare Integra | C6: API padrão ERP | J6: Número de usuários operacionais (vendedores): | N6: 5 | P6: Qtde Tumas Gestores
B7: Será usado ambiente de produção e homologação? | C7: NÃO | J7: Número de gestores: | N7: 1 | P7: =(ROUNDUP(N7/N9,0))*N10 -> 1 | R7: Regras para treinamentos: Treinamentos presenciais: 20 pessoas por turma, a partir de 25 pessoas será contabilizados 2 consultores. Treinamentos remotos: 10 pessoas por turma.
B8: O projeto será na Cloud Aliare? | C8: SIM | J8: Tamanho das Turmas p/ Treinamento Operacional: | N8: 25 | P8: Qtd Tumas Operac.
B9: Fases de implantação | C9: 1 | J9: Tamanho das Turmas p/ Treinamento Gestor: | N9: 10 | P9: =(ROUNDUP(N6/N8,0))*N10 -> 1 | W9: 1 | X9: consultor | Y9: 2 | Z9: consultores
B10: Coeficiente de complexidade (multi-empresa) | C10: 1 | J10: Em quantas etapas ocorrerá o Go-Live por fase: | N10: 1 | W10: 24 | Y10: 25
A12: Escopo Cliente (x) | B12: Módulos do Clover | C12: Estimativa de Horas do Projeto de Implantação
C13: Instalação dos sistemas | D13: Definição de regras, processos, layouts e documentação | E13: Integração de Dados Técnica | H13: Validação de dados da integração | K13: Parametrização | N13: Treinamento Adm., Config. e Simulação | O13: Validação do ambiente + testes funcionais | R13: Go-Live | S13: Acompanhamento Go-Live | T13: Pós-Produção
E14: Total | F14: Homologação | G14: Produção | H14: Total | I14: Homologação | J14: Produção | K14: Total | L14: Homologação | M14: Produção | O14: Total | P14: Homologação | Q14: Produção
A15: x | B15: CRM - MM - Funcionalidades Fundamentais | C15: =Funcionalidades!H2 -> 1 | D15: =IF(A15="x", Funcionalidades!$M$3, "") -> 5.2899 | E15: =IF(A15<>"x", "", IF(C6<>"Sem integração",(IF(AND(OR(C5="ALIARE - AGB",C5="SIMER",C5="ALIARE - SOLUTION"),C6="API padrão ERP"),Funcionalidades!I2,IF(AND(C5="ALIARE - AGB",C6="Integração (antiga)"),#REF!,IF(AND(OR(C5<>"ALIARE - AGB",C5<>"SIMER",C5<>"ALIARE - SOLUTION"),C6="API padrão ERP"),'Aliare Integra ERP Terceiro'!B117*24,Funcionalidades!I2)))),0))*'AGBCLOVER-Listagem dos fluxos'!$G$14 -> 20 | F15: 0 | G15: =IF($A$15 = "x", IF($C$7 = "SIM",$E$15*0.3, E15),"0,00") -> 20 | H15: =IF(A15="x", Funcionalidades!L2, "") -> 17.2689 | I15: =IF(A15 = "x", IF($C$7 = "SIM",H15*0.7, " "), " ") | J15: =IF(A15 = "x", IF($C$7 = "SIM",H15*0.3, H15)," ") -> 17.2689 | K15: =IF(A15="x", Funcionalidades!$N$3, "") -> 5.2899 | L15: =IF(A15 = "x", IF($C$7 = "SIM",K15*0.7, " "), K15) | M15: =IF(A15 = "x", IF($C$7 = "SIM",K15*0.3, K15), " ") -> 5.2899 | N15: =IF(A15="x", Funcionalidades!$O$3, "") -> 10.5171 | O15: =IF(A15="x", Funcionalidades!$P$3, "") -> 2.6466 | P15: =IF(A15 = "x", IF($C$7 = "SIM",O15*0.7, " "), O15) | Q15: =IF(A15 = "x", IF($C$7 = "SIM",O15*0.3, O15)," ") -> 2.6466 | R15: =IF($A15="x", Funcionalidades!$Q$3, "") -> 3.9666 | S15: =8*$C$9*N10 -> 8 | T15: 12
B16: CRM - MM - Registro de Visita | D16: =IF(A16="x", Funcionalidades!$M$100, "") | K16: =IF(A16="x", Funcionalidades!$N$100, "") | L16: =IF(A16 = "x", IF($C$7 = "SIM",K16*0.7, " "), K16) | M16: =IF(A16 = "x", IF($C$7 = "SIM",K16*0.3, K16), " ") | N16: =IF(A16="x", Funcionalidades!$O$100, "") | O16: =IF(A16="x", Funcionalidades!$P$100, "") | P16: =IF(A16 = "x", IF($C$7 = "SIM",O16*0.7, " "), O16) | Q16: =IF(A16 = "x", IF($C$7 = "SIM",O16*0.3, O16)," ") | R16: =IF(A16="x", Funcionalidades!$Q$100, "")
B17: CRM - MM - Potencial & Metas | D17: =IF(A17="x", Funcionalidades!$M$126, "") | K17: =IF(A17="x", Funcionalidades!$N$126, "") | L17: =IF(A17 = "x", IF($C$7 = "SIM",K17*0.7, " "), K17) | M17: =IF(A17 = "x", IF($C$7 = "SIM",K17*0.3, K17), " ") | N17: =IF(A17="x", Funcionalidades!$O$126, "") | O17: =IF(A17="x", Funcionalidades!$P$126, "") | P17: =IF(A17 = "x", IF($C$7 = "SIM",O17*0.7, " "), O17) | Q17: =IF(A17 = "x", IF($C$7 = "SIM",O17*0.3, O17)," ") | R17: =IF(A17="x", Funcionalidades!$Q$126, "")
B18: CRM - MM - Segmentação | D18: =IF(A18="x", Funcionalidades!$M$216, "") | K18: =IF(A18="x", Funcionalidades!$N$216, "") | L18: =IF(A18 = "x", IF($C$7 = "SIM",K18*0.7, " "), K18) | M18: =IF(A18 = "x", IF($C$7 = "SIM",K18*0.3, K18), " ") | N18: =IF(A18="x", Funcionalidades!$O$216, "") | O18: =IF(A18="x", Funcionalidades!$P$216, "") | P18: =IF(A18 = "x", IF($C$7 = "SIM",O18*0.7, " "), O18) | Q18: =IF(A18 = "x", IF($C$7 = "SIM",O18*0.3, O18)," ") | R18: =IF(A18="x", Funcionalidades!$Q$216, "")
B19: CRM - MM - Previsão de Vendas | D19: =IF(A19="x", Funcionalidades!$M$231, "") | K19: =IF(A19="x", Funcionalidades!$N$231, "") | L19: =IF(A19 = "x", IF($C$7 = "SIM",K19*0.7, " "), K19) | M19: =IF(A19 = "x", IF($C$7 = "SIM",K19*0.3, K19), " ") | N19: =IF(A19="x", Funcionalidades!$O$231, "") | O19: =IF(A19="x", Funcionalidades!$P$231, "") | P19: =IF(A19 = "x", IF($C$7 = "SIM",O19*0.7, " "), O19) | Q19: =IF(A19 = "x", IF($C$7 = "SIM",O19*0.3, O19)," ") | R19: =IF(A19="x", Funcionalidades!$Q$231, "")
B20: CRM - MM - Analise de Vendas | D20: =IF(A20="x", Funcionalidades!$M$264, "") | K20: =IF(A20="x", Funcionalidades!$N$264, "") | L20: =IF(A20 = "x", IF($C$7 = "SIM",K20*0.7, " "), K20) | M20: =IF(A20 = "x", IF($C$7 = "SIM",K20*0.3, K20), " ") | N20: =IF(A20="x", Funcionalidades!$O$264, "") | O20: =IF(A20="x", Funcionalidades!$P$264, "") | P20: =IF(A20 = "x", IF($C$7 = "SIM",O20*0.7, " "), O20) | Q20: =IF(A20 = "x", IF($C$7 = "SIM",O20*0.3, O20)," ") | R20: =IF(A20="x", Funcionalidades!$Q$264, "")
B21: CRM - MM - Potencial Maquinas | D21: =IF(A21="x", Funcionalidades!$M$274, "") | K21: =IF(A21="x", Funcionalidades!$N$274, "") | L21: =IF(A21 = "x", IF($C$7 = "SIM",K21*0.7, " "), K21) | M21: =IF(A21 = "x", IF($C$7 = "SIM",K21*0.3, K21), " ") | N21: =IF(A21="x", Funcionalidades!$O$274, "") | O21: =IF(A21="x", Funcionalidades!$P$274, "") | P21: =IF(A21 = "x", IF($C$7 = "SIM",O21*0.7, " "), O21) | Q21: =IF(A21 = "x", IF($C$7 = "SIM",O21*0.3, O21)," ") | R21: =IF(A21="x", Funcionalidades!$Q$274, "")
B22: CRM - MM - Chamados | D22: =IF(A22="x", Funcionalidades!$M$294, "") | K22: =IF(A22="x", Funcionalidades!$N$294, "") | L22: =IF(A22 = "x", IF($C$7 = "SIM",K22*0.7, " "), K22) | M22: =IF(A22 = "x", IF($C$7 = "SIM",K22*0.3, K22), " ") | N22: =IF(A22="x", Funcionalidades!$O$294, "") | O22: =IF(A22="x", Funcionalidades!$P$294, "") | P22: =IF(A22 = "x", IF($C$7 = "SIM",O22*0.7, " "), O22) | Q22: =IF(A22 = "x", IF($C$7 = "SIM",O22*0.3, O22)," ") | R22: =IF(A22="x", Funcionalidades!$Q$294, "")
A23: x | B23: CRM - MM - Força de Vendas | D23: =IF(A23="x", Funcionalidades!$M$142, "") -> 5.9895 | K23: =IF(A23="x", Funcionalidades!$N$142, "") -> 11.979 | L23: =IF(A23 = "x", IF($C$7 = "SIM",K23*0.7, " "), K23) | M23: =IF(A23 = "x", IF($C$7 = "SIM",K23*0.3, K23), " ") -> 11.979 | N23: =IF(A23="x", Funcionalidades!$O$142, "") -> 8.9865 | O23: =IF(A23="x", Funcionalidades!$P$142, "") -> 3.06 | P23: =IF(A23 = "x", IF($C$7 = "SIM",O23*0.7, " "), O23) | Q23: =IF(A23 = "x", IF($C$7 = "SIM",O23*0.3, O23)," ") -> 3.06 | R23: =IF(A23="x", Funcionalidades!$Q$142, "") -> 2.997
B24: CRM - MM - Viagem | D24: =IF(A24="x", Funcionalidades!$M$193, "") | K24: =IF(A24="x", Funcionalidades!$N$193, "") | L24: =IF(A24 = "x", IF($C$7 = "SIM",K24*0.7, " "), K24) | M24: =IF(A24 = "x", IF($C$7 = "SIM",K24*0.3, K24), " ") | N24: =IF(A24="x", Funcionalidades!$O$193, "") | O24: =IF(A24="x", Funcionalidades!$P$193, "") | P24: =IF(A24 = "x", IF($C$7 = "SIM",O24*0.7, " "), O24) | Q24: =IF(A24 = "x", IF($C$7 = "SIM",O24*0.3, O24)," ") | R24: =IF(A24="x", Funcionalidades!$Q$193, "")
B25: CRM - MM - Funil de Vendas | D25: =IF(A25="x", Funcionalidades!$M$248, "") | K25: =IF(A25="x", Funcionalidades!$N$248, "") | L25: =IF(A25 = "x", IF($C$7 = "SIM",K25*0.7, " "), K25) | M25: =IF(A25 = "x", IF($C$7 = "SIM",K25*0.3, K25), " ") | N25: =IF(A25="x", Funcionalidades!$O$248, "") | O25: =IF(A25="x", Funcionalidades!$P$248, "") | P25: =IF(A25 = "x", IF($C$7 = "SIM",O25*0.7, " "), O25) | Q25: =IF(A25 = "x", IF($C$7 = "SIM",O25*0.3, O25)," ") | R25: =IF(A25="x", Funcionalidades!$Q$248, "")
B26: CRM - MM - Proposta de Crédito | D26: =IF(A26="x", Funcionalidades!M222, "") | K26: =IF(A26="x", Funcionalidades!$N$222, "") | L26: =IF(A26 = "x", IF($C$7 = "SIM",K26*0.7, " "), K26) | M26: =IF(A26 = "x", IF($C$7 = "SIM",K26*0.3, K26), " ") | N26: =IF(A26="x", Funcionalidades!$O$222, "") | O26: =IF(A26="x", Funcionalidades!$P$222, "") | P26: =IF(A26 = "x", IF($C$7 = "SIM",O26*0.7, " "), O26) | Q26: =IF(A26 = "x", IF($C$7 = "SIM",O26*0.3, O26)," ") | R26: =IF(A26="x", Funcionalidades!$Q$222, "")
B27: CRM - MM - Ordem de Serviço | D27: =IF(A27="x", Funcionalidades!$M$239, "") | K27: =IF(A27="x", Funcionalidades!$N$239, "") | L27: =IF(A27 = "x", IF($C$7 = "SIM",K27*0.7, " "), K27) | M27: =IF(A27 = "x", IF($C$7 = "SIM",K27*0.3, K27), " ") | N27: =IF(A27="x", Funcionalidades!$O$239, "") | O27: =IF(A27="x", Funcionalidades!$P$239, "") | P27: =IF(A27 = "x", IF($C$7 = "SIM",O27*0.7, " "), O27) | Q27: =IF(A27 = "x", IF($C$7 = "SIM",O27*0.3, O27)," ") | R27: =IF(A27="x", Funcionalidades!$Q$239, "")
A28: =COUNTIF(A15:A27,"x") -> 2 | B28: TOTAL | C28: =C15 -> 1 | D28: =SUM(D15:D27) -> 11.2794 | F28: =SUM(F15:F27) -> 0 | G28: =SUM(G15:G27) -> 20 | I28: =SUM(I15:I27) -> 0 | J28: =SUM(J15:J27) -> 17.2689 | L28: =SUM(L15:L27) -> 0 | M28: =SUM(M15:M27) -> 17.2689 | N28: =SUM(N15:N27) -> 19.5036 | P28: =SUM(P15:P27) -> 0 | Q28: =SUM(Q15:Q27) -> 5.7066 | R28: =SUM(R15:R27) -> 6.9636 | S28: =$S$15 -> 8 | T28: =$T$15 -> 12
B30: SERVIÇOS
B31: Especialidade | C31: Horas Estimadas | D31: %
B32: Gerenciamento de Projeto | C32: =ROUNDUP(SUM(C34:C36)*C4,0) -> 10 | D32: =C32/$C$37 -> 0.07751938
B33: Instalação | C33: =ROUNDUP(C28,0) -> 1 | D33: =C33/$C$37 -> 0.007751938
B34: Implantação | C34: =ROUNDUP(SUM($D$28,$L$28:$T$28,$I$28:$J$28),0) -> 98 | D34: =C34/$C$37 -> 0.75968992
B35: Integração Técnica | C35: =ROUNDUP(SUM(F28:G28),0) -> 20 | D35: =C35/$C$37 -> 0.15503876
B36: Adequações | C36: =D42 -> 0 | D36: =C36/$C$37 -> 0
B37: TOTAL | C37: =SUM(C32:C36) -> 129 | D37: =SUM(D32:D36) -> 1
A40: Tarefa | B40: Descrição | D40: Horas
A41: 1 | B41: Adequações | D41: 0
C42: TOTAL | D42: =SUM(D41:D41) -> 0
L159: = SE(E(A101="x";D109="x"); 0; SE(E(A314='Resumo'!A23"x";OU(D314="x";D315="x";D316="x")); 0;'Aliare Integra AGB'!G24))

Sheet Funcionalidades
A1: TOTAL ESTIMADO DE HORAS (s/ horas de gestão de projeto) | F1: =SUM(G2+H2+I2) -> 99 | G1: C&S CRM | H1: instalação | I1: Integração de Dados | J1: Fluxos de Integração | K1: Tabelas Integradas | L1: Validação de Dados | M1: LRP | N1: Parametrização | O1: Simulação e Treinamento | P1: Validação de Ambiente | Q1: Go Live | R1: Acomp. Go Live | S1: Pós-produção
B2: Módulo | C2: Funcionalidade Mãe | D2: Contratado? | E2: Funcionalidade Filha | F2: Tipo de funcionalidade | G2: =SUM(G3+G100+G126+G142+G193+G216+G222+G231+G239+G248) -> 78 | H2: =("01:00:00" + (IF(Resumo!$C$5 = "ALIARE - AGB","05:00:00","00:00:00")) + (IF(Resumo!$C$7 = "SIM","04:00:00","00:00:00")))*24 -> 1 | I2: =SUM(I3,I100,I126,I142,I193,I216,I222,I231,I239,I248,I264,I274) -> 20 | L2: =(L3+L100+L126+L142+L193+L216+L222+L231+L239+L248) -> 17.2689 | M2: =SUM(M3,M100,M142,M193,M216,M222,M231,M239,M248) -> 9.966 | N2: =SUM(N3,N100,N126,N142,N193,N216,N222,N231,N239,N248) -> 17.2689 | O2: =SUM(O3,O100,O126,O142,O193,O216,O222,O231,O239,O248) -> 19.5036 | P2: =SUM(P3,P100,P126,P142,P193,P216,P222,P231,P239,P248) -> 5.7066 | Q2: =SUM(Q3,Q100,Q126,Q142,Q193,Q216,Q222,Q231,Q239,Q248) -> 6.9636 | R2: =SUM(R3,R100,R126,R142,R193,R216,R222,R231,R239) -> 0 | S2: =SUM(S3,S100,S126,S142,S193,S216,S222,S231,S239,S248) -> 0
B3: CRM - MM - Funcionalidades Fundamentais | G3: =ROUNDUP(IF($A$4="x", SUMIF($D$4:$D$99,"x",$G$4:$G$99) * 24, 0),0) -> 33 | I3: =ROUNDUP(IF($A$4="x",SUMIF($D$4:$D$99,"x",$I$4:$I$99)*24,0),0) -> 6 | L3: =G3*0.1603 + IF(Resumo!C7 = "SIM",(G3*0.1603)*0.3,0) -> 5.2899 | M3: =$G$3*0.1603 -> 5.2899 | N3: =$G$3*0.1603 + IF(Resumo!$C$7="SIM", $G$3*0.1603*0.3, 0) -> 5.2899 | O3: =$G$3*0.3187 -> 10.5171 | P3: =$G$3*0.0802 + IF(Resumo!$C$7 = "SIM",($G$3*0.0802*0.3),0) -> 2.6466 | Q3: =($G$3*0.1202)*Resumo!P9 -> 3.9666 | R3: =$G$3*0 -> 0 | S3: 0
A4: =IF(Resumo!A15="x",Resumo!A15,"") -> x | C4: Cadastros Fundamentais | D4: x | E4: Empresa/Filial | F4: Obrigatório | G4: 0.041666667 | J4: =IF(OR(Resumo!$C$5="ALIARE - AGB", Resumo!$C$5="SIMER",Resumo!$C$5="ALIARE - SOLUTION"), _xlfn.CONCAT('Aliare Integra Solution'!$A$15," + ",'Aliare Integra Solution'!$A$18), _xlfn.CONCAT('Aliare Integra ERP Terceiro'!$A$15,"+",'Aliare Integra ERP Terceiro'!$A$18)) -> Cadastro básico – Empresa + Cadastro básico - Filial | K4: =IF(Resumo!$C$5="ALIARE - SOLUTION", _xlfn.CONCAT('Aliare Integra Solution'!$B$15,"+",'Aliare Integra Solution'!$B$18), _xlfn.CONCAT('Aliare Integra ERP Terceiro'!$B$15,"+",'Aliare Integra ERP Terceiro'!$B$18)) -> 1.14 Empresa+1.15 Filial
D5: x | E5: Grupo Empresarial | F5: Obrigatório | G5: 0.013888889
D6: x | E6: Unidade Federativa | F6: Obrigatório | G6: 0.020833333 | J6: =IF(OR(Resumo!$C$5="ALIARE - AGB", Resumo!$C$5="SIMER",Resumo!$C$5="ALIARE - SOLUTION"), 'Aliare Integra Solution'!$A$6,'Aliare Integra ERP Terceiro'!$A$6) -> Cadastro básico - País, Estado e Cidade | K6: =IF(Resumo!$C$5="ALIARE - SOLUTION", 'Aliare Integra Solution'!$B$6, 'Aliare Integra ERP Terceiro'!$B$6) -> 1.01 País
D7: x | E7: País | F7: Obrigatório | G7: 0.0069444444 | K7: =IF(Resumo!$C$5="ALIARE - SOLUTION", 'Aliare Integra Solution'!$B$7, 'Aliare Integra ERP Terceiro'!$B$7) -> 1.02 Unidade Federativa
D8: x | E8: Cidade | F8: Obrigatório | G8: 0.0069444444 | K8: =IF(Resumo!$C$5="ALIARE - SOLUTION", 'Aliare Integra Solution'!$B$8, 'Aliare Integra ERP Terceiro'!$B$8) -> 1.03 Cidade
D9: x | E9: Unidade de medida | F9: Opcional | G9: 0.020833333 | J9: =IF(OR(Resumo!$C$5="ALIARE - AGB", Resumo!$C$5="SIMER",Resumo!$C$5="ALIARE - SOLUTION"), 'Aliare Integra Solution'!$A$9,'Aliare Integra ERP Terceiro'!$A$9) -> Cadastro básico - Unidade de medida | K9: =IF(Resumo!$C$5="ALIARE - SOLUTION", 'Aliare Integra Solution'!$B$9, 'Aliare Integra ERP Terceiro'!$B$9) -> 1.04 Unidade de Medida
D10: x | E10: Safra | F10: Opcional | G10: 0.03125 | J10: =IF(OR(Resumo!$C$5="ALIARE - AGB", Resumo!$C$5="SIMER",Resumo!$C$5="ALIARE - SOLUTION"), 'Aliare Integra Solution'!$A$33,'Aliare Integra ERP Terceiro'!$A$33) -> Cadastro básico - Safra | K10: =IF(Resumo!$C$5="ALIARE - SOLUTION", 'Aliare Integra Solution'!$B$33, 'Aliare Integra ERP Terceiro'!$B$33) -> 1.13 Safra
D11: x | E11: Cultura | F11: Opcional | J11: =IF(OR(Resumo!$C$5="ALIARE - AGB", Resumo!$C$5="SIMER",Resumo!$C$5="ALIARE - SOLUTION"), 'Aliare Integra Solution'!$A$32,'Aliare Integra ERP Terceiro'!$A$32) -> Cadastro básico - Cultura | K11: =IF(Resumo!$C$5="ALIARE - SOLUTION", 'Aliare Integra Solution'!$B$32, 'Aliare Integra ERP Terceiro'!$B$32) -> 1.12 Cultura
E12: Banco/Cooperativa | F12: Opcional | G12: 0.03125
E13: Área de Negócio | F13: Opcional | G13: 0.03125
D14: x | E14: Região | F14: Obrigatório | G14: 0.03125 | J14: =IF(OR(Resumo!$C$5="ALIARE - AGB", Resumo!$C$5="SIMER",Resumo!$C$5="ALIARE - SOLUTION"), _xlfn.CONCAT('Aliare Integra Solution'!$A$34,"+", 'Aliare Integra Solution'!$A$35), _xlfn.CONCAT('Aliare Integra ERP Terceiro'!$A$34,"+",'Aliare Integra ERP Terceiro'!$A$35)) -> Cadastro básico - Região+Cadastro básico - Região local | K14: =IF(Resumo!$C$5="ALIARE - SOLUTION", _xlfn.CONCAT('Aliare Integra Solution'!$B$34,"+", 'Aliare Integra Solution'!$B$35), _xlfn.CONCAT('Aliare Integra ERP Terceiro'!$B$34,"+",'Aliare Integra ERP Terceiro'!$B$35)) -> 1.19 Região+1.20 Região Local
C15: Parceiro | D15: x | E15: Propriedade | F15: Obrigatório | G15: 0.0625 | J15: =IF(OR(Resumo!$C$5="ALIARE - AGB", Resumo!$C$5="SIMER",Resumo!$C$5="ALIARE - SOLUTION"), 'Aliare Integra Solution'!$A$37,'Aliare Integra ERP Terceiro'!$A$37) -> Cadastro básico - Propriedade | K15: =IF(Resumo!$C$5="ALIARE - SOLUTION", 'Aliare Integra Solution'!$B$37, 'Aliare Integra ERP Terceiro'!$B$37) -> 1.22 Propriedade
D16: x | E16: Parceiro / Pessoa Física / Pessoa Jurídica | F16: Obrigatório | G16: 0.03125 | J16: =IF(OR(Resumo!$C$5="ALIARE - AGB", Resumo!$C$5="SIMER",Resumo!$C$5="ALIARE - SOLUTION"), _xlfn.CONCAT('Aliare Integra Solution'!$A$10,'Aliare Integra Solution'!$A$19,'Aliare Integra Solution'!$A$81), _xlfn.CONCAT('Aliare Integra ERP Terceiro'!$A$10,'Aliare Integra ERP Terceiro'!$A$19,'Aliare Integra ERP Terceiro'!$A$83)) -> Cadastro básico - Parceiro - Parte 1Cadastro básico - Pessoa física e jurídica - Fluxo 1Cadastro básico - Pessoa física complementar | K16: =IF(Resumo!$C$5="ALIARE - SOLUTION", 'Aliare Integra Solution'!$B$19, 'Aliare Integra ERP Terceiro'!$B$19) -> 1.16 Pessoa Física e 1.17 Pessoa Jurídica
E17: Times de Futebol | F17: Opcional | G17: 0.03125
E18: Tipos de Restrições do Local do Parceiro | F18: Opcional | G18: 0.03125
D19: x | E19: Contato | F19: Opcional | G19: 0.03125
E20: Cônjuge | F20: Opcional | G20: 0.03125
E21: Tipo parceiro | F21: Opcional | G21: 0.03125
E22: Classificação de Parceiro | F22: Opcional | G22: 0.03125
D23: x | E23: Notas | F23: Obrigatório | G23: 0.03125
D24: x | E24: Parceiro Superior | F24: Opcional | G24: 0.03125
E25: Grupo de Compra | F25: Opcional | G25: 0.041666667
D26: x | E26: Cadastro de Documentos | F26: Opcional | G26: 0.017361111
D27: x | E27: Local | F27: Obrigatório | G27: 0.03125 | I27: =IF(Resumo!$C$5="ALIARE - SOLUTION", 'Aliare Integra Solution'!$AC$12, 'Aliare Integra ERP Terceiro'!$AC$12) -> 0.125 | J27: =IF(OR(Resumo!$C$5="ALIARE - AGB", Resumo!$C$5="SIMER",Resumo!$C$5="ALIARE - SOLUTION"), _xlfn.CONCAT('Aliare Integra Solution'!$A$12,'Aliare Integra Solution'!$A$13,'Aliare Integra Solution'!$A$14), _xlfn.CONCAT('Aliare Integra ERP Terceiro'!$A$12,'Aliare Integra ERP Terceiro'!$A$13,'Aliare Integra ERP Terceiro'!$A$14)) -> Cadastro básico - Local - Entidade EmpresaCadastro básico - Local - Entidade ParceiroCadastro básico - Local - Entidade Propriedade | K27: =IF(Resumo!$C$5="ALIARE - SOLUTION", 'Aliare Integra Solution'!$B$12, 'Aliare Integra ERP Terceiro'!$B$12) -> 1.06 Local
D28: x | E28: Cadastro de Maquinário (Inventário de máquinas) | F28: Obrigatório | G28: 0.041666667
E29: Tipo Prioridade | F29: Opcional
C30: Lead | D30: x | E30: Origem do Lead, Cliente e Oportunidade | F30: Opcional | G30: 0.03125
D31: x | E31: Etapas do Lead | F31: Obrigatório | G31: 0.041666667
D32: x | E32: Tipo de Lead | F32: Opcional | G32: 0.03125
D33: x | E33: Lead | F33: Obrigatório | G33: 0.041666667
E34: Setor do Lead | F34: Opcional | G34: 0.03125
C35: Usuário | D35: x | E35: Usuário x Classe / Classe x Usuário | F35: Opcional | G35: 0.020833333
D36: x | E36: Usuário (Dados Gerais) | F36: Opcional | G36: 0.020833333
D37: x | E37: Empresa | F37: Obrigatório | G37: 0.020833333
D38: x | E38: Parceiro | F38: Obrigatório | G38: 0.020833333 | J38: =IF(OR(Resumo!$C$5="ALIARE - AGB", Resumo!$C$5="SIMER",Resumo!$C$5="ALIARE - SOLUTION"), 'Aliare Integra Solution'!$A$28,'Aliare Integra ERP Terceiro'!$A$28) -> Cadastro básico - Usuário empresa, filial e parceiro | K38: =IF(Resumo!$C$5="ALIARE - SOLUTION", _xlfn.CONCAT('Aliare Integra Solution'!$B$28,"+", 'Aliare Integra Solution'!$B$29), _xlfn.CONCAT('Aliare Integra ERP Terceiro'!$B$29,"+",'Aliare Integra ERP Terceiro'!$B$30)) -> 1.28 Usuário Filial+1.29 Usuário Empresa
D39: x | E39: Filial | F39: Obrigatório | G39: 0.020833333
D40: x | E40: Copiar Dados de Usuário | F40: Obrigatório | G40: 0.020833333
D41: x | E41: Produto/Classe de Produto | F41: Opcional | G41: 0.03125
D42: x | E42: Região | F42: Obrigatório | G42: 0.020833333
E43: Veículos | F43: Opcional | G43: 0.020833333 | J43: =IF(OR(Resumo!$C$5="ALIARE - AGB", Resumo!$C$5="SIMER",Resumo!$C$5="ALIARE - SOLUTION"), 'Aliare Integra Solution'!$A$46,'Aliare Integra ERP Terceiro'!$A$46) -> Cadastro básico - Veiculo | K43: =IF(Resumo!$C$5="ALIARE - SOLUTION", 'Aliare Integra Solution'!$B$46, 'Aliare Integra ERP Terceiro'!$B$46) -> 1.29 Veículo
E44: Locais | F44: Opcional | G44: 0.020833333
E45: Área de Negócio | F45: Opcional | G45: 0.020833333
E46: Viagem | F46: Opcional | G46: 0.020833333
E47: Despesa de Viagem | F47: Opcional | G47: 0.020833333
E48: Centro de Custo | F48: Opcional | G48: 0.020833333
C49: Área de Atuação | D49: x | E49: Área Atuação - Filial | F49: Opcional | G49: 0.03125
D50: x | E50: Área de Atuação - Usuário | F50: Opcional | G50: 0.03125
C51: Veículo | E51: Combustível | F51: Opcional | G51: 0.020833333
E52: Tipos de Veículos | F52: Obrigatório | G52: 0.020833333
C53: Produto | E53: Embalagem | F53: Opcional, pode ser necessário
D54: x | E54: Classe de Produto | F54: Obrigatório | G54: 0.03125 | J54: =IF(OR(Resumo!$C$5="ALIARE - AGB", Resumo!$C$5="SIMER",Resumo!$C$5="ALIARE - SOLUTION"), 'Aliare Integra Solution'!$A$23,'Aliare Integra ERP Terceiro'!$A$23) -> Cadastro básico - Classe de produto | K54: =IF(Resumo!$C$5="ALIARE - SOLUTION", 'Aliare Integra Solution'!$B$23, 'Aliare Integra ERP Terceiro'!$B$23) -> 1.09 Classe de Produto
D55: x | E55: Produto | F55: Obrigatório | G55: 0.041666667 | I55: =IF(Resumo!$C$5="ALIARE - SOLUTION", 'Aliare Integra Solution'!$AC$22, 'Aliare Integra ERP Terceiro'!$AC$22) -> 0.125 | J55: =IF(OR(Resumo!$C$5="ALIARE - AGB", Resumo!$C$5="SIMER",Resumo!$C$5="ALIARE - SOLUTION"), 'Aliare Integra Solution'!$A$22,'Aliare Integra ERP Terceiro'!$A$22) -> Cadastro básico - Produto e produto classe | K55: =IF(Resumo!$C$5="ALIARE - SOLUTION", 'Aliare Integra Solution'!$B$22, 'Aliare Integra ERP Terceiro'!$B$22) -> 1.08 Produto e 1.10 Produto Classe
E56: Pesquisa Produtos Concorrentes | F56: Validar Jane
E57: Categoria de Produtos | F57: Opcional | G57: 0.020833333
E58: Categorização de Produtos | F58: Opcional | G58: 0.020833333
E59: Classificação de Produtos | F59: Opcional | G59: 0.020833333
E60: Incompatibilidade de Produtos | F60: Validar Jane
E61: Linha do Produto | F61: Validar Jane
E62: Tipo de Situação do Produto | F62: Validar Jane
E63: Levantamento Produtos Concorrentes | F63: Validar Jane
D64: x | E64: Fabricante/Registrante | F64: Opcional | G64: 0.020833333
E65: Indicador Contábil | F65: Validar Jane
E66: Grupo Usina | F66: Validar Jane
E67: Operadoras | F67: Validar Jane
E68: Situação Bem | F68: Validar Jane
C69: Relatórios | D69: x | E69: Informações do Parceiro | F69: Opcional | G69: 0.020833333
E70: Dados DAP | F70: Opcional | G70: 0.020833333
E71: Exportação de Localizações | F71: Opcional | G71: 0.020833333
D72: x | E72: Aniversariantes | F72: Obrigatório | G72: 0.020833333
E73: Relatório de Utilização de Dados | F73: Opcional | G73: 0.020833333
D74: x | E74: Localização de Parceiro | F74: Opcional | G74: 0.020833333
E75: Tipo de Parceiro | F75: Opcional | G75: 0.020833333
E76: Grupo de Compra | F76: Opcional | G76: 0.020833333
D77: x | E77: Propriedades Por Profissional | F77: Opcional | G77: 0.020833333
D78: x | E78: Parceiro Por Profissional | F78: Opcional | G78: 0.020833333
D79: x | E79: Clima | F79: Obrigatório | G79: 0.020833333
E80: Permissão de Localização do Aplicativo | F80: Opcional | G80: 0.020833333
D81: x | E81: Área Atuação - Filial | F81: Opcional | G81: 0.020833333
E82: Croqui de Propriedade | F82: Opcional | G82: 0.020833333
D83: x | E83: Utilização da Aplicação | F83: Opcional | G83: 0.020833333
C84: Configuradores | D84: x | E84: Agendador de Tarefas | F84: Obrigatório | G84: 0.013888889
D85: x | E85: PropertiesTAG | F85: Obrigatório | G85: 0.013888889
D86: x | E86: Gestão de Consentimento LGPD | F86: Obrigatório | G86: 0.020833333
D87: x | E87: Solicitação do Direito de Esquecimento | F87: Obrigatório | G87: 0.020833333
D88: x | E88: Geral | F88: Obrigatório | G88: 0.020833333
E89: Grupo de Usuário | F89: Opcional | G89: 0.020833333
D90: x | E90: Jornada de trabalho do usuário | F90: Obrigatório | G90: 0.017361111
D91: x | E91: Configurador de Licenciamento e Licenciamento de Usuários | F91: Obrigatório | G91: 0.020833333
D92: x | E92: Usuário Hierarquia | F92: Obrigatório | G92: 0.03125
E93: Bloqueio de Acesso | F93: Opcional | G93: 0.017361111
D94: x | E94: Configurador de Área de atuação - Usuário | F94: Opcional | G94: 0.017361111
D95: x | E95: Painel Inicial | F95: Obrigatório | G95: 0.020833333
E96: Configurador de Grupo de Compra | F96: Opcional | G96: 0.020833333
D97: x | E97: Contato | F97: Opcional | G97: 0.020833333
D98: x | E98: Croqui | F98: Opcional | G98: 0.017361111
D99: x | E99: Configurador de Lead | F99: Opcional | G99: 0.020833333
B100: CRM - MM - Registro de Visita | G100: =ROUNDUP(IF($A$101="x", SUMIF($D$101:$D$125,"x",$G$101:$G$125) * 24, 0),0) -> 0 | I100: =ROUNDUP(IF($A$101="x",SUMIF($D$101:$D$125,"x",$I$101:$I$125)*24,0),0) -> 0 | L100: =IF(A101="x",SUM(L101:L125)*24 + IF(Resumo!C7 = "SIM",SUM(L101:L125)*24*0.3,0),0) -> 0 | M100: =IF(D109="x",(($G$100-8.25)*0.1592),$G$100*0.1592) -> -1.3134 | N100: =(($G$100-$L$100)*0.1802) + IF(Resumo!$C$7 = "SIM",((($G$100-$L$100)*0.1802)*0.3),0) -> 0 | O100: =($G$100-$L$100)*0.2402 -> 0 | P100: =(($G$100-$L100)*0.1802) + IF(Resumo!$C$7 = "SIM",(($G$100-$L$100)*0.1802)*0.3,0) -> 0 | Q100: =(($G$100-$L$100)*0.2402)*Resumo!P9 -> 0 | R100: =$G$100*0 -> 0 | S100: 0 | Y100: =SUM(Q100:X100) -> 0
...

Sheet Cálculo do AFV (configuração)
B1: =SUM(B2:B37) -> 43.25
A2: tipo de negociação | B2: 1
A3: configurador de tipo de negociação | B3: 2
A4: Configurador geral de pedido | B4: 0.5
A5: Campanha de troca | B5: 1
A6: Campanha de oferta | B6: 1
A7: Cota | B7: 1.5
A8: Frete | B8: 1.5
A9: Comissão | B9: 1
A10: Avalista | B10: 1
A11: Acompanhamento do pedido; | B11: 2
A12: Limite de crédito | B12: 0.5
A13: Estoque | B13: 1
A14: tipo de documento de cobrança | B14: 0.75
A15: Configuração AFV Manager | C15: 8 | D15: poderá ser reduzido
A16: Cadastro de impostos de troca | B16: 1.5
A17: Configurador de margem | B17: 1
A18: Semáforo | B18: 1.5
A19: Exportação de pedido | B19: 8
A20: Avaliação de máquina usada | B20: 1
A21: Conversor de moedas | B21: 1
A22: Analítico | B22: 1.5
A23: Regra de aprovação de pedido | B23: 3
A24: Cadastro de impostos ICMS | B24: 2
A25: Configuração de usuário | B25: 1
A26: Consulta de preço e estoque | B26: 1.5
A27: Títulos | B27: 0.5
A28: Ordem de Carregamento | B28: 2
A29: Substituição de itens | B29: 2 | D29: não será mais preciso fazer com o Aliare Integra, tendo em vista que esse recurso é permitido fazer no AGB
A30: Preço Exceção | B30: 1

Sheet Aliare Integra Solution
H1: =Resumo!$A15 -> x | I1: =Resumo!$A16 -> 0 | J1: =Resumo!#REF! -> #REF! | K1: =Resumo!#REF! -> #REF! | L1: =Resumo!#REF! -> #REF! | M1: =Resumo!A17 -> 0 | N1: =Resumo!A18 -> 0 | O1: =Resumo!A19 -> 0 | P1: =Resumo!#REF! -> #REF! | Q1: =Resumo!A20 -> 0 | R1: =Resumo!#REF! -> #REF! | S1: =Resumo!A21 -> 0 | T1: =Resumo!A22 -> 0 | U1: =Resumo!#REF! -> #REF! | V1: =Resumo!A23 -> x | W1: =Resumo!A24 -> 0 | X1: =Resumo!A25 -> 0 | Y1: =Resumo!#REF! -> #REF! | Z1: =Resumo!A26 -> 0 | AA1: =Resumo!A27 -> 0 | AB1: =Resumo!#REF! -> #REF!
A2: Fluxos | B2: Tabela | C2: Tipo | D2: Cofig. Integração AGB | E2: Teste interno, carga inicial | F2: Apoio a Validação / homologação e produção AGB | G2: Validação / homologação AGB | H2: CRM - MM - Funcionalidades Fundamentais | I2: CRM - MM - Registro de Visita | J2: CRM - MM - Planejamento da Consultoria Agronômica | K2: CRM - MM - Campos Demonstrativos | L2: CRM - MM - Consulta Preço e Estoque à Campo | M2: CRM - MM - Potencial & Metas | N2: CRM - MM - Segmentação | O2: CRM - MM - Previsão de Vendas | P2: CRM - MM - MarketShare | Q2: CRM - MM - Analise de Vendas | R2: CRM - MM - Escoamento de produtos | S2: CRM - MM - Potencial Maquinas | T2: CRM - MM - Chamados | U2: CRM - MM - Questionário de Pós Venda | V2: CRM - MM - Força de Vendas | W2: CRM - MM - Viagem | X2: CRM - MM - Funil de Vendas | Y2: CRM - MM - Levantamento de Rebanho | Z2: CRM - MM - Proposta de Crédito | AA2: CRM - MM - Ordem de Serviço | AB2: CRM - MM - Gestão de Eventos | AC2: Aliare Integra | AD2: CeS
B3: Todos os cadastros básicos | C3: **Sempre | D3: 0 | H3: SIM | I3: SIM | J3: SIM | K3: SIM | L3: SIM | M3: SIM | N3: SIM | O3: SIM | P3: SIM | Q3: SIM | R3: SIM | S3: SIM | T3: SIM | U3: SIM | V3: SIM | W3: SIM | X3: SIM | Y3: SIM | Z3: SIM | AA3: SIM | AB3: SIM | AC3: =IF(COUNTIFS($H$1:$AB$1,"x",H3:AB3,"SIM")>0,(D3+E3+F3),0) -> 0 | AD3: =IF(COUNTIFS($H$1:$AB$1,"x",H3:AB3,"SIM")>0,G3,0) -> 0 | AE3: =COUNTIFS(H3:AB3,"SIM") -> 21
B4: Todas as movimentações financeiras | C4: **Sempre | D4: 0 | H4: SIM | I4: SIM | J4: SIM | K4: SIM | L4: SIM | M4: SIM | N4: SIM | O4: SIM | P4: SIM | Q4: SIM | R4: SIM | S4: SIM | T4: SIM | U4: SIM | V4: SIM | W4: SIM | X4: SIM | Y4: SIM | Z4: SIM | AA4: SIM | AB4: SIM | AC4: =IF(COUNTIFS($H$1:$AB$1,"x",H4:AB4,"SIM")>0,(D4+E4+F4),0) -> 0 | AD4: =IF(COUNTIFS($H$1:$AB$1,"x",H4:AB4,"SIM")>0,G4,0) -> 0 | AE4: =COUNTIFS(H4:AB4,"SIM") -> 21
B5: Todos os fluxos de força de venda | C5: **Sempre | D5: 0 | H5: SIM | I5: SIM | J5: SIM | K5: SIM | L5: SIM | M5: SIM | N5: SIM | O5: SIM | P5: SIM | Q5: SIM | R5: SIM | S5: SIM | T5: SIM | U5: SIM | V5: SIM | W5: SIM | X5: SIM | Y5: SIM | Z5: SIM | AA5: SIM | AB5: SIM | AC5: =IF(COUNTIFS($H$1:$AB$1,"x",H5:AB5,"SIM")>0,(D5+E5+F5),0) -> 0 | AD5: =IF(COUNTIFS($H$1:$AB$1,"x",H5:AB5,"SIM")>0,G5,0) -> 0 | AE5: =COUNTIFS(H5:AB5,"SIM") -> 21
A6: Cadastro básico - País, Estado e Cidade | B6: 1.01 País | C6: **Sempre | D6: 0.0069444444 | E6: 0.020833333 | F6: 0 | G6: 0.020833333 | H6: SIM | I6: SIM | J6: SIM | K6: SIM | L6: SIM | M6: SIM | N6: SIM | O6: SIM | P6: SIM | Q6: SIM | R6: SIM | S6: SIM | T6: SIM | U6: SIM | V6: SIM | W6: SIM | X6: SIM | Y6: SIM | Z6: SIM | AA6: SIM | AB6: SIM | AC6: =IF(COUNTIFS($H$1:$AB$1,"x",H6:AB6,"SIM")>0,(D6+E6+F6),0) -> 0.027777778 | AD6: =IF(COUNTIFS($H$1:$AB$1,"x",H6:AB6,"SIM")>0,G6,0) -> 0.020833333 | AE6: =COUNTIFS(H6:AB6,"SIM") -> 21
B7: 1.02 Unidade Federativa | C7: **Sempre | H7: SIM | I7: SIM | J7: SIM | K7: SIM | L7: SIM | M7: SIM | N7: SIM | O7: SIM | P7: SIM | Q7: SIM | R7: SIM | S7: SIM | T7: SIM | U7: SIM | V7: SIM | W7: SIM | X7: SIM | Y7: SIM | Z7: SIM | AA7: SIM | AB7: SIM | AC7: =IF(COUNTIFS($H$1:$AB$1,"x",H7:AB7,"SIM")>0,(D7+E7+F7),0) -> 0 | AD7: =IF(COUNTIFS($H$1:$AB$1,"x",H7:AB7,"SIM")>0,G7,0) -> 0 | AE7: =COUNTIFS(H7:AB7,"SIM") -> 21
B8: 1.03 Cidade | C8: **Sempre | H8: SIM | I8: SIM | J8: SIM | K8: SIM | L8: SIM | M8: SIM | N8: SIM | O8: SIM | P8: SIM | Q8: SIM | R8: SIM | S8: SIM | T8: SIM | U8: SIM | V8: SIM | W8: SIM | X8: SIM | Y8: SIM | Z8: SIM | AA8: SIM | AB8: SIM | AC8: =IF(COUNTIFS($H$1:$AB$1,"x",H8:AB8,"SIM")>0,(D8+E8+F8),0) -> 0 | AD8: =IF(COUNTIFS($H$1:$AB$1,"x",H8:AB8,"SIM")>0,G8,0) -> 0 | AE8: =COUNTIFS(H8:AB8,"SIM") -> 21
A9: Cadastro básico - Unidade de medida | B9: 1.04 Unidade de Medida | C9: **Sempre | D9: 0.0069444444 | E9: 0.0069444444 | F9: 0 | G9: 0.010416667 | H9: SIM | I9: SIM | J9: SIM | K9: SIM | L9: SIM | M9: SIM | N9: SIM | O9: SIM | P9: SIM | Q9: SIM | R9: SIM | S9: SIM | T9: SIM | U9: SIM | V9: SIM | W9: SIM | X9: SIM | Y9: SIM | Z9: SIM | AA9: SIM | AB9: SIM | AC9: =IF(COUNTIFS($H$1:$AB$1,"x",H9:AB9,"SIM")>0,(D9+E9+F9),0) -> 0.013888889 | AD9: =IF(COUNTIFS($H$1:$AB$1,"x",H9:AB9,"SIM")>0,G9,0) -> 0.010416667 | AE9: =COUNTIFS(H9:AB9,"SIM") -> 21
A10: Cadastro básico - Parceiro - Parte 1 | B10: 1.05 Parceiro | C10: **Sempre | D10: 0.09375 | E10: 0.020833333 | F10: 0.020833333 | G10: 0.020833333 | H10: SIM | I10: SIM | J10: SIM | K10: SIM | L10: SIM | M10: SIM | N10: SIM | O10: SIM | P10: SIM | Q10: SIM | R10: SIM | S10: SIM | T10: SIM | U10: SIM | V10: SIM | W10: SIM | X10: SIM | Y10: SIM | Z10: SIM | AA10: SIM | AB10: SIM | AC10: =IF(COUNTIFS($H$1:$AB$1,"x",H10:AB10,"SIM")>0,(D10+E10+F10),0) -> 0.13541667 | AD10: =IF(COUNTIFS($H$1:$AB$1,"x",H10:AB10,"SIM")>0,G10,0) -> 0.020833333 | AE10: =COUNTIFS(H10:AB10,"SIM") -> 21
A11: Cadastro básico - Parceiro - Parte 2 | H11: SIM | I11: SIM | J11: SIM | K11: SIM | L11: SIM | M11: SIM | N11: SIM | O11: SIM | P11: SIM | Q11: SIM | R11: SIM | S11: SIM | T11: SIM | U11: SIM | V11: SIM | W11: SIM | X11: SIM | Y11: SIM | Z11: SIM | AA11: SIM | AB11: SIM | AC11: =IF(COUNTIFS($H$1:$AB$1,"x",H11:AB11,"SIM")>0,(D11+E11+F11),0) -> 0 | AD11: =IF(COUNTIFS($H$1:$AB$1,"x",H11:AB11,"SIM")>0,G11,0) -> 0 | AE11: =COUNTIFS(H11:AB11,"SIM") -> 21
A12: Cadastro básico - Local - Entidade Empresa | B12: 1.06 Local | C12: **Sempre | D12: 0.125 | E12: 0 | F12: 0 | G12: 0.020833333 | H12: SIM | I12: SIM | J12: SIM | K12: SIM | L12: SIM | M12: SIM | N12: SIM | O12: SIM | P12: SIM | Q12: SIM | R12: SIM | S12: SIM | T12: SIM | U12: SIM | V12: SIM | W12: SIM | X12: SIM | Y12: SIM | Z12: SIM | AA12: SIM | AB12: SIM | AC12: =IF(COUNTIFS($H$1:$AB$1,"x",H12:AB12,"SIM")>0,(D12+E12+F12),0) -> 0.125 | AD12: =IF(COUNTIFS($H$1:$AB$1,"x",H12:AB12,"SIM")>0,G12,0) -> 0.020833333 | AE12: =COUNTIFS(H12:AB12,"SIM") -> 21
A13: Cadastro básico - Local - Entidade Parceiro | H13: SIM | I13: SIM | J13: SIM | K13: SIM | L13: SIM | M13: SIM | N13: SIM | O13: SIM | P13: SIM | Q13: SIM | R13: SIM | S13: SIM | T13: SIM | U13: SIM | V13: SIM | W13: SIM | X13: SIM | Y13: SIM | Z13: SIM | AA13: SIM | AB13: SIM | AC13: =IF(COUNTIFS($H$1:$AB$1,"x",H13:AB13,"SIM")>0,(D13+E13+F13),0) -> 0 | AD13: =IF(COUNTIFS($H$1:$AB$1,"x",H13:AB13,"SIM")>0,G13,0) -> 0 | AE13: =COUNTIFS(H13:AB13,"SIM") -> 21
A14: Cadastro básico - Local - Entidade Propriedade | H14: SIM | I14: SIM | J14: SIM | K14: SIM | L14: SIM | M14: SIM | N14: SIM | O14: SIM | P14: SIM | Q14: SIM | R14: SIM | S14: SIM | T14: SIM | U14: SIM | V14: SIM | W14: SIM | X14: SIM | Y14: SIM | Z14: SIM | AA14: SIM | AB14: SIM | AC14: =IF(COUNTIFS($H$1:$AB$1,"x",H14:AB14,"SIM")>0,(D14+E14+F14),0) -> 0 | AD14: =IF(COUNTIFS($H$1:$AB$1,"x",H14:AB14,"SIM")>0,G14,0) -> 0 | AE14: =COUNTIFS(H14:AB14,"SIM") -> 21
A15: Cadastro básico – Empresa | B15: 1.14 Empresa | C15: **Sempre | D15: 0.0069444444 | E15: 0.0069444444 | F15: 0 | G15: 0.010416667 | H15: SIM | I15: SIM | J15: SIM | K15: SIM | L15: SIM | M15: SIM | N15: SIM | O15: SIM | P15: SIM | Q15: SIM | R15: SIM | S15: SIM | T15: SIM | U15: SIM | V15: SIM | W15: SIM | X15: SIM | Y15: SIM | Z15: SIM | AA15: SIM | AB15: SIM | AC15: =IF(COUNTIFS($H$1:$AB$1,"x",H15:AB15,"SIM")>0,(D15+E15+F15),0) -> 0.013888889 | AD15: =IF(COUNTIFS($H$1:$AB$1,"x",H15:AB15,"SIM")>0,G15,0) -> 0.010416667 | AE15: =COUNTIFS(H15:AB15,"SIM") -> 21
A16: Cadastro básico - Registrante | B16: 1.15.1 Registrante / Fabricante | C16: *Módulo | D16: 0.0069444444 | E16: 0.0069444444 | F16: 0.0069444444 | H16: NÃO | I16: SIM | J16: SIM | K16: SIM | L16: SIM | M16: SIM | N16: SIM | O16: SIM | P16: SIM | Q16: SIM | R16: SIM | S16: SIM | T16: SIM | U16: SIM | V16: SIM | W16: SIM | X16: SIM | Y16: SIM | Z16: SIM | AA16: SIM | AB16: SIM | AC16: =IF(COUNTIFS($H$1:$AB$1,"x",H16:AB16,"SIM")>0,(D16+E16+F16),0) -> 0.020833333 | AD16: =IF(COUNTIFS($H$1:$AB$1,"x",H16:AB16,"SIM")>0,G16,0) -> 0 | AE16: =COUNTIFS(H16:AB16,"SIM") -> 20
A17: Cadastro básico - Fornecedor | B17: 1.15.2 Fornecedor | C17: *Módulo | D17: 0.0069444444 | E17: 0.0069444444 | F17: 0.0069444444 | H17: NÃO | I17: SIM | J17: SIM | K17: SIM | L17: SIM | M17: SIM | N17: SIM | O17: SIM | P17: SIM | Q17: SIM | R17: SIM | S17: SIM | T17: SIM | U17: SIM | V17: SIM | W17: SIM | X17: SIM | Y17: SIM | Z17: SIM | AA17: SIM | AB17: SIM | AC17: =IF(COUNTIFS($H$1:$AB$1,"x",H17:AB17,"SIM")>0,(D17+E17+F17),0) -> 0.020833333 | AD17: =IF(COUNTIFS($H$1:$AB$1,"x",H17:AB17,"SIM")>0,G17,0) -> 0 | AE17: =COUNTIFS(H17:AB17,"SIM") -> 20
A18: Cadastro básico - Filial | B18: 1.15 Filial | C18: **Sempre | D18: 0.0069444444 | E18: 0.0069444444 | F18: 0.0069444444 | G18: 0.017361111 | H18: SIM | I18: SIM | J18: SIM | K18: SIM | L18: SIM | M18: SIM | N18: SIM | O18: SIM | P18: SIM | Q18: SIM | R18: SIM | S18: SIM | T18: SIM | U18: SIM | V18: SIM | W18: SIM | X18: SIM | Y18: SIM | Z18: SIM | AA18: SIM | AB18: SIM | AC18: =IF(COUNTIFS($H$1:$AB$1,"x",H18:AB18,"SIM")>0,(D18+E18+F18),0) -> 0.020833333 | AD18: =IF(COUNTIFS($H$1:$AB$1,"x",H18:AB18,"SIM")>0,G18,0) -> 0.017361111 | AE18: =COUNTIFS(H18:AB18,"SIM") -> 21
A19: Cadastro básico - Pessoa física e jurídica - Fluxo 1 | B19: 1.16 Pessoa Física e 1.17 Pessoa Jurídica | C19: **Sempre | D19: 0.013888889 | E19: 0.020833333 | F19: 0.027777778 | G19: 0.041666667 | H19: SIM | I19: SIM | J19: SIM | K19: SIM | L19: SIM | M19: SIM | N19: SIM | O19: SIM | P19: SIM | Q19: SIM | R19: SIM | S19: SIM | T19: SIM | U19: SIM | V19: SIM | W19: SIM | X19: SIM | Y19: SIM | Z19: SIM | AA19: SIM | AB19: SIM | AC19: =IF(COUNTIFS($H$1:$AB$1,"x",H19:AB19,"SIM")>0,(D19+E19+F19),0) -> 0.0625 | AD19: =IF(COUNTIFS($H$1:$AB$1,"x",H19:AB19,"SIM")>0,G19,0) -> 0.041666667 | AE19: =COUNTIFS(H19:AB19,"SIM") -> 21
A20: Cadastro básico - Pessoa física - Fluxo 2 | H20: SIM | I20: SIM | J20: SIM | K20: SIM | L20: SIM | M20: SIM | N20: SIM | O20: SIM | P20: SIM | Q20: SIM | R20: SIM | S20: SIM | T20: SIM | U20: SIM | V20: SIM | W20: SIM | X20: SIM | Y20: SIM | Z20: SIM | AA20: SIM | AB20: SIM | AC20: =IF(COUNTIFS($H$1:$AB$1,"x",H20:AB20,"SIM")>0,(D20+E20+F20),0) -> 0 | AD20: =IF(COUNTIFS($H$1:$AB$1,"x",H20:AB20,"SIM")>0,G20,0) -> 0 | AE20: =COUNTIFS(H20:AB20,"SIM") -> 21
A21: Cadastro básico - Pessoa jurídica - Fluxo 3 | AC21: =IF(COUNTIFS($H$1:$AB$1,"x",H21:AB21,"SIM")>0,(D21+E21+F21),0) -> 0 | AD21: =IF(COUNTIFS($H$1:$AB$1,"x",H21:AB21,"SIM")>0,G21,0) -> 0 | AE21: =COUNTIFS(H21:AB21,"SIM") -> 0
A22: Cadastro básico - Produto e produto classe | B22: 1.08 Produto e 1.10 Produto Classe | C22: *Módulo | D22: 0.125 | E22: 0 | F22: 0 | G22: 0.013888889 | H22: SIM | I22: SIM | J22: SIM | K22: SIM | L22: SIM | M22: SIM | N22: SIM | O22: SIM | P22: SIM | Q22: SIM | R22: SIM | S22: SIM | T22: SIM | U22: SIM | V22: SIM | W22: SIM | X22: SIM | Y22: SIM | Z22: SIM | AA22: SIM | AB22: SIM | AC22: =IF(COUNTIFS($H$1:$AB$1,"x",H22:AB22,"SIM")>0,(D22+E22+F22),0) -> 0.125 | AD22: =IF(COUNTIFS($H$1:$AB$1,"x",H22:AB22,"SIM")>0,G22,0) -> 0.013888889 | AE22: =COUNTIFS(H22:AB22,"SIM") -> 21
A23: Cadastro básico - Classe de produto | B23: 1.09 Classe de Produto | C23: *Módulo | D23: 0.0069444444 | E23: 0.017361111 | F23: 0.017361111 | G23: 0.013888889 | H23: NÃO | I23: SIM | J23: SIM | K23: SIM | L23: SIM | M23: SIM | N23: SIM | O23: SIM | P23: SIM | Q23: SIM | R23: SIM | S23: SIM | T23: SIM | U23: SIM | V23: SIM | W23: SIM | X23: SIM | Y23: SIM | Z23: SIM | AA23: SIM | AB23: SIM | AC23: =IF(COUNTIFS($H$1:$AB$1,"x",H23:AB23,"SIM")>0,(D23+E23+F23),0) -> 0.041666667 | AD23: =IF(COUNTIFS($H$1:$AB$1,"x",H23:AB23,"SIM")>0,G23,0) -> 0.013888889 | AE23: =COUNTIFS(H23:AB23,"SIM") -> 20
A24: Movimentação financeira - Local nota fiscal | B24: 3.1 Local Nota Fiscal | C24: *Módulo | D24: 0.45833333 | E24: 0 | F24: 0 | G24: 0.083333333 | H24: NÃO | I24: SIM | J24: NÃO | K24: NÃO | L24: NÃO | M24: SIM | N24: NÃO | O24: SIM | P24: SIM | Q24: SIM | R24: SIM | S24: NÃO | T24: NÃO | U24: SIM | V24: NÃO | W24: NÃO | X24: SIM | Y24: NÃO | Z24: NÃO | AA24: NÃO | AB24: NÃO | AC24: =IF(COUNTIFS($H$1:$AB$1,"x",H24:AB24,"SIM")>0,(D24+E24+F24),0) -> 0 | AD24: =IF(COUNTIFS($H$1:$AB$1,"x",H24:AB24,"SIM")>0,G24,0) -> 0 | AE24: =COUNTIFS(H24:AB24,"SIM") -> 8
A25: Movimentação financeira - Faturamento mensal - Parte 1 | B25: 3.2 Pedidos em Carteira (Fat. Mensal) | C25: *Módulo | D25: 0 | E25: 0 | F25: 0 | G25: 0.16666667 | H25: NÃO | I25: NÃO | J25: NÃO | K25: NÃO | L25: NÃO | M25: SIM | N25: SIM | O25: SIM | P25: NÃO | Q25: SIM | R25: NÃO | S25: NÃO | T25: NÃO | U25: NÃO | V25: NÃO | W25: NÃO | X25: NÃO | Y25: NÃO | Z25: NÃO | AA25: NÃO | AB25: NÃO | AC25: =IF(COUNTIFS($H$1:$AB$1,"x",H25:AB25,"SIM")>0,(D25+E25+F25),0) -> 0 | AD25: =IF(COUNTIFS($H$1:$AB$1,"x",H25:AB25,"SIM")>0,G25,0) -> 0 | AE25: =COUNTIFS(H25:AB25,"SIM") -> 4
A26: Movimentação financeira - Faturamento mensal - Parte 2 | AC26: =IF(COUNTIFS($H$1:$AB$1,"x",H26:AB26,"SIM")>0,(D26+E26+F26),0) -> 0 | AD26: =IF(COUNTIFS($H$1:$AB$1,"x",H26:AB26,"SIM")>0,G26,0) -> 0 | AE26: =COUNTIFS(H26:AB26,"SIM") -> 0
A27: Cadastro básico - Usuários | B27: 1.11 Usuário | C27: *Qualifica | D27: 0.0069444444 | E27: 0.0069444444 | F27: 0 | G27: 0.0069444444 | H27: SIM | I27: SIM | J27: NÃO | K27: NÃO | L27: SIM | M27: NÃO | N27: NÃO | O27: NÃO | P27: NÃO | Q27: NÃO | R27: NÃO | S27: NÃO | T27: NÃO | U27: NÃO | V27: SIM | W27: NÃO | X27: NÃO | Y27: NÃO | Z27: NÃO | AA27: NÃO | AB27: NÃO | AC27: =IF(COUNTIFS($H$1:$AB$1,"x",H27:AB27,"SIM")>0,(D27+E27+F27),0) -> 0.013888889 | AD27: =IF(COUNTIFS($H$1:$AB$1,"x",H27:AB27,"SIM")>0,G27,0) -> 0.0069444444 | AE27: =COUNTIFS(H27:AB27,"SIM") -> 4
A28: Cadastro básico - Usuário empresa, filial e parceiro | B28: 1.28 Usuário Filial | C28: *Qualifica | D28: 0.010416667 | E28: 0.010416667 | F28: 0.0069444444 | G28: 0.020833333 | H28: SIM | I28: =$H$27 -> SIM | J28: NÃO | K28: NÃO | L28: SIM | M28: NÃO | N28: NÃO | O28: NÃO | P28: NÃO | Q28: NÃO | R28: NÃO | S28: NÃO | T28: NÃO | U28: NÃO | V28: SIM | W28: NÃO | X28: NÃO | Y28: NÃO | Z28: NÃO | AA28: NÃO | AB28: NÃO | AC28: =IF(COUNTIFS($H$1:$AB$1,"x",H28:AB28,"SIM")>0,(D28+E28+F28),0) -> 0.027777778 | AD28: =IF(COUNTIFS($H$1:$AB$1,"x",H28:AB28,"SIM")>0,G28,0) -> 0.020833333 | AE28: =COUNTIFS(H28:AB28,"SIM") -> 4
B29: 1.29 Usuário Empresa | C29: *Qualifica | H29: SIM | I29: =$H$27 -> SIM | J29: NÃO | K29: NÃO | L29: SIM | M29: NÃO | N29: NÃO | O29: NÃO | P29: NÃO | Q29: NÃO | R29: NÃO | S29: NÃO | T29: NÃO | U29: NÃO | V29: SIM | W29: NÃO | X29: NÃO | Y29: NÃO | Z29: NÃO | AA29: NÃO | AB29: NÃO | AC29: =IF(COUNTIFS($H$1:$AB$1,"x",H29:AB29,"SIM")>0,(D29+E29+F29),0) -> 0 | AD29: =IF(COUNTIFS($H$1:$AB$1,"x",H29:AB29,"SIM")>0,G29,0) -> 0 | AE29: =COUNTIFS(H29:AB29,"SIM") -> 4
B30: 1.28 Usuário Parceiro | C30: *Qualifica | H30: SIM | I30: =$H$27 -> SIM | J30: NÃO | K30: NÃO | L30: SIM | M30: NÃO | N30: NÃO | O30: NÃO | P30: NÃO | Q30: NÃO | R30: NÃO | S30: NÃO | T30: NÃO | U30: NÃO | V30: SIM | W30: NÃO | X30: NÃO | Y30: NÃO | Z30: NÃO | AA30: NÃO | AB30: NÃO | AC30: =IF(COUNTIFS($H$1:$AB$1,"x",H30:AB30,"SIM")>0,(D30+E30+F30),0) -> 0 | AD30: =IF(COUNTIFS($H$1:$AB$1,"x",H30:AB30,"SIM")>0,G30,0) -> 0 | AE30: =COUNTIFS(H30:AB30,"SIM") -> 4
B31: 1.27 Usuário Produto | C31: *Qualifica | H31: NÃO | I31: NÃO | J31: NÃO | K31: NÃO | L31: NÃO | M31: NÃO | N31: NÃO | O31: NÃO | P31: NÃO | Q31: NÃO | R31: NÃO | S31: NÃO | T31: NÃO | U31: NÃO | V31: NÃO | W31: NÃO | X31: NÃO | Y31: NÃO | Z31: NÃO | AA31: NÃO | AB31: NÃO | AC31: =IF(COUNTIFS($H$1:$AB$1,"x",H31:AB31,"SIM")>0,(D31+E31+F31),0) -> 0 | AD31: =IF(COUNTIFS($H$1:$AB$1,"x",H31:AB31,"SIM")>0,G31,0) -> 0 | AE31: =COUNTIFS(H31:AB31,"SIM") -> 0
A32: Cadastro básico - Cultura | B32: 1.12 Cultura | C32: *Qualifica | D32: 0.0069444444 | E32: 0.0069444444 | F32: 0 | G32: 0.0069444444 | H32: SIM | I32: SIM | J32: SIM | K32: SIM | L32: SIM | M32: SIM | N32: NÃO | O32: NÃO | P32: NÃO | Q32: NÃO | R32: NÃO | S32: NÃO | T32: NÃO | U32: NÃO | V32: SIM | W32: NÃO | X32: NÃO | Y32: NÃO | Z32: NÃO | AA32: NÃO | AB32: NÃO | AC32: =IF(COUNTIFS($H$1:$AB$1,"x",H32:AB32,"SIM")>0,(D32+E32+F32),0) -> 0.013888889 | AD32: =IF(COUNTIFS($H$1:$AB$1,"x",H32:AB32,"SIM")>0,G32,0) -> 0.0069444444 | AE32: =COUNTIFS(H32:AB32,"SIM") -> 7
A33: Cadastro básico - Safra | B33: 1.13 Safra | C33: *Qualifica | D33: 0.0069444444 | E33: 0.0069444444 | F33: 0 | G33: 0.0069444444 | H33: NÃO | I33: SIM | J33: SIM | K33: SIM | L33: SIM | M33: SIM | N33: NÃO | O33: NÃO | P33: NÃO | Q33: SIM | R33: NÃO | S33: NÃO | T33: NÃO | U33: NÃO | V33: SIM | W33: NÃO | X33: NÃO | Y33: NÃO | Z33: NÃO | AA33: NÃO | AB33: NÃO | AC33: =IF(COUNTIFS($H$1:$AB$1,"x",H33:AB33,"SIM")>0,(D33+E33+F33),0) -> 0.013888889 | AD33: =IF(COUNTIFS($H$1:$AB$1,"x",H33:AB33,"SIM")>0,G33,0) -> 0.0069444444 | AE33: =COUNTIFS(H33:AB33,"SIM") -> 7
A34: Cadastro básico - Região | B34: 1.19 Região | C34: *Qualifica | D34: 0.0069444444 | E34: 0.0069444444 | F34: 0 | G34: 0.0069444444 | H34: SIM | I34: SIM | J34: SIM | K34: SIM | L34: SIM | M34: SIM | N34: NÃO | O34: NÃO | P34: NÃO | Q34: NÃO | R34: NÃO | S34: NÃO | T34: NÃO | U34: NÃO | V34: SIM | W34: NÃO | X34: NÃO | Y34: NÃO | Z34: NÃO | AA34: NÃO | AB34: NÃO | AC34: =IF(COUNTIFS($H$1:$AB$1,"x",H34:AB34,"SIM")>0,(D34+E34+F34),0) -> 0.013888889 | AD34: =IF(COUNTIFS($H$1:$AB$1,"x",H34:AB34,"SIM")>0,G34,0) -> 0.0069444444 | AE34: =COUNTIFS(H34:AB34,"SIM") -> 7
A35: Cadastro básico - Região local | B35: 1.20 Região Local | C35: *Qualifica | D35: 0.0069444444 | E35: 0.0069444444 | F35: 0.0069444444 | G35: 0.0069444444 | H35: SIM | I35: SIM | J35: SIM | K35: SIM | L35: SIM | M35: SIM | N35: NÃO | O35: NÃO | P35: NÃO | Q35: NÃO | R35: NÃO | S35: NÃO | T35: NÃO | U35: NÃO | V35: SIM | W35: NÃO | X35: NÃO | Y35: NÃO | Z35: NÃO | AA35: NÃO | AB35: NÃO | AC35: =IF(COUNTIFS($H$1:$AB$1,"x",H35:AB35,"SIM")>0,(D35+E35+F35),0) -> 0.020833333 | AD35: =IF(COUNTIFS($H$1:$AB$1,"x",H35:AB35,"SIM")>0,G35,0) -> 0.0069444444 | AE35: =COUNTIFS(H35:AB35,"SIM") -> 7
A36: Cadastro básico - Usuário região | B36: 1.21 Usuário Região | C36: *Qualifica | D36: 0.0069444444 | E36: 0.0069444444 | F36: 0.0069444444 | G36: 0.0034722222 | H36: SIM | I36: SIM | J36: SIM | K36: SIM | L36: SIM | M36: SIM | N36: NÃO | O36: NÃO | P36: NÃO | Q36: NÃO | R36: NÃO | S36: NÃO | T36: NÃO | U36: NÃO | V36: SIM | W36: NÃO | X36: NÃO | Y36: NÃO | Z36: NÃO | AA36: NÃO | AB36: NÃO | AC36: =IF(COUNTIFS($H$1:$AB$1,"x",H36:AB36,"SIM")>0,(D36+E36+F36),0) -> 0.020833333 | AD36: =IF(COUNTIFS($H$1:$AB$1,"x",H36:AB36,"SIM")>0,G36,0) -> 0.0034722222 | AE36: =COUNTIFS(H36:AB36,"SIM") -> 7
A37: Cadastro básico - Propriedade | B37: 1.22 Propriedade | C37: *Qualifica | D37: 0.013888889 | E37: 0.013888889 | F37: 0 | G37: 0.020833333 | H37: SIM | I37: SIM | J37: SIM | K37: SIM | L37: NÃO | M37: SIM | N37: NÃO | O37: NÃO | P37: NÃO | Q37: NÃO | R37: NÃO | S37: NÃO | T37: NÃO | U37: NÃO | V37: NÃO | W37: NÃO | X37: NÃO | Y37: NÃO | Z37: NÃO | AA37: NÃO | AB37: NÃO | AC37: =IF(COUNTIFS($H$1:$AB$1,"x",H37:AB37,"SIM")>0,(D37+E37+F37),0) -> 0.027777778 | AD37: =IF(COUNTIFS($H$1:$AB$1,"x",H37:AB37,"SIM")>0,G37,0) -> 0.020833333 | AE37: =COUNTIFS(H37:AB37,"SIM") -> 5
A38: Cadastro básico - Vínculo imobiliário | B38: 1.23 Vin. Imob. | C38: *Qualifica | H38: SIM | I38: SIM | J38: SIM | K38: SIM | L38: NÃO | M38: SIM | N38: NÃO | O38: NÃO | P38: NÃO | Q38: NÃO | R38: NÃO | S38: NÃO | T38: NÃO | U38: NÃO | V38: NÃO | W38: NÃO | X38: NÃO | Y38: NÃO | Z38: NÃO | AA38: NÃO | AB38: NÃO | AC38: =IF(COUNTIFS($H$1:$AB$1,"x",H38:AB38,"SIM")>0,(D38+E38+F38),0) -> 0 | AD38: =IF(COUNTIFS($H$1:$AB$1,"x",H38:AB38,"SIM")>0,G38,0) -> 0 | AE38: =COUNTIFS(H38:AB38,"SIM") -> 5
A39: Cadastro básico - Posse | B39: 1.24 Posse | C39: *Qualifica | H39: SIM | I39: SIM | J39: SIM | K39: SIM | L39: NÃO | M39: SIM | N39: NÃO | O39: NÃO | P39: NÃO | Q39: NÃO | R39: NÃO | S39: NÃO | T39: NÃO | U39: NÃO | V39: NÃO | W39: NÃO | X39: NÃO | Y39: NÃO | Z39: NÃO | AA39: NÃO | AB39: NÃO | AC39: =IF(COUNTIFS($H$1:$AB$1,"x",H39:AB39,"SIM")>0,(D39+E39+F39),0) -> 0 | AD39: =IF(COUNTIFS($H$1:$AB$1,"x",H39:AB39,"SIM")>0,G39,0) -> 0 | AE39: =COUNTIFS(H39:AB39,"SIM") -> 5
A40: Cadastro básico - Arrendamento | B40: 1.25 Arrend. | C40: *Qualifica | H40: NÃO | I40: NÃO | J40: NÃO | K40: NÃO | L40: NÃO | M40: NÃO | N40: NÃO | O40: NÃO | P40: NÃO | Q40: NÃO | R40: NÃO | S40: NÃO | T40: NÃO | U40: NÃO | V40: NÃO | W40: NÃO | X40: NÃO | Y40: NÃO | Z40: NÃO | AA40: NÃO | AB40: NÃO | AC40: =IF(COUNTIFS($H$1:$AB$1,"x",H40:AB40,"SIM")>0,(D40+E40+F40),0) -> 0 | AD40: =IF(COUNTIFS($H$1:$AB$1,"x",H40:AB40,"SIM")>0,G40,0) -> 0 | AE40: =COUNTIFS(H40:AB40,"SIM") -> 0
B41: 1.26 Região Filial | C41: *Qualifica | H41: NÃO | I41: NÃO | J41: NÃO | K41: NÃO | L41: NÃO | M41: NÃO | N41: NÃO | O41: NÃO | P41: NÃO | Q41: NÃO | R41: NÃO | S41: NÃO | T41: NÃO | U41: NÃO | V41: NÃO | W41: NÃO | X41: NÃO | Y41: NÃO | Z41: NÃO | AA41: NÃO | AB41: NÃO | AC41: =IF(COUNTIFS($H$1:$AB$1,"x",H41:AB41,"SIM")>0,(D41+E41+F41),0) -> 0 | AD41: =IF(COUNTIFS($H$1:$AB$1,"x",H41:AB41,"SIM")>0,G41,0) -> 0 | AE41: =COUNTIFS(H41:AB41,"SIM") -> 0
A42: Cadastro básico - Tipo parceiro | B42: 1.33 Tipo Parceiro | C42: *Qualifica | D42: 0.0069444444 | E42: 0.010416667 | F42: 0.0069444444 | G42: 0.0069444444 | H42: SIM | I42: SIM | J42: NÃO | K42: NÃO | L42: NÃO | M42: NÃO | N42: NÃO | O42: NÃO | P42: NÃO | Q42: NÃO | R42: NÃO | S42: NÃO | T42: NÃO | U42: NÃO | V42: NÃO | W42: NÃO | X42: NÃO | Y42: NÃO | Z42: NÃO | AA42: NÃO | AB42: NÃO | AC42: =IF(COUNTIFS($H$1:$AB$1,"x",H42:AB42,"SIM")>0,(D42+E42+F42),0) -> 0.024305556 | AD42: =IF(COUNTIFS($H$1:$AB$1,"x",H42:AB42,"SIM")>0,G42,0) -> 0.0069444444 | AE42: =COUNTIFS(H42:AB42,"SIM") -> 2
A43: Cadastro básico - Parceiro tipo parceiro | B43: 1.34 Parceiro Tipo Parceiro | C43: *Qualifica | D43: 0.0069444444 | E43: 0.010416667 | F43: 0.0069444444 | G43: 0.0034722222 | H43: SIM | I43: =$J$58 -> NÃO | J43: NÃO | K43: NÃO | L43: NÃO | M43: NÃO | N43: NÃO | O43: NÃO | P43: NÃO | Q43: NÃO | R43: NÃO | S43: NÃO | T43: NÃO | U43: NÃO | V43: NÃO | W43: NÃO | X43: NÃO | Y43: NÃO | Z43: NÃO | AA43: NÃO | AB43: NÃO | AC43: =IF(COUNTIFS($H$1:$AB$1,"x",H43:AB43,"SIM")>0,(D43+E43+F43),0) -> 0.024305556 | AD43: =IF(COUNTIFS($H$1:$AB$1,"x",H43:AB43,"SIM")>0,G43,0) -> 0.0034722222 | AE43: =COUNTIFS(H43:AB43,"SIM") -> 1
A44: Cadastro básico - Estoque | B44: 3.4 Estoque | C44: *Qualifica | D44: 0.0069444444 | E44: 0.013888889 | F44: 0.013888889 | G44: 0.020833333 | H44: =$H$41 -> NÃO | I44: =$J$58 -> NÃO | J44: NÃO | K44: NÃO | L44: SIM | M44: NÃO | N44: NÃO | O44: NÃO | P44: NÃO | Q44: NÃO | R44: NÃO | S44: NÃO | T44: NÃO | U44: NÃO | V44: SIM | W44: NÃO | X44: NÃO | Y44: NÃO | Z44: NÃO | AA44: NÃO | AB44: NÃO | AC44: =IF(COUNTIFS($H$1:$AB$1,"x",H44:AB44,"SIM")>0,(D44+E44+F44),0) -> 0.034722222 | AD44: =IF(COUNTIFS($H$1:$AB$1,"x",H44:AB44,"SIM")>0,G44,0) -> 0.020833333 | AE44: =COUNTIFS(H44:AB44,"SIM") -> 2
B45: 3.10 Carga (Romaneios) | C45: *Qualifica | H45: =$H$41 -> NÃO | I45: NÃO | J45: NÃO | K45: NÃO | L45: NÃO | M45: NÃO | N45: NÃO | O45: NÃO | P45: NÃO | Q45: NÃO | R45: NÃO | S45: NÃO | T45: NÃO | U45: NÃO | V45: NÃO | W45: NÃO | X45: NÃO | Y45: NÃO | Z45: NÃO | AA45: NÃO | AB45: NÃO | AC45: =IF(COUNTIFS($H$1:$AB$1,"x",H45:AB45,"SIM")>0,(D45+E45+F45),0) -> 0 | AD45: =IF(COUNTIFS($H$1:$AB$1,"x",H45:AB45,"SIM")>0,G45,0) -> 0 | AE45: =COUNTIFS(H45:AB45,"SIM") -> 0
A46: Cadastro básico - Veiculo | B46: 1.29 Veículo | C46: *Qualifica | D46: 0.0069444444 | E46: 0.0069444444 | F46: 0 | G46: 0.010416667 | H46: =$H$41 -> NÃO | I46: NÃO | J46: NÃO | K46: NÃO | L46: NÃO | M46: NÃO | N46: NÃO | O46: NÃO | P46: NÃO | Q46: NÃO | R46: NÃO | S46: NÃO | T46: NÃO | U46: NÃO | V46: NÃO | W46: SIM | X46: NÃO | Y46: NÃO | Z46: NÃO | AA46: =$H$62 -> NÃO | AB46: NÃO | AC46: =IF(COUNTIFS($H$1:$AB$1,"x",H46:AB46,"SIM")>0,(D46+E46+F46),0) -> 0 | AD46: =IF(COUNTIFS($H$1:$AB$1,"x",H46:AB46,"SIM")>0,G46,0) -> 0 | AE46: =COUNTIFS(H46:AB46,"SIM") -> 1
B47: 1.30 Centro de Custo | C47: *Qualifica | H47: =$H$41 -> NÃO | I47: NÃO | J47: NÃO | K47: NÃO | L47: NÃO | M47: NÃO | N47: NÃO | O47: NÃO | P47: NÃO | Q47: NÃO | R47: NÃO | S47: NÃO | T47: NÃO | U47: NÃO | V47: NÃO | W47: NÃO | X47: NÃO | Y47: NÃO | Z47: NÃO | AA47: NÃO | AB47: NÃO | AC47: =IF(COUNTIFS($H$1:$AB$1,"x",H47:AB47,"SIM")>0,(D47+E47+F47),0) -> 0 | AD47: =IF(COUNTIFS($H$1:$AB$1,"x",H47:AB47,"SIM")>0,G47,0) -> 0 | AE47: =COUNTIFS(H47:AB47,"SIM") -> 0
B48: 1.31 Usuário Centro de Custo | C48: *Qualifica | H48: =$H$41 -> NÃO | I48: NÃO | J48: NÃO | K48: NÃO | L48: NÃO | M48: NÃO | N48: NÃO | O48: NÃO | P48: NÃO | Q48: NÃO | R48: NÃO | S48: NÃO | T48: NÃO | U48: NÃO | V48: NÃO | W48: NÃO | X48: NÃO | Y48: NÃO | Z48: NÃO | AA48: NÃO | AB48: NÃO | AC48: =IF(COUNTIFS($H$1:$AB$1,"x",H48:AB48,"SIM")>0,(D48+E48+F48),0) -> 0 | AD48: =IF(COUNTIFS($H$1:$AB$1,"x",H48:AB48,"SIM")>0,G48,0) -> 0 | AE48: =COUNTIFS(H48:AB48,"SIM") -> 0
B49: 1.32 Despesa | C49: *Qualifica | H49: =$H$41 -> NÃO | I49: NÃO | J49: NÃO | K49: NÃO | L49: NÃO | M49: NÃO | N49: NÃO | O49: NÃO | P49: NÃO | Q49: NÃO | R49: NÃO | S49: NÃO | T49: NÃO | U49: NÃO | V49: NÃO | W49: NÃO | X49: NÃO | Y49: NÃO | Z49: NÃO | AA49: NÃO | AB49: NÃO | AC49: =IF(COUNTIFS($H$1:$AB$1,"x",H49:AB49,"SIM")>0,(D49+E49+F49),0) -> 0 | AD49: =IF(COUNTIFS($H$1:$AB$1,"x",H49:AB49,"SIM")>0,G49,0) -> 0 | AE49: =COUNTIFS(H49:AB49,"SIM") -> 0
B50: 4.3 Exportação de Viagem | C50: *Qualifica | H50: =$H$41 -> NÃO | I50: NÃO | J50: NÃO | K50: NÃO | L50: NÃO | M50: NÃO | N50: NÃO | O50: NÃO | P50: NÃO | Q50: NÃO | R50: NÃO | S50: NÃO | T50: NÃO | U50: NÃO | V50: NÃO | W50: NÃO | X50: NÃO | Y50: NÃO | Z50: NÃO | AA50: NÃO | AB50: NÃO | AC50: =IF(COUNTIFS($H$1:$AB$1,"x",H50:AB50,"SIM")>0,(D50+E50+F50),0) -> 0 | AD50: =IF(COUNTIFS($H$1:$AB$1,"x",H50:AB50,"SIM")>0,G50,0) -> 0 | AE50: =COUNTIFS(H50:AB50,"SIM") -> 0
B51: 4.4 Rastreador Veículo | C51: *Qualifica | H51: =$H$41 -> NÃO | I51: NÃO | J51: NÃO | K51: NÃO | L51: NÃO | M51: NÃO | N51: NÃO | O51: NÃO | P51: NÃO | Q51: NÃO | R51: NÃO | S51: NÃO | T51: NÃO | U51: NÃO | V51: NÃO | W51: NÃO | X51: NÃO | Y51: NÃO | Z51: NÃO | AA51: NÃO | AB51: NÃO | AC51: =IF(COUNTIFS($H$1:$AB$1,"x",H51:AB51,"SIM")>0,(D51+E51+F51),0) -> 0 | AD51: =IF(COUNTIFS($H$1:$AB$1,"x",H51:AB51,"SIM")>0,G51,0) -> 0 | AE51: =COUNTIFS(H51:AB51,"SIM") -> 0
A52: Cadastro básico - Silo | B52: 1.37 Silo | C52: *Qualifica | D52: 0.0069444444 | E52: 0.0069444444 | F52: 0 | G52: 0.0069444444 | H52: =$H$41 -> NÃO | I52: NÃO | J52: NÃO | K52: NÃO | L52: NÃO | M52: NÃO | N52: NÃO | O52: NÃO | P52: NÃO | Q52: NÃO | R52: NÃO | S52: NÃO | T52: NÃO | U52: NÃO | V52: SIM | W52: NÃO | X52: NÃO | Y52: NÃO | Z52: NÃO | AA52: NÃO | AB52: NÃO | AC52: =IF(COUNTIFS($H$1:$AB$1,"x",H52:AB52,"SIM")>0,(D52+E52+F52),0) -> 0.013888889 | AD52: =IF(COUNTIFS($H$1:$AB$1,"x",H52:AB52,"SIM")>0,G52,0) -> 0.0069444444 | AE52: =COUNTIFS(H52:AB52,"SIM") -> 1
B53: 1.39 Preço Produto | C53: *Qualifica | H53: =$H$41 -> NÃO | I53: NÃO | J53: NÃO | K53: NÃO | L53: NÃO | M53: NÃO | N53: NÃO | O53: NÃO | P53: NÃO | Q53: NÃO | R53: NÃO | S53: NÃO | T53: NÃO | U53: NÃO | V53: =$I$63 -> NÃO | W53: NÃO | X53: NÃO | Y53: NÃO | Z53: NÃO | AA53: NÃO | AB53: NÃO | AC53: =IF(COUNTIFS($H$1:$AB$1,"x",H53:AB53,"SIM")>0,(D53+E53+F53),0) -> 0 | AD53: =IF(COUNTIFS($H$1:$AB$1,"x",H53:AB53,"SIM")>0,G53,0) -> 0 | AE53: =COUNTIFS(H53:AB53,"SIM") -> 0
B54: 1.60 Segmentação | C54: *Qualifica | H54: =$H$41 -> NÃO | I54: NÃO | J54: NÃO | K54: NÃO | L54: NÃO | M54: NÃO | N54: NÃO | O54: NÃO | P54: NÃO | Q54: NÃO | R54: NÃO | S54: NÃO | T54: NÃO | U54: NÃO | V54: =$I$63 -> NÃO | W54: NÃO | X54: NÃO | Y54: NÃO | Z54: NÃO | AA54: NÃO | AB54: NÃO | AC54: =IF(COUNTIFS($H$1:$AB$1,"x",H54:AB54,"SIM")>0,(D54+E54+F54),0) -> 0 | AD54: =IF(COUNTIFS($H$1:$AB$1,"x",H54:AB54,"SIM")>0,G54,0) -> 0 | AE54: =COUNTIFS(H54:AB54,"SIM") -> 0
B55: 3.3 Metas de Venda | C55: *Qualifica | H55: =$H$41 -> NÃO | I55: NÃO | J55: NÃO | K55: NÃO | L55: NÃO | M55: NÃO | N55: NÃO | O55: NÃO | P55: NÃO | Q55: NÃO | R55: NÃO | S55: NÃO | T55: NÃO | U55: NÃO | V55: =$I$63 -> NÃO | W55: NÃO | X55: NÃO | Y55: NÃO | Z55: NÃO | AA55: NÃO | AB55: NÃO | AC55: =IF(COUNTIFS($H$1:$AB$1,"x",H55:AB55,"SIM")>0,(D55+E55+F55),0) -> 0 | AD55: =IF(COUNTIFS($H$1:$AB$1,"x",H55:AB55,"SIM")>0,G55,0) -> 0 | AE55: =COUNTIFS(H55:AB55,"SIM") -> 0
A56: Movimentação financeira - Histórico de aquisição de produtos | B56: 3.8 Histórico Aquisição Produtos | C56: *Qualifica | D56: 0 | E56: 0 | F56: 0 | G56: 0.020833333 | H56: =$H$41 -> NÃO | I56: NÃO | J56: NÃO | K56: NÃO | L56: NÃO | M56: NÃO | N56: NÃO | O56: NÃO | P56: NÃO | Q56: NÃO | R56: NÃO | S56: NÃO | T56: NÃO | U56: NÃO | V56: SIM | W56: NÃO | X56: NÃO | Y56: NÃO | Z56: NÃO | AA56: NÃO | AB56: NÃO | AC56: =IF(COUNTIFS($H$1:$AB$1,"x",H56:AB56,"SIM")>0,(D56+E56+F56),0) -> 0 | AD56: =IF(COUNTIFS($H$1:$AB$1,"x",H56:AB56,"SIM")>0,G56,0) -> 0.020833333 | AE56: =COUNTIFS(H56:AB56,"SIM") -> 1
B57: 3.9 Histórico Produção Entregue | C57: *Qualifica | H57: =$H$41 -> NÃO | I57: NÃO | J57: NÃO | K57: NÃO | L57: NÃO | M57: NÃO | N57: NÃO | O57: NÃO | P57: NÃO | Q57: NÃO | R57: NÃO | S57: NÃO | T57: NÃO | U57: NÃO | V57: =$I$63 -> NÃO | W57: NÃO | X57: NÃO | Y57: NÃO | Z57: NÃO | AA57: NÃO | AB57: NÃO | AC57: =IF(COUNTIFS($H$1:$AB$1,"x",H57:AB57,"SIM")>0,(D57+E57+F57),0) -> 0 | AD57: =IF(COUNTIFS($H$1:$AB$1,"x",H57:AB57,"SIM")>0,G57,0) -> 0 | AE57: =COUNTIFS(H57:AB57,"SIM") -> 0
A58: Movimentação financeira - Resumo financeiro do cliente | B58: 3.11 PCResumoFinanceiro + 3.12 PCResumoTitulos | C58: *Qualifica | D58: 0.041666667 | E58: 0 | F58: 0 | G58: 0.083333333 | H58: =$H$41 -> NÃO | I58: NÃO | J58: NÃO | K58: NÃO | L58: NÃO | M58: NÃO | N58: NÃO | O58: NÃO | P58: NÃO | Q58: NÃO | R58: NÃO | S58: NÃO | T58: NÃO | U58: NÃO | V58: SIM | W58: NÃO | X58: NÃO | Y58: NÃO | Z58: NÃO | AA58: =$H$62 -> NÃO | AB58: NÃO | AC58: =IF(COUNTIFS($H$1:$AB$1,"x",H58:AB58,"SIM")>0,(D58+E58+F58),0) -> 0.041666667 | AD58: =IF(COUNTIFS($H$1:$AB$1,"x",H58:AB58,"SIM")>0,G58,0) -> 0.083333333 | AE58: =COUNTIFS(H58:AB58,"SIM") -> 1
A59: Movimentação financeira - Títulos | B59: 3.7 Títulos | C59: *Qualifica | D59: 0.20833333 | E59: 0 | F59: 0 | G59: 0.013888889 | H59: =$H$41 -> NÃO | I59: NÃO | J59: NÃO | K59: NÃO | L59: NÃO | M59: NÃO | N59: NÃO | O59: NÃO | P59: NÃO | Q59: NÃO | R59: NÃO | S59: NÃO | T59: NÃO | U59: NÃO | V59: SIM | W59: NÃO | X59: NÃO | Y59: NÃO | Z59: SIM | AA59: =$H$62 -> NÃO | AB59: NÃO | AC59: =IF(COUNTIFS($H$1:$AB$1,"x",H59:AB59,"SIM")>0,(D59+E59+F59),0) -> 0.20833333 | AD59: =IF(COUNTIFS($H$1:$AB$1,"x",H59:AB59,"SIM")>0,G59,0) -> 0.013888889 | AE59: =COUNTIFS(H59:AB59,"SIM") -> 2
B60: 1.35 Banco | C60: *Qualifica | H60: =$H$41 -> NÃO | I60: NÃO | J60: NÃO | K60: NÃO | L60: NÃO | M60: NÃO | N60: NÃO | O60: NÃO | P60: NÃO | Q60: NÃO | R60: NÃO | S60: NÃO | T60: NÃO | U60: NÃO | V60: SIM | W60: NÃO | X60: NÃO | Y60: NÃO | Z60: NÃO | AA60: =$H$62 -> NÃO | AB60: NÃO | AC60: =IF(COUNTIFS($H$1:$AB$1,"x",H60:AB60,"SIM")>0,(D60+E60+F60),0) -> 0 | AD60: =IF(COUNTIFS($H$1:$AB$1,"x",H60:AB60,"SIM")>0,G60,0) -> 0 | AE60: =COUNTIFS(H60:AB60,"SIM") -> 1
A61: Modalidade Recolhimento Funrural | B61: 2.22 Modalidade Recolhimento Funrural | C61: *Qualifica | H61: =$H$41 -> NÃO | I61: NÃO | J61: NÃO | K61: NÃO | L61: NÃO | M61: NÃO | N61: NÃO | O61: NÃO | P61: NÃO | Q61: NÃO | R61: NÃO | S61: NÃO | T61: NÃO | U61: NÃO | V61: NÃO | W61: NÃO | X61: NÃO | Y61: NÃO | Z61: =$I$63 -> NÃO | AA61: =$H$62 -> NÃO | AB61: NÃO | AC61: =IF(COUNTIFS($H$1:$AB$1,"x",H61:AB61,"SIM")>0,(D61+E61+F61),0) -> 0 | AD61: =IF(COUNTIFS($H$1:$AB$1,"x",H61:AB61,"SIM")>0,G61,0) -> 0 | AE61: =COUNTIFS(H61:AB61,"SIM") -> 0
A62: Cadastro básico - Limite de crédito parceiro | B62: 1.40 Limite Crédito Parceiro | C62: *Qualifica | D62: 0.0069444444 | E62: 0.013888889 | F62: 0.011111111 | G62: 0.013888889 | H62: =$H$41 -> NÃO | I62: NÃO | J62: NÃO | K62: NÃO | L62: NÃO | M62: NÃO | N62: NÃO | O62: NÃO | P62: NÃO | Q62: NÃO | R62: NÃO | S62: NÃO | T62: NÃO | U62: NÃO | V62: SIM | W62: NÃO | X62: NÃO | Y62: NÃO | Z62: SIM | AA62: =$H$62 -> NÃO | AB62: NÃO | AC62: =IF(COUNTIFS($H$1:$AB$1,"x",H62:AB62,"SIM")>0,(D62+E62+F62),0) -> 0.031944444 | AD62: =IF(COUNTIFS($H$1:$AB$1,"x",H62:AB62,"SIM")>0,G62,0) -> 0.013888889 | AE62: =COUNTIFS(H62:AB62,"SIM") -> 2
A63: Pedido - PVPedidoHistoricoSituacao, PVPedidoItemHistoricoSituacao, PVPedidoItemNotaFiscal | B63: 2.26 PVPedHistSituacao | C63: *Qualifica | D63: 0.010416667 | E63: 0.020833333 | F63: 0.020833333 | G63: 0.020833333 | H63: =$H$41 -> NÃO | I63: NÃO | J63: NÃO | K63: NÃO | L63: NÃO | M63: NÃO | N63: NÃO | O63: NÃO | P63: NÃO | Q63: NÃO | R63: NÃO | S63: NÃO | T63: NÃO | U63: NÃO | V63: SIM | W63: NÃO | X63: NÃO | Y63: NÃO | Z63: NÃO | AA63: NÃO | AB63: NÃO | AC63: =IF(COUNTIFS($H$1:$AB$1,"x",H63:AB63,"SIM")>0,(D63+E63+F63),0) -> 0.052083333 | AD63: =IF(COUNTIFS($H$1:$AB$1,"x",H63:AB63,"SIM")>0,G63,0) -> 0.020833333 | AE63: =COUNTIFS(H63:AB63,"SIM") -> 1
B64: 2.27 PVPedItemHistSituacao | C64: *Qualifica | H64: =$H$41 -> NÃO | I64: NÃO | J64: NÃO | K64: NÃO | L64: NÃO | M64: NÃO | N64: NÃO | O64: NÃO | P64: NÃO | Q64: NÃO | R64: NÃO | S64: NÃO | T64: NÃO | U64: NÃO | V64: SIM | W64: NÃO | X64: NÃO | Y64: NÃO | Z64: =$I$63 -> NÃO | AA64: =$H$62 -> NÃO | AB64: NÃO | AC64: =IF(COUNTIFS($H$1:$AB$1,"x",H64:AB64,"SIM")>0,(D64+E64+F64),0) -> 0 | AD64: =IF(COUNTIFS($H$1:$AB$1,"x",H64:AB64,"SIM")>0,G64,0) -> 0 | AE64: =COUNTIFS(H64:AB64,"SIM") -> 1
B65: 2.26 PVPedidoItemNotaFiscal | C65: *Qualifica | H65: =$H$41 -> NÃO | I65: NÃO | J65: NÃO | K65: NÃO | L65: NÃO | M65: NÃO | N65: NÃO | O65: NÃO | P65: NÃO | Q65: NÃO | R65: NÃO | S65: NÃO | T65: NÃO | U65: NÃO | V65: SIM | W65: NÃO | X65: NÃO | Y65: NÃO | Z65: =$I$63 -> NÃO | AA65: =$H$62 -> NÃO | AB65: NÃO | AC65: =IF(COUNTIFS($H$1:$AB$1,"x",H65:AB65,"SIM")>0,(D65+E65+F65),0) -> 0 | AD65: =IF(COUNTIFS($H$1:$AB$1,"x",H65:AB65,"SIM")>0,G65,0) -> 0 | AE65: =COUNTIFS(H65:AB65,"SIM") -> 1
A66: Lançamento de pedido no AGB | B66: 4.0 Exportação de pedido | C66: *Qualifica | D66: 0.10416667 | E66: 0 | F66: 0 | G66: 0.16666667 | H66: =$H$41 -> NÃO | I66: NÃO | J66: NÃO | K66: NÃO | L66: NÃO | M66: NÃO | N66: NÃO | O66: NÃO | P66: NÃO | Q66: NÃO | R66: NÃO | S66: NÃO | T66: NÃO | U66: NÃO | V66: SIM | W66: NÃO | X66: NÃO | Y66: NÃO | Z66: =$I$63 -> NÃO | AA66: =$H$62 -> NÃO | AB66: NÃO | AC66: =IF(COUNTIFS($H$1:$AB$1,"x",H66:AB66,"SIM")>0,(D66+E66+F66),0) -> 0.10416667 | AD66: =IF(COUNTIFS($H$1:$AB$1,"x",H66:AB66,"SIM")>0,G66,0) -> 0.16666667 | AE66: =COUNTIFS(H66:AB66,"SIM") -> 1
A67: Lançamento de pedido barter no AGB | B67: 4.1 Exportação de pedido barter | C67: *Qualifica | D67: 0 | E67: 0 | F67: 0 | G67: 0.16666667 | H67: =$H$41 -> NÃO | I67: NÃO | J67: NÃO | K67: NÃO | L67: NÃO | M67: NÃO | N67: NÃO | O67: NÃO | P67: NÃO | Q67: NÃO | R67: NÃO | S67: NÃO | T67: NÃO | U67: NÃO | V67: SIM | W67: NÃO | X67: NÃO | Y67: NÃO | Z67: =$I$64 -> NÃO | AA67: =$H$63 -> NÃO | AB67: NÃO | AC67: =IF(COUNTIFS($H$1:$AB$1,"x",H67:AB67,"SIM")>0,(D67+E67+F67),0) -> 0 | AD67: =IF(COUNTIFS($H$1:$AB$1,"x",H67:AB67,"SIM")>0,G67,0) -> 0.16666667 | AE67: =COUNTIFS(H67:AB67,"SIM") -> 1
A68: Força de venda - PV Tipo documento cobrança | B68: 2.29 PVTipoDocumentoCobranca | C68: Avaliado | D68: 0.0069444444 | E68: 0.020833333 | F68: 0.013888889 | G68: 0.0069444444 | H68: =$H$41 -> NÃO | I68: NÃO | J68: NÃO | K68: NÃO | L68: NÃO | M68: NÃO | N68: NÃO | O68: NÃO | P68: NÃO | Q68: NÃO | R68: NÃO | S68: NÃO | T68: NÃO | U68: NÃO | V68: SIM | W68: NÃO | X68: NÃO | Y68: NÃO | Z68: =$I$63 -> NÃO | AA68: =$H$62 -> NÃO | AB68: NÃO | AC68: =IF(COUNTIFS($H$1:$AB$1,"x",H68:AB68,"SIM")>0,(D68+E68+F68),0) -> 0.041666667 | AD68: =IF(COUNTIFS($H$1:$AB$1,"x",H68:AB68,"SIM")>0,G68,0) -> 0.0069444444 | AE68: =COUNTIFS(H68:AB68,"SIM") -> 1
A69: Força de venda - PV Tabelas de preço Força de venda - Deleção de PVTabelaPrecoItem | B69: 2.11 PVTabelaPrecoCondicao | C69: Avaliado | D69: 0.25 | E69: 0 | F69: 0 | G69: 0.11805556 | H69: =$H$41 -> NÃO | I69: NÃO | J69: NÃO | K69: NÃO | L69: SIM | M69: NÃO | N69: NÃO | O69: NÃO | P69: NÃO | Q69: NÃO | R69: NÃO | S69: NÃO | T69: NÃO | U69: NÃO | V69: SIM | W69: NÃO | X69: NÃO | Y69: NÃO | Z69: =$I$63 -> NÃO | AA69: =$H$62 -> NÃO | AB69: NÃO | AC69: =IF(COUNTIFS($H$1:$AB$1,"x",H69:AB69,"SIM")>0,(D69+E69+F69),0) -> 0.25 | AD69: =IF(COUNTIFS($H$1:$AB$1,"x",H69:AB69,"SIM")>0,G69,0) -> 0.11805556 | AE69: =COUNTIFS(H69:AB69,"SIM") -> 2
B70: 2.15 PVTabelaPrecoItem | C70: Avaliado | H70: =$H$41 -> NÃO | I70: NÃO | J70: NÃO | K70: NÃO | L70: SIM | M70: NÃO | N70: NÃO | O70: NÃO | P70: NÃO | Q70: NÃO | R70: NÃO | S70: NÃO | T70: NÃO | U70: NÃO | V70: SIM | W70: NÃO | X70: NÃO | Y70: NÃO | Z70: =$I$63 -> NÃO | AA70: =$H$62 -> NÃO | AB70: NÃO | AC70: =IF(COUNTIFS($H$1:$AB$1,"x",H70:AB70,"SIM")>0,(D70+E70+F70),0) -> 0 | AD70: =IF(COUNTIFS($H$1:$AB$1,"x",H70:AB70,"SIM")>0,G70,0) -> 0 | AE70: =COUNTIFS(H70:AB70,"SIM") -> 2
B71: 2.4 PVTabelaPreco | C71: Avaliado | H71: =$H$41 -> NÃO | I71: NÃO | J71: NÃO | K71: NÃO | L71: SIM | M71: NÃO | N71: NÃO | O71: NÃO | P71: NÃO | Q71: NÃO | R71: NÃO | S71: NÃO | T71: NÃO | U71: NÃO | V71: SIM | W71: NÃO | X71: NÃO | Y71: NÃO | Z71: =$I$63 -> NÃO | AA71: =$H$62 -> NÃO | AB71: NÃO | AC71: =IF(COUNTIFS($H$1:$AB$1,"x",H71:AB71,"SIM")>0,(D71+E71+F71),0) -> 0 | AD71: =IF(COUNTIFS($H$1:$AB$1,"x",H71:AB71,"SIM")>0,G71,0) -> 0 | AE71: =COUNTIFS(H71:AB71,"SIM") -> 2
B72: 2.16 PVTabelaPrecoItemProjecao | C72: Avaliado | H72: =$H$41 -> NÃO | I72: NÃO | J72: NÃO | K72: NÃO | L72: SIM | M72: NÃO | N72: NÃO | O72: NÃO | P72: NÃO | Q72: NÃO | R72: NÃO | S72: NÃO | T72: NÃO | U72: NÃO | V72: SIM | W72: NÃO | X72: NÃO | Y72: NÃO | Z72: =$I$63 -> NÃO | AA72: =$H$62 -> NÃO | AB72: NÃO | AC72: =IF(COUNTIFS($H$1:$AB$1,"x",H72:AB72,"SIM")>0,(D72+E72+F72),0) -> 0 | AD72: =IF(COUNTIFS($H$1:$AB$1,"x",H72:AB72,"SIM")>0,G72,0) -> 0 | AE72: =COUNTIFS(H72:AB72,"SIM") -> 2
B73: 2.6 PVTabelaPrecoUsuario | C73: Avaliado | H73: =$H$41 -> NÃO | I73: NÃO | J73: NÃO | K73: NÃO | L73: SIM | M73: NÃO | N73: NÃO | O73: NÃO | P73: NÃO | Q73: NÃO | R73: NÃO | S73: NÃO | T73: NÃO | U73: NÃO | V73: SIM | W73: NÃO | X73: NÃO | Y73: NÃO | Z73: =$I$63 -> NÃO | AA73: =$H$62 -> NÃO | AB73: NÃO | AC73: =IF(COUNTIFS($H$1:$AB$1,"x",H73:AB73,"SIM")>0,(D73+E73+F73),0) -> 0 | AD73: =IF(COUNTIFS($H$1:$AB$1,"x",H73:AB73,"SIM")>0,G73,0) -> 0 | AE73: =COUNTIFS(H73:AB73,"SIM") -> 2
B74: 2.7 PVTabelaPrecoFilial | C74: Avaliado | H74: =$H$41 -> NÃO | I74: NÃO | J74: NÃO | K74: NÃO | L74: SIM | M74: NÃO | N74: NÃO | O74: NÃO | P74: NÃO | Q74: NÃO | R74: NÃO | S74: NÃO | T74: NÃO | U74: NÃO | V74: SIM | W74: NÃO | X74: NÃO | Y74: NÃO | Z74: =$I$63 -> NÃO | AA74: =$H$62 -> NÃO | AB74: NÃO | AC74: =IF(COUNTIFS($H$1:$AB$1,"x",H74:AB74,"SIM")>0,(D74+E74+F74),0) -> 0 | AD74: =IF(COUNTIFS($H$1:$AB$1,"x",H74:AB74,"SIM")>0,G74,0) -> 0 | AE74: =COUNTIFS(H74:AB74,"SIM") -> 2
B75: 2.7 PVTabelaPrecoTipoParceiro | C75: Avaliado | H75: =$H$41 -> NÃO | I75: NÃO | J75: NÃO | K75: NÃO | L75: SIM | M75: NÃO | N75: NÃO | O75: NÃO | P75: NÃO | Q75: NÃO | R75: NÃO | S75: NÃO | T75: NÃO | U75: NÃO | V75: SIM | W75: NÃO | X75: NÃO | Y75: NÃO | Z75: =$I$63 -> NÃO | AA75: =$H$62 -> NÃO | AB75: NÃO | AC75: =IF(COUNTIFS($H$1:$AB$1,"x",H75:AB75,"SIM")>0,(D75+E75+F75),0) -> 0 | AD75: =IF(COUNTIFS($H$1:$AB$1,"x",H75:AB75,"SIM")>0,G75,0) -> 0 | AE75: =COUNTIFS(H75:AB75,"SIM") -> 2
B76: 2.7 PVTabelaPrecoSafra | C76: Avaliado | H76: =$H$41 -> NÃO | I76: NÃO | J76: NÃO | K76: NÃO | L76: SIM | M76: NÃO | N76: NÃO | O76: NÃO | P76: NÃO | Q76: NÃO | R76: NÃO | S76: NÃO | T76: NÃO | U76: NÃO | V76: SIM | W76: NÃO | X76: NÃO | Y76: NÃO | Z76: =$I$63 -> NÃO | AA76: =$H$62 -> NÃO | AB76: NÃO | AC76: =IF(COUNTIFS($H$1:$AB$1,"x",H76:AB76,"SIM")>0,(D76+E76+F76),0) -> 0 | AD76: =IF(COUNTIFS($H$1:$AB$1,"x",H76:AB76,"SIM")>0,G76,0) -> 0 | AE76: =COUNTIFS(H76:AB76,"SIM") -> 2
A77: Força de venda - PV Tipo de Negociação | B77: 2.18 PVTipoDeNegociacao | C77: Avaliado | D77: 0.0069444444 | E77: 0.013888889 | F77: 0.013888889 | G77: 0.0069444444 | H77: =$H$41 -> NÃO | I77: NÃO | J77: NÃO | K77: NÃO | L77: SIM | M77: NÃO | N77: NÃO | O77: NÃO | P77: NÃO | Q77: NÃO | R77: NÃO | S77: NÃO | T77: NÃO | U77: NÃO | V77: SIM | W77: NÃO | X77: NÃO | Y77: NÃO | Z77: =$I$63 -> NÃO | AA77: =$H$62 -> NÃO | AB77: NÃO | AC77: =IF(COUNTIFS($H$1:$AB$1,"x",H77:AB77,"SIM")>0,(D77+E77+F77),0) -> 0.034722222 | AD77: =IF(COUNTIFS($H$1:$AB$1,"x",H77:AB77,"SIM")>0,G77,0) -> 0.0069444444 | AE77: =COUNTIFS(H77:AB77,"SIM") -> 2
A78: Força de venda - PV Condição de pagamento | B78: 2.10 PVCondicaoPagamento | C78: Avaliado | D78: 0.0069444444 | E78: 0.0034722222 | F78: 0.0034722222 | G78: 0.013888889 | H78: =$H$41 -> NÃO | I78: NÃO | J78: NÃO | K78: NÃO | L78: SIM | M78: NÃO | N78: NÃO | O78: NÃO | P78: NÃO | Q78: NÃO | R78: NÃO | S78: NÃO | T78: NÃO | U78: NÃO | V78: SIM | W78: NÃO | X78: NÃO | Y78: NÃO | Z78: =$I$63 -> NÃO | AA78: =$H$62 -> NÃO | AB78: NÃO | AC78: =IF(COUNTIFS($H$1:$AB$1,"x",H78:AB78,"SIM")>0,(D78+E78+F78),0) -> 0.013888889 | AD78: =IF(COUNTIFS($H$1:$AB$1,"x",H78:AB78,"SIM")>0,G78,0) -> 0.013888889 | AE78: =COUNTIFS(H78:AB78,"SIM") -> 2
A79: Força de venda - PV Condição de pagamento tipo documento cobrança | B79: 2,2 PVCondicaoPagamentoTipoDocumentoCobranca | C79: Avaliado | D79: 0.0069444444 | E79: 0.0069444444 | F79: 0.0034722222 | G79: 0.013888889 | H79: =$H$41 -> NÃO | I79: NÃO | J79: NÃO | K79: NÃO | L79: SIM | M79: NÃO | N79: NÃO | O79: NÃO | P79: NÃO | Q79: NÃO | R79: NÃO | S79: NÃO | T79: NÃO | U79: NÃO | V79: SIM | W79: NÃO | X79: NÃO | Y79: NÃO | Z79: =$I$63 -> NÃO | AA79: =$H$62 -> NÃO | AB79: NÃO | AC79: =IF(COUNTIFS($H$1:$AB$1,"x",H79:AB79,"SIM")>0,(D79+E79+F79),0) -> 0.017361111 | AD79: =IF(COUNTIFS($H$1:$AB$1,"x",H79:AB79,"SIM")>0,G79,0) -> 0.013888889 | AE79: =COUNTIFS(H79:AB79,"SIM") -> 2
A80: Força de venda - Cotação PTAX | B80: CotacaoPTAX | C80: Avaliado | D80: 0.0069444444 | E80: 0.0069444444 | F80: 0.0069444444 | G80: 0.013888889 | H80: =$H$41 -> NÃO | I80: NÃO | J80: NÃO | K80: NÃO | L80: SIM | M80: NÃO | N80: NÃO | O80: NÃO | P80: NÃO | Q80: NÃO | R80: NÃO | S80: NÃO | T80: NÃO | U80: NÃO | V80: SIM | W80: NÃO | X80: NÃO | Y80: NÃO | Z80: =$I$63 -> NÃO | AA80: =$H$62 -> NÃO | AB80: NÃO | AC80: =IF(COUNTIFS($H$1:$AB$1,"x",H80:AB80,"SIM")>0,(D80+E80+F80),0) -> 0.020833333 | AD80: =IF(COUNTIFS($H$1:$AB$1,"x",H80:AB80,"SIM")>0,G80,0) -> 0.013888889 | AE80: =COUNTIFS(H80:AB80,"SIM") -> 2
A81: Cadastro básico - Pessoa física complementar | B81: PessoaFisicaComplementar | C81: Avaliado | D81: 0.0069444444 | E81: 0.0069444444 | F81: 0.0069444444 | G81: 0.013888889 | H81: =$H$41 -> NÃO | I81: NÃO | J81: NÃO | K81: NÃO | L81: =$H$62 -> NÃO | M81: NÃO | N81: NÃO | O81: NÃO | P81: NÃO | Q81: NÃO | R81: NÃO | S81: NÃO | T81: NÃO | U81: NÃO | V81: SIM | W81: NÃO | X81: NÃO | Y81: NÃO | Z81: =$I$63 -> NÃO | AA81: =$H$62 -> NÃO | AB81: NÃO | AC81: =IF(COUNTIFS($H$1:$AB$1,"x",H81:AB81,"SIM")>0,(D81+E81+F81),0) -> 0.020833333 | AD81: =IF(COUNTIFS($H$1:$AB$1,"x",H81:AB81,"SIM")>0,G81,0) -> 0.013888889 | AE81: =COUNTIFS(H81:AB81,"SIM") -> 1
A82: Cadastro básico - Cônjuge | B82: Conjuge | C82: Avaliado | D82: 0.0069444444 | E82: 0.0069444444 | F82: 0.0069444444 | G82: 0.013888889 | H82: =$H$41 -> NÃO | I82: NÃO | J82: NÃO | K82: NÃO | L82: =$H$62 -> NÃO | M82: NÃO | N82: NÃO | O82: NÃO | P82: NÃO | Q82: NÃO | R82: NÃO | S82: NÃO | T82: NÃO | U82: NÃO | V82: SIM | W82: NÃO | X82: NÃO | Y82: NÃO | Z82: =$I$63 -> NÃO | AA82: =$H$62 -> NÃO | AB82: NÃO | AC82: =IF(COUNTIFS($H$1:$AB$1,"x",H82:AB82,"SIM")>0,(D82+E82+F82),0) -> 0.020833333 | AD82: =IF(COUNTIFS($H$1:$AB$1,"x",H82:AB82,"SIM")>0,G82,0) -> 0.013888889 | AE82: =COUNTIFS(H82:AB82,"SIM") -> 1
A83: Cadastro básico - Classificação de produto | B83: ClassificacaoProduto | C83: Avaliado | D83: 0.0069444444 | E83: 0.0069444444 | F83: 0.0069444444 | G83: 0.013888889 | H83: =$H$41 -> NÃO | I83: NÃO | J83: NÃO | K83: NÃO | L83: =$H$62 -> NÃO | M83: NÃO | N83: NÃO | O83: NÃO | P83: NÃO | Q83: NÃO | R83: NÃO | S83: NÃO | T83: NÃO | U83: NÃO | V83: SIM | W83: NÃO | X83: NÃO | Y83: NÃO | Z83: =$I$63 -> NÃO | AA83: =$H$62 -> NÃO | AB83: NÃO | AC83: =IF(COUNTIFS($H$1:$AB$1,"x",H83:AB83,"SIM")>0,(D83+E83+F83),0) -> 0.020833333 | AD83: =IF(COUNTIFS($H$1:$AB$1,"x",H83:AB83,"SIM")>0,G83,0) -> 0.013888889 | AE83: =COUNTIFS(H83:AB83,"SIM") -> 1
B84: 2.17 PVCondicaoPagamentoParcela | C84: Avaliado | H84: =$H$41 -> NÃO | I84: NÃO | J84: NÃO | K84: NÃO | L84: =$H$62 -> NÃO | M84: NÃO | N84: NÃO | O84: NÃO | P84: NÃO | Q84: NÃO | R84: NÃO | S84: NÃO | T84: NÃO | U84: NÃO | V84: NÃO | W84: NÃO | X84: NÃO | Y84: NÃO | Z84: =$I$63 -> NÃO | AA84: =$H$62 -> NÃO | AB84: NÃO | AC84: =IF(COUNTIFS($H$1:$AB$1,"x",H84:AB84,"SIM")>0,(D84+E84+F84),0) -> 0 | AD84: =IF(COUNTIFS($H$1:$AB$1,"x",H84:AB84,"SIM")>0,G84,0) -> 0 | AE84: =COUNTIFS(H84:AB84,"SIM") -> 0
B85: 2.23 PVTabelaPrecoItemCondicao | C85: Avaliado | H85: =$H$41 -> NÃO | I85: NÃO | J85: NÃO | K85: NÃO | L85: =$H$62 -> NÃO | M85: NÃO | N85: NÃO | O85: NÃO | P85: NÃO | Q85: NÃO | R85: NÃO | S85: NÃO | T85: NÃO | U85: NÃO | V85: NÃO | W85: NÃO | X85: NÃO | Y85: NÃO | Z85: =$I$63 -> NÃO | AA85: =$H$62 -> NÃO | AB85: NÃO | AC85: =IF(COUNTIFS($H$1:$AB$1,"x",H85:AB85,"SIM")>0,(D85+E85+F85),0) -> 0 | AD85: =IF(COUNTIFS($H$1:$AB$1,"x",H85:AB85,"SIM")>0,G85,0) -> 0 | AE85: =COUNTIFS(H85:AB85,"SIM") -> 0
B86: 2.25 Condição de Pagamento Safra | C86: Avaliado | H86: =$H$41 -> NÃO | I86: NÃO | J86: NÃO | K86: NÃO | L86: =$H$62 -> NÃO | M86: NÃO | N86: NÃO | O86: NÃO | P86: NÃO | Q86: NÃO | R86: NÃO | S86: NÃO | T86: NÃO | U86: NÃO | V86: NÃO | W86: NÃO | X86: NÃO | Y86: NÃO | Z86: =$I$63 -> NÃO | AA86: =$H$62 -> NÃO | AB86: NÃO | AC86: =IF(COUNTIFS($H$1:$AB$1,"x",H86:AB86,"SIM")>0,(D86+E86+F86),0) -> 0 | AD86: =IF(COUNTIFS($H$1:$AB$1,"x",H86:AB86,"SIM")>0,G86,0) -> 0 | AE86: =COUNTIFS(H86:AB86,"SIM") -> 0
B87: 2.30 PVExcecaoCondicaoPagamento | C87: Avaliado | H87: =$H$41 -> NÃO | I87: NÃO | J87: NÃO | K87: NÃO | L87: =$H$62 -> NÃO | M87: NÃO | N87: NÃO | O87: NÃO | P87: NÃO | Q87: NÃO | R87: NÃO | S87: NÃO | T87: NÃO | U87: NÃO | V87: NÃO | W87: NÃO | X87: NÃO | Y87: NÃO | Z87: =$I$63 -> NÃO | AA87: =$H$62 -> NÃO | AB87: NÃO | AC87: =IF(COUNTIFS($H$1:$AB$1,"x",H87:AB87,"SIM")>0,(D87+E87+F87),0) -> 0 | AD87: =IF(COUNTIFS($H$1:$AB$1,"x",H87:AB87,"SIM")>0,G87,0) -> 0 | AE87: =COUNTIFS(H87:AB87,"SIM") -> 0
B88: 2.31 PVExcecaoCondicaoPagamentoClasseProduto | C88: Avaliado | H88: =$H$41 -> NÃO | I88: NÃO | J88: NÃO | K88: NÃO | L88: =$H$62 -> NÃO | M88: NÃO | N88: NÃO | O88: NÃO | P88: NÃO | Q88: NÃO | R88: NÃO | S88: NÃO | T88: NÃO | U88: NÃO | V88: NÃO | W88: NÃO | X88: NÃO | Y88: NÃO | Z88: =$I$63 -> NÃO | AA88: =$H$62 -> NÃO | AB88: NÃO | AC88: =IF(COUNTIFS($H$1:$AB$1,"x",H88:AB88,"SIM")>0,(D88+E88+F88),0) -> 0 | AD88: =IF(COUNTIFS($H$1:$AB$1,"x",H88:AB88,"SIM")>0,G88,0) -> 0 | AE88: =COUNTIFS(H88:AB88,"SIM") -> 0
B89: 2.32 PVExcecaoCondicaoPagamentoProduto | C89: Avaliado | H89: =$H$41 -> NÃO | I89: NÃO | J89: NÃO | K89: NÃO | L89: =$H$62 -> NÃO | M89: NÃO | N89: NÃO | O89: NÃO | P89: NÃO | Q89: NÃO | R89: NÃO | S89: NÃO | T89: NÃO | U89: NÃO | V89: NÃO | W89: NÃO | X89: NÃO | Y89: NÃO | Z89: =$I$63 -> NÃO | AA89: =$H$62 -> NÃO | AB89: NÃO | AC89: =IF(COUNTIFS($H$1:$AB$1,"x",H89:AB89,"SIM")>0,(D89+E89+F89),0) -> 0 | AD89: =IF(COUNTIFS($H$1:$AB$1,"x",H89:AB89,"SIM")>0,G89,0) -> 0 | AE89: =COUNTIFS(H89:AB89,"SIM") -> 0
B90: 2.33 TabelaDePrecoExcecaoClasseDeProduto | C90: Avaliado | H90: =$H$41 -> NÃO | I90: NÃO | J90: NÃO | K90: NÃO | L90: =$H$62 -> NÃO | M90: NÃO | N90: NÃO | O90: NÃO | P90: NÃO | Q90: NÃO | R90: NÃO | S90: NÃO | T90: NÃO | U90: NÃO | V90: NÃO | W90: NÃO | X90: NÃO | Y90: NÃO | Z90: =$I$63 -> NÃO | AA90: =$H$62 -> NÃO | AB90: NÃO | AC90: =IF(COUNTIFS($H$1:$AB$1,"x",H90:AB90,"SIM")>0,(D90+E90+F90),0) -> 0 | AD90: =IF(COUNTIFS($H$1:$AB$1,"x",H90:AB90,"SIM")>0,G90,0) -> 0 | AE90: =COUNTIFS(H90:AB90,"SIM") -> 0
B91: 2.13 PVExcecaoTabelaPreco | C91: Avaliado | H91: =$H$41 -> NÃO | I91: NÃO | J91: NÃO | K91: NÃO | L91: =$H$62 -> NÃO | M91: NÃO | N91: NÃO | O91: NÃO | P91: NÃO | Q91: NÃO | R91: NÃO | S91: NÃO | T91: NÃO | U91: NÃO | V91: NÃO | W91: NÃO | X91: NÃO | Y91: NÃO | Z91: =$I$63 -> NÃO | AA91: =$H$62 -> NÃO | AB91: NÃO | AC91: =IF(COUNTIFS($H$1:$AB$1,"x",H91:AB91,"SIM")>0,(D91+E91+F91),0) -> 0 | AD91: =IF(COUNTIFS($H$1:$AB$1,"x",H91:AB91,"SIM")>0,G91,0) -> 0 | AE91: =COUNTIFS(H91:AB91,"SIM") -> 0
B92: 2.14 PVExcecaoTabelaPrecoItem | C92: Avaliado | H92: =$H$41 -> NÃO | I92: NÃO | J92: NÃO | K92: NÃO | L92: =$H$62 -> NÃO | M92: NÃO | N92: NÃO | O92: NÃO | P92: NÃO | Q92: NÃO | R92: NÃO | S92: NÃO | T92: NÃO | U92: NÃO | V92: NÃO | W92: NÃO | X92: NÃO | Y92: NÃO | Z92: =$I$63 -> NÃO | AA92: =$H$62 -> NÃO | AB92: NÃO | AC92: =IF(COUNTIFS($H$1:$AB$1,"x",H92:AB92,"SIM")>0,(D92+E92+F92),0) -> 0 | AD92: =IF(COUNTIFS($H$1:$AB$1,"x",H92:AB92,"SIM")>0,G92,0) -> 0 | AE92: =COUNTIFS(H92:AB92,"SIM") -> 0
B93: 2.8 PVTabelaPrecoLocalFaturamento | C93: Avaliado | H93: =$H$41 -> NÃO | I93: NÃO | J93: NÃO | K93: NÃO | L93: =$H$62 -> NÃO | M93: NÃO | N93: NÃO | O93: NÃO | P93: NÃO | Q93: NÃO | R93: NÃO | S93: NÃO | T93: NÃO | U93: NÃO | V93: NÃO | W93: NÃO | X93: NÃO | Y93: NÃO | Z93: =$I$63 -> NÃO | AA93: =$H$62 -> NÃO | AB93: NÃO | AC93: =IF(COUNTIFS($H$1:$AB$1,"x",H93:AB93,"SIM")>0,(D93+E93+F93),0) -> 0 | AD93: =IF(COUNTIFS($H$1:$AB$1,"x",H93:AB93,"SIM")>0,G93,0) -> 0 | AE93: =COUNTIFS(H93:AB93,"SIM") -> 0
B94: 2.9 PVTabelaPrecoUFDestino | C94: Avaliado | H94: =$H$41 -> NÃO | I94: NÃO | J94: NÃO | K94: NÃO | L94: =$H$62 -> NÃO | M94: NÃO | N94: NÃO | O94: NÃO | P94: NÃO | Q94: NÃO | R94: NÃO | S94: NÃO | T94: NÃO | U94: NÃO | V94: NÃO | W94: NÃO | X94: NÃO | Y94: NÃO | Z94: =$I$63 -> NÃO | AA94: =$H$62 -> NÃO | AB94: NÃO | AC94: =IF(COUNTIFS($H$1:$AB$1,"x",H94:AB94,"SIM")>0,(D94+E94+F94),0) -> 0 | AD94: =IF(COUNTIFS($H$1:$AB$1,"x",H94:AB94,"SIM")>0,G94,0) -> 0 | AE94: =COUNTIFS(H94:AB94,"SIM") -> 0
B95: 2.36 PVCampanhaTrocaFilial | C95: Avaliado | H95: =$H$41 -> NÃO | I95: NÃO | J95: NÃO | K95: NÃO | L95: =$H$62 -> NÃO | M95: NÃO | N95: NÃO | O95: NÃO | P95: NÃO | Q95: NÃO | R95: NÃO | S95: NÃO | T95: NÃO | U95: NÃO | V95: NÃO | W95: NÃO | X95: NÃO | Y95: NÃO | Z95: =$I$63 -> NÃO | AA95: =$H$62 -> NÃO | AB95: NÃO | AC95: =IF(COUNTIFS($H$1:$AB$1,"x",H95:AB95,"SIM")>0,(D95+E95+F95),0) -> 0 | AD95: =IF(COUNTIFS($H$1:$AB$1,"x",H95:AB95,"SIM")>0,G95,0) -> 0 | AE95: =COUNTIFS(H95:AB95,"SIM") -> 0
... B109: 1.8 Produto Chassi | C109: Avaliado | H109: =$H$41 -> NÃO | I109: NÃO | J109: NÃO | K109: NÃO | L109: =$H$62 -> NÃO | M109: NÃO | N109: NÃO | O109: NÃO | P109: NÃO | Q109: NÃO | R109: NÃO | S109: NÃO | T109: NÃO | U109: NÃO | V109: NÃO | W109: NÃO | X109: NÃO | Y109: NÃO | Z109: =$I$63 -> NÃO | AA109: =$H$62 -> NÃO | AB109: NÃO | AC109: =IF(COUNTIFS($H$1:$AB$1,"x",H109:AB109,"SIM")>0,(D109+E109+F109),0) -> 0 | AD109: =IF(COUNTIFS($H$1:$AB$1,"x",H109:AB109,"SIM")>0,G109,0) -> 0 | AE109: =COUNTIFS(H109:AB109,"SIM") -> 0
B110: 1.9 Exportar Ordem de Serviço | C110: Avaliado | D110: 0.33333333 | H110: =$H$41 -> NÃO | I110: NÃO | J110: NÃO | K110: NÃO | L110: =$H$62 -> NÃO | M110: NÃO | N110: NÃO | O110: NÃO | P110: NÃO | Q110: NÃO | R110: NÃO | S110: NÃO | T110: NÃO | U110: NÃO | V110: NÃO | W110: NÃO | X110: NÃO | Y110: NÃO | Z110: =$I$63 -> NÃO | AA110: SIM | AB110: NÃO | AC110: =IF(COUNTIFS($H$1:$AB$1,"x",H110:AB110,"SIM")>0,(D110+E110+F110),0) -> 0 | AD110: =IF(COUNTIFS($H$1:$AB$1,"x",H110:AB110,"SIM")>0,G110,0) -> 0 | AE110: =COUNTIFS(H110:AB110,"SIM") -> 1
B111: 5.0 Integrar Gestão de Eventos | C111: Avaliado | H111: =$H$41 -> NÃO | I111: NÃO | J111: NÃO | K111: NÃO | L111: =$H$62 -> NÃO | M111: NÃO | N111: NÃO | O111: NÃO | P111: NÃO | Q111: NÃO | R111: NÃO | S111: NÃO | T111: NÃO | U111: NÃO | V111: NÃO | W111: NÃO | X111: NÃO | Y111: NÃO | Z111: =$I$63 -> NÃO | AA111: =$H$62 -> NÃO | AB111: NÃO | AC111: =IF(COUNTIFS($H$1:$AB$1,"x",H111:AB111,"SIM")>0,(D111+E111+F111),0) -> 0 | AD111: =IF(COUNTIFS($H$1:$AB$1,"x",H111:AB111,"SIM")>0,G111,0) -> 0 | AE111: =COUNTIFS(H111:AB111,"SIM") -> 0
D112: =SUM(D3:D111) -> 1.9756944 | E112: =SUM(E3:E111) -> 0.33680556 | F112: =SUM(F3:F111) -> 0.22986111 | G112: =SUM(G3:G111) -> 1.25 | AC112: =SUM(AC3:AC111) -> 1.7368056 | AD112: =SUM(AD3:AD111) -> 0.98958333

Sheet Aliare Integra ERP Terceiro
H1: =Resumo!$A15 -> x | I1: =Resumo!$A16 -> 0 | J1: =Resumo!#REF! -> #REF! | K1: =Resumo!#REF! -> #REF! | L1: =Resumo!#REF! -> #REF! | M1: =Resumo!A17 -> 0 | N1: =Resumo!A18 -> 0 | O1: =Resumo!A19 -> 0 | P1: =Resumo!#REF! -> #REF! | Q1: =Resumo!A20 -> 0 | R1: =Resumo!#REF! -> #REF! | S1: =Resumo!A21 -> 0 | T1: =Resumo!A22 -> 0 | U1: =Resumo!#REF! -> #REF! | V1: =Resumo!A23 -> x | W1: =Resumo!A24 -> 0 | X1: =Resumo!A25 -> 0 | Y1: =Resumo!#REF! -> #REF! | Z1: =Resumo!A26 -> 0 | AA1: =Resumo!A27 -> 0 | AB1: =Resumo!#REF! -> #REF!
A2: Fluxos | B2: Tabela | C2: Tipo | D2: Cofig. Integração ERP Terceiro | E2: Teste interno, carga inicial | F2: Apoio a Validação / homologação e produção ERP Terceiro | G2: Validação de Dados Integrados ERP Terceiro | H2: CRM - MM - Funcionalidades Fundamentais | I2: CRM - MM - Registro de Visita | J2: CRM - MM - Planejamento da Consultoria Agronômica | K2: CRM - MM - Campos Demonstrativos | L2: CRM - MM - Consulta Preço e Estoque à Campo | M2: CRM - MM - Potencial & Metas | N2: CRM - MM - Segmentação | O2: CRM - MM - Previsão de Vendas | P2: CRM - MM - MarketShare | Q2: CRM - MM - Analise de Vendas | R2: CRM - MM - Escoamento de produtos | S2: CRM - MM - Potencial Maquinas | T2: CRM - MM - Chamados | U2: CRM - MM - Questionário de Pós Venda | V2: CRM - MM - Força de Vendas | W2: CRM - MM - Viagem | X2: CRM - MM - Funil de Vendas | Y2: CRM - MM - Levantamento de Rebanho | Z2: CRM - MM - Proposta de Crédito | AA2: CRM - MM - Ordem de Serviço | AB2: CRM - MM - Gestão de Eventos | AC2: Aliare Integra | AD2: CeS
B3: Todos os cadastros básicos | C3: **Sempre | D3: 0 | F3: 0 | G3: 0 | H3: SIM | I3: SIM | J3: SIM | K3: SIM | L3: SIM | M3: SIM | N3: SIM | O3: SIM | P3: SIM | Q3: SIM | R3: SIM | S3: SIM | T3: SIM | U3: SIM | V3: SIM | W3: SIM | X3: SIM | Y3: SIM | Z3: SIM | AA3: SIM | AB3: SIM | AC3: =IF(COUNTIFS($H$1:$AB$1,"x",H3:AB3,"SIM")>0,(D3+E3+F3),0) -> 0 | AD3: =IF(COUNTIFS($H$1:$AB$1,"x",H3:AB3,"SIM")>0,G3) -> 0 | AE3: =COUNTIFS(H3:AB3,"SIM") -> 21
B4: Todas as movimentações financeiras | C4: **Sempre | D4: 0 | F4: 0 | G4: 0 | H4: SIM | I4: SIM | J4: SIM | K4: SIM | L4: SIM | M4: SIM | N4: SIM | O4: SIM | P4: SIM | Q4: SIM | R4: SIM | S4: SIM | T4: SIM | U4: SIM | V4: SIM | W4: SIM | X4: SIM | Y4: SIM | Z4: SIM | AA4: SIM | AB4: SIM | AC4: =IF(COUNTIFS($H$1:$AB$1,"x",H4:AB4,"SIM")>0,(D4+E4+F4),0) -> 0 | AD4: =IF(COUNTIFS($H$1:$AB$1,"x",H4:AB4,"SIM")>0,G4) -> 0 | AE4: =COUNTIFS(H4:AB4,"SIM") -> 21
B5: Todos os fluxos de força de venda | C5: **Sempre | D5: 0 | F5: 0 | G5: 0 | H5: SIM | I5: SIM | J5: SIM | K5: SIM | L5: SIM | M5: SIM | N5: SIM | O5: SIM | P5: SIM | Q5: SIM | R5: SIM | S5: SIM | T5: SIM | U5: SIM | V5: SIM | W5: SIM | X5: SIM | Y5: SIM | Z5: SIM | AA5: SIM | AB5: SIM | AC5: =IF(COUNTIFS($H$1:$AB$1,"x",H5:AB5,"SIM")>0,(D5+E5+F5),0) -> 0 | AD5: =IF(COUNTIFS($H$1:$AB$1,"x",H5:AB5,"SIM")>0,G5) -> 0 | AE5: =COUNTIFS(H5:AB5,"SIM") -> 21
A6: Cadastro básico - País, Estado e Cidade | B6: 1.01 País | C6: **Sempre | G6: 0.020833333 | H6: SIM | I6: SIM | J6: SIM | K6: SIM | L6: SIM | M6: SIM | N6: SIM | O6: SIM | P6: SIM | Q6: SIM | R6: SIM | S6: SIM | T6: SIM | U6: SIM | V6: SIM | W6: SIM | X6: SIM | Y6: SIM | Z6: SIM | AA6: SIM | AB6: SIM | AC6: =IF(COUNTIFS($H$1:$AB$1,"x",H6:AB6,"SIM")>0,(D6+E6+F6),0) -> 0 | AD6: =IF(COUNTIFS($H$1:$AB$1,"x",H6:AB6,"SIM")>0,G6) -> 0.020833333 | AE6: =COUNTIFS(H6:AB6,"SIM") -> 21
B7: 1.02 Unidade Federativa | C7: **Sempre | H7: SIM | I7: SIM | J7: SIM | K7: SIM | L7: SIM | M7: SIM | N7: SIM | O7: SIM | P7: SIM | Q7: SIM | R7: SIM | S7: SIM | T7: SIM | U7: SIM | V7: SIM | W7: SIM | X7: SIM | Y7: SIM | Z7: SIM | AA7: SIM | AB7: SIM | AC7: =IF(COUNTIFS($H$1:$AB$1,"x",H7:AB7,"SIM")>0,(D7+E7+F7),0) -> 0 | AD7: =IF(COUNTIFS($H$1:$AB$1,"x",H7:AB7,"SIM")>0,G7) -> 0 | AE7: =COUNTIFS(H7:AB7,"SIM") -> 21
B8: 1.03 Cidade | C8: **Sempre | H8: SIM | I8: SIM | J8: SIM | K8: SIM | L8: SIM | M8: SIM | N8: SIM | O8: SIM | P8: SIM | Q8: SIM | R8: SIM | S8: SIM | T8: SIM | U8: SIM | V8: SIM | W8: SIM | X8: SIM | Y8: SIM | Z8: SIM | AA8: SIM | AB8: SIM | AC8: =IF(COUNTIFS($H$1:$AB$1,"x",H8:AB8,"SIM")>0,(D8+E8+F8),0) -> 0 | AD8: =IF(COUNTIFS($H$1:$AB$1,"x",H8:AB8,"SIM")>0,G8) -> 0 | AE8: =COUNTIFS(H8:AB8,"SIM") -> 21
A9: Cadastro básico - Unidade de medida | B9: 1.04 Unidade de Medida | C9: **Sempre | G9: 0.010416667 | H9: SIM | I9: SIM | J9: SIM | K9: SIM | L9: SIM | M9: SIM | N9: SIM | O9: SIM | P9: SIM | Q9: SIM | R9: SIM | S9: SIM | T9: SIM | U9: SIM | V9: SIM | W9: SIM | X9: SIM | Y9: SIM | Z9: SIM | AA9: SIM | AB9: SIM | AC9: =IF(COUNTIFS($H$1:$AB$1,"x",H9:AB9,"SIM")>0,(D9+E9+F9),0) -> 0 | AD9: =IF(COUNTIFS($H$1:$AB$1,"x",H9:AB9,"SIM")>0,G9) -> 0.010416667 | AE9: =COUNTIFS(H9:AB9,"SIM") -> 21
A10: Cadastro básico - Parceiro - Parte 1 | B10: 1.05 Parceiro | C10: **Sempre | G10: 0.020833333 | H10: SIM | I10: SIM | J10: SIM | K10: SIM | L10: SIM | M10: SIM | N10: SIM | O10: SIM | P10: SIM | Q10: SIM | R10: SIM | S10: SIM | T10: SIM | U10: SIM | V10: SIM | W10: SIM | X10: SIM | Y10: SIM | Z10: SIM | AA10: SIM | AB10: SIM | AC10: =IF(COUNTIFS($H$1:$AB$1,"x",H10:AB10,"SIM")>0,(D10+E10+F10),0) -> 0 | AD10: =IF(COUNTIFS($H$1:$AB$1,"x",H10:AB10,"SIM")>0,G10) -> 0.020833333 | AE10: =COUNTIFS(H10:AB10,"SIM") -> 21
A11: Cadastro básico - Parceiro - Parte 2 | H11: SIM | I11: SIM | J11: SIM | K11: SIM | L11: SIM | M11: SIM | N11: SIM | O11: SIM | P11: SIM | Q11: SIM | R11: SIM | S11: SIM | T11: SIM | U11: SIM | V11: SIM | W11: SIM | X11: SIM | Y11: SIM | Z11: SIM | AA11: SIM | AB11: SIM | AC11: =IF(COUNTIFS($H$1:$AB$1,"x",H11:AB11,"SIM")>0,(D11+E11+F11),0) -> 0 | AD11: =IF(COUNTIFS($H$1:$AB$1,"x",H11:AB11,"SIM")>0,G11) -> 0 | AE11: =COUNTIFS(H11:AB11,"SIM") -> 21
A12: Cadastro básico - Local - Entidade Empresa | B12: 1.06 Local | C12: **Sempre | D12: 0.66666667 | G12: 0.020833333 | H12: SIM | I12: SIM | J12: SIM | K12: SIM | L12: SIM | M12: SIM | N12: SIM | O12: SIM | P12: SIM | Q12: SIM | R12: SIM | S12: SIM | T12: SIM | U12: SIM | V12: SIM | W12: SIM | X12: SIM | Y12: SIM | Z12: SIM | AA12: SIM | AB12: SIM | AC12: =IF(COUNTIFS($H$1:$AB$1,"x",H12:AB12,"SIM")>0,(D12+E12+F12),0) -> 0.66666667 | AD12: =IF(COUNTIFS($H$1:$AB$1,"x",H12:AB12,"SIM")>0,G12) -> 0.020833333 | AE12: =COUNTIFS(H12:AB12,"SIM") -> 21
A13: Cadastro básico - Local - Entidade Parceiro | H13: SIM | I13: SIM | J13: SIM | K13: SIM | L13: SIM | M13: SIM | N13: SIM | O13: SIM | P13: SIM | Q13: SIM | R13: SIM | S13: SIM | T13: SIM | U13: SIM | V13: SIM | W13: SIM | X13: SIM | Y13: SIM | Z13: SIM | AA13: SIM | AB13: SIM | AC13: =IF(COUNTIFS($H$1:$AB$1,"x",H13:AB13,"SIM")>0,(D13+E13+F13),0) -> 0 | AD13: =IF(COUNTIFS($H$1:$AB$1,"x",H13:AB13,"SIM")>0,G13) -> 0 | AE13: =COUNTIFS(H13:AB13,"SIM") -> 21
A14: Cadastro básico - Local - Entidade Propriedade | H14: SIM | I14: SIM | J14: SIM | K14: SIM | L14: SIM | M14: SIM | N14: SIM | O14: SIM | P14: SIM | Q14: SIM | R14: SIM | S14: SIM | T14: SIM | U14: SIM | V14: SIM | W14: SIM | X14: SIM | Y14: SIM | Z14: SIM | AA14: SIM | AB14: SIM | AC14: =IF(COUNTIFS($H$1:$AB$1,"x",H14:AB14,"SIM")>0,(D14+E14+F14),0) -> 0 | AD14: =IF(COUNTIFS($H$1:$AB$1,"x",H14:AB14,"SIM")>0,G14) -> 0 | AE14: =COUNTIFS(H14:AB14,"SIM") -> 21
A15: Cadastro básico – Empresa | B15: 1.14 Empresa | C15: **Sempre | G15: 0.010416667 | H15: SIM | I15: SIM | J15: SIM | K15: SIM | L15: SIM | M15: SIM | N15: SIM | O15: SIM | P15: SIM | Q15: SIM | R15: SIM | S15: SIM | T15: SIM | U15: SIM | V15: SIM | W15: SIM | X15: SIM | Y15: SIM | Z15: SIM | AA15: SIM | AB15: SIM | AC15: =IF(COUNTIFS($H$1:$AB$1,"x",H15:AB15,"SIM")>0,(D15+E15+F15),0) -> 0 | AD15: =IF(COUNTIFS($H$1:$AB$1,"x",H15:AB15,"SIM")>0,G15) -> 0.010416667 | AE15: =COUNTIFS(H15:AB15,"SIM") -> 21
A16: Cadastro básico - Registrante | B16: 1.15.1 Registrante / Fabricante | C16: *Módulo | H16: NÃO | I16: SIM | J16: SIM | K16: SIM | L16: SIM | M16: SIM | N16: SIM | O16: SIM | P16: SIM | Q16: SIM | R16: SIM | S16: SIM | T16: SIM | U16: SIM | V16: SIM | W16: SIM | X16: SIM | Y16: SIM | Z16: SIM | AA16: SIM | AB16: SIM | AC16: =IF(COUNTIFS($H$1:$AB$1,"x",H16:AB16,"SIM")>0,(D16+E16+F16),0) -> 0 | AD16: =IF(COUNTIFS($H$1:$AB$1,"x",H16:AB16,"SIM")>0,G16) -> 0 | AE16: =COUNTIFS(H16:AB16,"SIM") -> 20
A17: Cadastro básico - Fornecedor | B17: 1.15.2 Fornecedor | C17: *Módulo | H17: NÃO | I17: SIM | J17: SIM | K17: SIM | L17: SIM | M17: SIM | N17: SIM | O17: SIM | P17: SIM | Q17: SIM | R17: SIM | S17: SIM | T17: SIM | U17: SIM | V17: SIM | W17: SIM | X17: SIM | Y17: SIM | Z17: SIM | AA17: SIM | AB17: SIM | AC17: =IF(COUNTIFS($H$1:$AB$1,"x",H17:AB17,"SIM")>0,(D17+E17+F17),0) -> 0 | AD17: =IF(COUNTIFS($H$1:$AB$1,"x",H17:AB17,"SIM")>0,G17) -> 0 | AE17: =COUNTIFS(H17:AB17,"SIM") -> 20
A18: Cadastro básico - Filial | B18: 1.15 Filial | C18: **Sempre | G18: 0.017361111 | H18: SIM | I18: SIM | J18: SIM | K18: SIM | L18: SIM | M18: SIM | N18: SIM | O18: SIM | P18: SIM | Q18: SIM | R18: SIM | S18: SIM | T18: SIM | U18: SIM | V18: SIM | W18: SIM | X18: SIM | Y18: SIM | Z18: SIM | AA18: SIM | AB18: SIM | AC18: =IF(COUNTIFS($H$1:$AB$1,"x",H18:AB18,"SIM")>0,(D18+E18+F18),0) -> 0 | AD18: =IF(COUNTIFS($H$1:$AB$1,"x",H18:AB18,"SIM")>0,G18) -> 0.017361111 | AE18: =COUNTIFS(H18:AB18,"SIM") -> 21
A19: Cadastro básico - Pessoa física e jurídica - Fluxo 1 | B19: 1.16 Pessoa Física e 1.17 Pessoa Jurídica | C19: **Sempre | G19: 0.041666667 | H19: SIM | I19: SIM | J19: SIM | K19: SIM | L19: SIM | M19: SIM | N19: SIM | O19: SIM | P19: SIM | Q19: SIM | R19: SIM | S19: SIM | T19: SIM | U19: SIM | V19: SIM | W19: SIM | X19: SIM | Y19: SIM | Z19: SIM | AA19: SIM | AB19: SIM | AC19: =IF(COUNTIFS($H$1:$AB$1,"x",H19:AB19,"SIM")>0,(D19+E19+F19),0) -> 0 | AD19: =IF(COUNTIFS($H$1:$AB$1,"x",H19:AB19,"SIM")>0,G19) -> 0.041666667 | AE19: =COUNTIFS(H19:AB19,"SIM") -> 21
A20: Cadastro básico - Pessoa física - Fluxo 2 | H20: SIM | I20: SIM | J20: SIM | K20: SIM | L20: SIM | M20: SIM | N20: SIM | O20: SIM | P20: SIM | Q20: SIM | R20: SIM | S20: SIM | T20: SIM | U20: SIM | V20: SIM | W20: SIM | X20: SIM | Y20: SIM | Z20: SIM | AA20: SIM | AB20: SIM | AC20: =IF(COUNTIFS($H$1:$AB$1,"x",H20:AB20,"SIM")>0,(D20+E20+F20),0) -> 0 | AD20: =IF(COUNTIFS($H$1:$AB$1,"x",H20:AB20,"SIM")>0,G20) -> 0 | AE20: =COUNTIFS(H20:AB20,"SIM") -> 21
A21: Cadastro básico - Pessoa jurídica - Fluxo 3 | AC21: =IF(COUNTIFS($H$1:$AB$1,"x",H21:AB21,"SIM")>0,(D21+E21+F21),0) -> 0 | AD21: =IF(COUNTIFS($H$1:$AB$1,"x",H21:AB21,"SIM")>0,G21) -> FALSE | AE21: =COUNTIFS(H21:AB21,"SIM") -> 0
A22: Cadastro básico - Produto e produto classe | B22: 1.08 Produto e 1.10 Produto Classe | C22: *Módulo | D22: 0.66666667 | G22: 0.020833333 | H22: NÃO | I22: SIM | J22: SIM | K22: SIM | L22: SIM | M22: SIM | N22: SIM | O22: SIM | P22: SIM | Q22: SIM | R22: SIM | S22: SIM | T22: SIM | U22: SIM | V22: SIM | W22: SIM | X22: SIM | Y22: SIM | Z22: SIM | AA22: SIM | AB22: SIM | AC22: =IF(COUNTIFS($H$1:$AB$1,"x",H22:AB22,"SIM")>0,(D22+E22+F22),0) -> 0.66666667 | AD22: =IF(COUNTIFS($H$1:$AB$1,"x",H22:AB22,"SIM")>0,G22) -> 0.020833333 | AE22: =COUNTIFS(H22:AB22,"SIM") -> 20
A23: Cadastro básico - Classe de produto | B23: 1.09 Classe de Produto | C23: *Módulo | G23: 0.020833333 | H23: NÃO | I23: SIM | J23: SIM | K23: SIM | L23: SIM | M23: SIM | N23: SIM | O23: SIM | P23: SIM | Q23: SIM | R23: SIM | S23: SIM | T23: SIM | U23: SIM | V23: SIM | W23: SIM | X23: SIM | Y23: SIM | Z23: SIM | AA23: SIM | AB23: SIM | AC23: =IF(COUNTIFS($H$1:$AB$1,"x",H23:AB23,"SIM")>0,(D23+E23+F23),0) -> 0 | AD23: =IF(COUNTIFS($H$1:$AB$1,"x",H23:AB23,"SIM")>0,G23) -> 0.020833333 | AE23: =COUNTIFS(H23:AB23,"SIM") -> 20
A24: Movimentação financeira - Local nota fiscal | B24: 3.1 Local Nota Fiscal | C24: *Módulo | D24: 0.29166667 | G24: 0.083333333 | H24: NÃO | I24: SIM | J24: NÃO | K24: NÃO | L24: NÃO | M24: SIM | N24: NÃO | O24: SIM | P24: SIM | Q24: SIM | R24: SIM | S24: NÃO | T24: NÃO | U24: SIM | V24: NÃO | W24: NÃO | X24: SIM | Y24: NÃO | Z24: NÃO | AA24: NÃO | AB24: NÃO | AC24: =IF(COUNTIFS($H$1:$AB$1,"x",H24:AB24,"SIM")>0,(D24+E24+F24),0) -> 0 | AD24: =IF(COUNTIFS($H$1:$AB$1,"x",H24:AB24,"SIM")>0,G24) -> FALSE | AE24: =COUNTIFS(H24:AB24,"SIM") -> 8
A25: Movimentação financeira - Faturamento mensal - Parte 1 | B25: 3.2 Pedidos em Carteira (Fat. Mensal) | C25: *Módulo | D25: 0.020833333 | F25: 0.010416667 | G25: 0.16666667 | H25: NÃO | I25: NÃO | J25: NÃO | K25: NÃO | L25: NÃO | M25: SIM | N25: SIM | O25: SIM | P25: NÃO | Q25: SIM | R25: NÃO | S25: NÃO | T25: NÃO | U25: NÃO | V25: NÃO | W25: NÃO | X25: NÃO | Y25: NÃO | Z25: NÃO | AA25: NÃO | AB25: NÃO | AC25: =IF(COUNTIFS($H$1:$AB$1,"x",H25:AB25,"SIM")>0,(D25+E25+F25),0) -> 0 | AD25: =IF(COUNTIFS($H$1:$AB$1,"x",H25:AB25,"SIM")>0,G25) -> FALSE | AE25: =COUNTIFS(H25:AB25,"SIM") -> 4
A26: Movimentação financeira - Faturamento mensal - Parte 2 | AC26: =IF(COUNTIFS($H$1:$AB$1,"x",H26:AB26,"SIM")>0,(D26+E26+F26),0) -> 0 | AD26: =IF(COUNTIFS($H$1:$AB$1,"x",H26:AB26,"SIM")>0,G26) -> FALSE | AE26: =COUNTIFS(H26:AB26,"SIM") -> 0
A27: Cadastro básico - Usuários | B27: 1.11 Usuário | C27: *Qualifica | G27: 0.0069444444 | H27: SIM | I27: SIM | J27: NÃO | K27: NÃO | L27: SIM | M27: NÃO | N27: NÃO | O27: NÃO | P27: NÃO | Q27: NÃO | R27: NÃO | S27: NÃO | T27: NÃO | U27: NÃO | V27: SIM | W27: NÃO | X27: NÃO | Y27: NÃO | Z27: NÃO | AA27: NÃO | AB27: NÃO | AC27: =IF(COUNTIFS($H$1:$AB$1,"x",H27:AB27,"SIM")>0,(D27+E27+F27),0) -> 0 | AD27: =IF(COUNTIFS($H$1:$AB$1,"x",H27:AB27,"SIM")>0,G27) -> 0.0069444444 | AE27: =COUNTIFS(H27:AB27,"SIM") -> 4
A28: Cadastro básico - Usuário empresa, filial e parceiro | B28: 1.28 Usuário Filial | C28: *Qualifica | G28: 0.020833333 | H28: SIM | I28: =$H$27 -> SIM | J28: NÃO | K28: NÃO | L28: SIM | M28: NÃO | N28: NÃO | O28: NÃO | P28: NÃO | Q28: NÃO | R28: NÃO | S28: NÃO | T28: NÃO | U28: NÃO | V28: SIM | W28: NÃO | X28: NÃO | Y28: NÃO | Z28: NÃO | AA28: NÃO | AB28: NÃO | AC28: =IF(COUNTIFS($H$1:$AB$1,"x",H28:AB28,"SIM")>0,(D28+E28+F28),0) -> 0 | AD28: =IF(COUNTIFS($H$1:$AB$1,"x",H28:AB28,"SIM")>0,G28) -> 0.020833333 | AE28: =COUNTIFS(H28:AB28,"SIM") -> 4
B29: 1.29 Usuário Empresa | C29: *Qualifica | H29: SIM | I29: =$H$27 -> SIM | J29: NÃO | K29: NÃO | L29: SIM | M29: NÃO | N29: NÃO | O29: NÃO | P29: NÃO | Q29: NÃO | R29: NÃO | S29: NÃO | T29: NÃO | U29: NÃO | V29: SIM | W29: NÃO | X29: NÃO | Y29: NÃO | Z29: NÃO | AA29: NÃO | AB29: NÃO | AC29: =IF(COUNTIFS($H$1:$AB$1,"x",H29:AB29,"SIM")>0,(D29+E29+F29),0) -> 0 | AD29: =IF(COUNTIFS($H$1:$AB$1,"x",H29:AB29,"SIM")>0,G29) -> 0 | AE29: =COUNTIFS(H29:AB29,"SIM") -> 4
B30: 1.28 Usuário Parceiro | C30: *Qualifica | H30: SIM | I30: =$H$27 -> SIM | J30: NÃO | K30: NÃO | L30: SIM | M30: NÃO | N30: NÃO | O30: NÃO | P30: NÃO | Q30: NÃO | R30: NÃO | S30: NÃO | T30: NÃO | U30: NÃO | V30: SIM | W30: NÃO | X30: NÃO | Y30: NÃO | Z30: NÃO | AA30: NÃO | AB30: NÃO | AC30: =IF(COUNTIFS($H$1:$AB$1,"x",H30:AB30,"SIM")>0,(D30+E30+F30),0) -> 0 | AD30: =IF(COUNTIFS($H$1:$AB$1,"x",H30:AB30,"SIM")>0,G30) -> 0 | AE30: =COUNTIFS(H30:AB30,"SIM") -> 4
B31: 1.27 Usuário Produto | C31: *Qualifica | D31: 0.0069444444 | H31: NÃO | I31: NÃO | J31: NÃO | K31: NÃO | L31: NÃO | M31: NÃO | N31: NÃO | O31: NÃO | P31: NÃO | Q31: NÃO | R31: NÃO | S31: NÃO | T31: NÃO | U31: NÃO | V31: NÃO | W31: NÃO | X31: NÃO | Y31: NÃO | Z31: NÃO | AA31: NÃO | AB31: NÃO | AC31: =IF(COUNTIFS($H$1:$AB$1,"x",H31:AB31,"SIM")>0,(D31+E31+F31),0) -> 0 | AD31: =IF(COUNTIFS($H$1:$AB$1,"x",H31:AB31,"SIM")>0,G31) -> FALSE | AE31: =COUNTIFS(H31:AB31,"SIM") -> 0
A32: Cadastro básico - Cultura | B32: 1.12 Cultura | C32: *Qualifica | G32: 0.0069444444 | H32: SIM | I32: SIM | J32: SIM | K32: SIM | L32: SIM | M32: SIM | N32: NÃO | O32: NÃO | P32: NÃO | Q32: NÃO | R32: NÃO | S32: NÃO | T32: NÃO | U32: NÃO | V32: SIM | W32: NÃO | X32: NÃO | Y32: NÃO | Z32: NÃO | AA32: NÃO | AB32: NÃO | AC32: =IF(COUNTIFS($H$1:$AB$1,"x",H32:AB32,"SIM")>0,(D32+E32+F32),0) -> 0 | AD32: =IF(COUNTIFS($H$1:$AB$1,"x",H32:AB32,"SIM")>0,G32) -> 0.0069444444 | AE32: =COUNTIFS(H32:AB32,"SIM") -> 7
A33: Cadastro básico - Safra | B33: 1.13 Safra | C33: *Qualifica | G33: 0.020833333 | H33: NÃO | I33: SIM | J33: SIM | K33: SIM | L33: SIM | M33: SIM | N33: NÃO | O33: NÃO | P33: NÃO | Q33: SIM | R33: NÃO | S33: NÃO | T33: NÃO | U33: NÃO | V33: SIM | W33: NÃO | X33: NÃO | Y33: NÃO | Z33: NÃO | AA33: NÃO | AB33: NÃO | AC33: =IF(COUNTIFS($H$1:$AB$1,"x",H33:AB33,"SIM")>0,(D33+E33+F33),0) -> 0 | AD33: =IF(COUNTIFS($H$1:$AB$1,"x",H33:AB33,"SIM")>0,G33) -> 0.020833333 | AE33: =COUNTIFS(H33:AB33,"SIM") -> 7
A34: Cadastro básico - Região | B34: 1.19 Região | C34: *Qualifica | G34: 0.010416667 | H34: SIM | I34: SIM | J34: SIM | K34: SIM | L34: SIM | M34: SIM | N34: NÃO | O34: NÃO | P34: NÃO | Q34: NÃO | R34: NÃO | S34: NÃO | T34: NÃO | U34: NÃO | V34: SIM | W34: NÃO | X34: NÃO | Y34: NÃO | Z34: NÃO | AA34: NÃO | AB34: NÃO | AC34: =IF(COUNTIFS($H$1:$AB$1,"x",H34:AB34,"SIM")>0,(D34+E34+F34),0) -> 0 | AD34: =IF(COUNTIFS($H$1:$AB$1,"x",H34:AB34,"SIM")>0,G34) -> 0.010416667 | AE34: =COUNTIFS(H34:AB34,"SIM") -> 7
A35: Cadastro básico - Região local | B35: 1.20 Região Local | C35: *Qualifica | G35: 0.017361111 | H35: SIM | I35: SIM | J35: SIM | K35: SIM | L35: SIM | M35: SIM | N35: NÃO | O35: NÃO | P35: NÃO | Q35: NÃO | R35: NÃO | S35: NÃO | T35: NÃO | U35: NÃO | V35: SIM | W35: NÃO | X35: NÃO | Y35: NÃO | Z35: NÃO | AA35: NÃO | AB35: NÃO | AC35: =IF(COUNTIFS($H$1:$AB$1,"x",H35:AB35,"SIM")>0,(D35+E35+F35),0) -> 0 | AD35: =IF(COUNTIFS($H$1:$AB$1,"x",H35:AB35,"SIM")>0,G35) -> 0.017361111 | AE35: =COUNTIFS(H35:AB35,"SIM") -> 7
A36: Cadastro básico - Usuário região | B36: 1.21 Usuário Região | C36: *Qualifica | G36: 0.010416667 | H36: SIM | I36: SIM | J36: SIM | K36: SIM | L36: SIM | M36: SIM | N36: NÃO | O36: NÃO | P36: NÃO | Q36: NÃO | R36: NÃO | S36: NÃO | T36: NÃO | U36: NÃO | V36: SIM | W36: NÃO | X36: NÃO | Y36: NÃO | Z36: NÃO | AA36: NÃO | AB36: NÃO | AC36: =IF(COUNTIFS($H$1:$AB$1,"x",H36:AB36,"SIM")>0,(D36+E36+F36),0) -> 0 | AD36: =IF(COUNTIFS($H$1:$AB$1,"x",H36:AB36,"SIM")>0,G36) -> 0.010416667 | AE36: =COUNTIFS(H36:AB36,"SIM") -> 7
A37: Cadastro básico - Propriedade | B37: 1.22 Propriedade | C37: *Qualifica | G37: 0.020833333 | H37: SIM | I37: SIM | J37: SIM | K37: SIM | L37: NÃO | M37: SIM | N37: NÃO | O37: NÃO | P37: NÃO | Q37: NÃO | R37: NÃO | S37: NÃO | T37: NÃO | U37: NÃO | V37: NÃO | W37: NÃO | X37: NÃO | Y37: NÃO | Z37: NÃO | AA37: NÃO | AB37: NÃO | AC37: =IF(COUNTIFS($H$1:$AB$1,"x",H37:AB37,"SIM")>0,(D37+E37+F37),0) -> 0 | AD37: =IF(COUNTIFS($H$1:$AB$1,"x",H37:AB37,"SIM")>0,G37) -> 0.020833333 | AE37: =COUNTIFS(H37:AB37,"SIM") -> 5
A38: Cadastro básico - Vínculo imobiliário | B38: 1.23 Vin. Imob. | C38: *Qualifica | H38: SIM | I38: SIM | J38: SIM | K38: SIM | L38: NÃO | M38: SIM | N38: NÃO | O38: NÃO | P38: NÃO | Q38: NÃO | R38: NÃO | S38: NÃO | T38: NÃO | U38: NÃO | V38: NÃO | W38: NÃO | X38: NÃO | Y38: NÃO | Z38: NÃO | AA38: NÃO | AB38: NÃO | AC38: =IF(COUNTIFS($H$1:$AB$1,"x",H38:AB38,"SIM")>0,(D38+E38+F38),0) -> 0 | AD38: =IF(COUNTIFS($H$1:$AB$1,"x",H38:AB38,"SIM")>0,G38) -> 0 | AE38: =COUNTIFS(H38:AB38,"SIM") -> 5
A39: Cadastro básico - Posse | B39: 1.24 Posse | C39: *Qualifica | H39: SIM | I39: SIM | J39: SIM | K39: SIM | L39: NÃO | M39: SIM | N39: NÃO | O39: NÃO | P39: NÃO | Q39: NÃO | R39: NÃO | S39: NÃO | T39: NÃO | U39: NÃO | V39: NÃO | W39: NÃO | X39: NÃO | Y39: NÃO | Z39: NÃO | AA39: NÃO | AB39: NÃO | AC39: =IF(COUNTIFS($H$1:$AB$1,"x",H39:AB39,"SIM")>0,(D39+E39+F39),0) -> 0 | AD39: =IF(COUNTIFS($H$1:$AB$1,"x",H39:AB39,"SIM")>0,G39) -> 0 | AE39: =COUNTIFS(H39:AB39,"SIM") -> 5
A40: Cadastro básico - Arrendamento | B40: 1.25 Arrend. | C40: *Qualifica | H40: NÃO | I40: NÃO | J40: NÃO | K40: NÃO | L40: NÃO | M40: NÃO | N40: NÃO | O40: NÃO | P40: NÃO | Q40: NÃO | R40: NÃO | S40: NÃO | T40: NÃO | U40: NÃO | V40: NÃO | W40: NÃO | X40: NÃO | Y40: NÃO | Z40: NÃO | AA40: NÃO | AB40: NÃO | AC40: =IF(COUNTIFS($H$1:$AB$1,"x",H40:AB40,"SIM")>0,(D40+E40+F40),0) -> 0 | AD40: =IF(COUNTIFS($H$1:$AB$1,"x",H40:AB40,"SIM")>0,G40) -> FALSE | AE40: =COUNTIFS(H40:AB40,"SIM") -> 0
B41: 1.26 Região Filial | C41: *Qualifica | H41: NÃO | I41: NÃO | J41: NÃO | K41: NÃO | L41: NÃO | M41: NÃO | N41: NÃO | O41: NÃO | P41: NÃO | Q41: NÃO | R41: NÃO | S41: NÃO | T41: NÃO | U41: NÃO | V41: NÃO | W41: NÃO | X41: NÃO | Y41: NÃO | Z41: NÃO | AA41: NÃO | AB41: NÃO | AC41: =IF(COUNTIFS($H$1:$AB$1,"x",H41:AB41,"SIM")>0,(D41+E41+F41),0) -> 0 | AD41: =IF(COUNTIFS($H$1:$AB$1,"x",H41:AB41,"SIM")>0,G41) -> FALSE | AE41: =COUNTIFS(H41:AB41,"SIM") -> 0
A42: Cadastro básico - Tipo parceiro | B42: 1.33 Tipo Parceiro | C42: *Qualifica | G42: 0.010416667 | H42: SIM | I42: SIM | J42: NÃO | K42: NÃO | L42: NÃO | M42: NÃO | N42: NÃO | O42: NÃO | P42: NÃO | Q42: NÃO | R42: NÃO | S42: NÃO | T42: NÃO | U42: NÃO | V42: NÃO | W42: NÃO | X42: NÃO | Y42: NÃO | Z42: NÃO | AA42: NÃO | AB42: NÃO | AC42: =IF(COUNTIFS($H$1:$AB$1,"x",H42:AB42,"SIM")>0,(D42+E42+F42),0) -> 0 | AD42: =IF(COUNTIFS($H$1:$AB$1,"x",H42:AB42,"SIM")>0,G42) -> 0.010416667 | AE42: =COUNTIFS(H42:AB42,"SIM") -> 2
A43: Cadastro básico - Parceiro tipo parceiro | B43: 1.34 Parceiro Tipo Parceiro | C43: *Qualifica | G43: 0.010416667 | H43: SIM | I43: =$J$58 -> NÃO | J43: NÃO | K43: NÃO | L43: NÃO | M43: NÃO | N43: NÃO | O43: NÃO | P43: NÃO | Q43: NÃO | R43: NÃO | S43: NÃO | T43: NÃO | U43: NÃO | V43: NÃO | W43: NÃO | X43: NÃO | Y43: NÃO | Z43: NÃO | AA43: NÃO | AB43: NÃO | AC43: =IF(COUNTIFS($H$1:$AB$1,"x",H43:AB43,"SIM")>0,(D43+E43+F43),0) -> 0 | AD43: =IF(COUNTIFS($H$1:$AB$1,"x",H43:AB43,"SIM")>0,G43) -> 0.010416667 | AE43: =COUNTIFS(H43:AB43,"SIM") -> 1
A44: Cadastro básico - Estoque | B44: 3.4 Estoque | C44: *Qualifica | D44: 0.020833333 | F44: 0.010416667 | G44: 0.041666667 | H44: =$H$41 -> NÃO | I44: =$J$58 -> NÃO | J44: NÃO | K44: NÃO | L44: SIM | M44: NÃO | N44: NÃO | O44: NÃO | P44: NÃO | Q44: NÃO | R44: NÃO | S44: NÃO | T44: NÃO | U44: NÃO | V44: SIM | W44: NÃO | X44: NÃO | Y44: NÃO | Z44: NÃO | AA44: NÃO | AB44: NÃO | AC44: =IF(COUNTIFS($H$1:$AB$1,"x",H44:AB44,"SIM")>0,(D44+E44+F44),0) -> 0.03125 | AD44: =IF(COUNTIFS($H$1:$AB$1,"x",H44:AB44,"SIM")>0,G44) -> 0.041666667 | AE44: =COUNTIFS(H44:AB44,"SIM") -> 2
B45: 3.10 Carga (Romaneios) | C45: *Qualifica | H45: =$H$41 -> NÃO | I45: NÃO | J45: NÃO | K45: NÃO | L45: NÃO | M45: NÃO | N45: NÃO | O45: NÃO | P45: NÃO | Q45: NÃO | R45: NÃO | S45: NÃO | T45: NÃO | U45: NÃO | V45: NÃO | W45: NÃO | X45: NÃO | Y45: NÃO | Z45: NÃO | AA45: NÃO | AB45: NÃO | AC45: =IF(COUNTIFS($H$1:$AB$1,"x",H45:AB45,"SIM")>0,(D45+E45+F45),0) -> 0 | AD45: =IF(COUNTIFS($H$1:$AB$1,"x",H45:AB45,"SIM")>0,G45) -> FALSE | AE45: =COUNTIFS(H45:AB45,"SIM") -> 0
A46: Cadastro básico - Veiculo | B46: 1.29 Veículo | C46: *Qualifica | D46: 0.020833333 | F46: 0.010416667 | G46: 0.010416667 | H46: =$H$41 -> NÃO | I46: NÃO | J46: NÃO | K46: NÃO | L46: NÃO | M46: NÃO | N46: NÃO | O46: NÃO | P46: NÃO | Q46: NÃO | R46: NÃO | S46: NÃO | T46: NÃO | U46: NÃO | V46: NÃO | W46: SIM | X46: NÃO | Y46: NÃO | Z46: NÃO | AA46: =$H$62 -> NÃO | AB46: NÃO | AC46: =IF(COUNTIFS($H$1:$AB$1,"x",H46:AB46,"SIM")>0,(D46+E46+F46),0) -> 0 | AD46: =IF(COUNTIFS($H$1:$AB$1,"x",H46:AB46,"SIM")>0,G46) -> FALSE | AE46: =COUNTIFS(H46:AB46,"SIM") -> 1
B47: 1.30 Centro de Custo | C47: *Qualifica | H47: =$H$41 -> NÃO | I47: NÃO | J47: NÃO | K47: NÃO | L47: NÃO | M47: NÃO | N47: NÃO | O47: NÃO | P47: NÃO | Q47: NÃO | R47: NÃO | S47: NÃO | T47: NÃO | U47: NÃO | V47: NÃO | W47: NÃO | X47: NÃO | Y47: NÃO | Z47: NÃO | AA47: NÃO | AB47: NÃO | AC47: =IF(COUNTIFS($H$1:$AB$1,"x",H47:AB47,"SIM")>0,(D47+E47+F47),0) -> 0 | AD47: =IF(COUNTIFS($H$1:$AB$1,"x",H47:AB47,"SIM")>0,G47) -> FALSE | AE47: =COUNTIFS(H47:AB47,"SIM") -> 0
B48: 1.31 Usuário Centro de Custo | C48: *Qualifica | H48: =$H$41 -> NÃO | I48: NÃO | J48: NÃO | K48: NÃO | L48: NÃO | M48: NÃO | N48: NÃO | O48: NÃO | P48: NÃO | Q48: NÃO | R48: NÃO | S48: NÃO | T48: NÃO | U48: NÃO | V48: NÃO | W48: NÃO | X48: NÃO | Y48: NÃO | Z48: NÃO | AA48: NÃO | AB48: NÃO | AC48: =IF(COUNTIFS($H$1:$AB$1,"x",H48:AB48,"SIM")>0,(D48+E48+F48),0) -> 0 | AD48: =IF(COUNTIFS($H$1:$AB$1,"x",H48:AB48,"SIM")>0,G48) -> FALSE | AE48: =COUNTIFS(H48:AB48,"SIM") -> 0
B49: 1.32 Despesa | C49: *Qualifica | H49: =$H$41 -> NÃO | I49: NÃO | J49: NÃO | K49: NÃO | L49: NÃO | M49: NÃO | N49: NÃO | O49: NÃO | P49: NÃO | Q49: NÃO | R49: NÃO | S49: NÃO | T49: NÃO | U49: NÃO | V49: NÃO | W49: NÃO | X49: NÃO | Y49: NÃO | Z49: NÃO | AA49: NÃO | AB49: NÃO | AC49: =IF(COUNTIFS($H$1:$AB$1,"x",H49:AB49,"SIM")>0,(D49+E49+F49),0) -> 0 | AD49: =IF(COUNTIFS($H$1:$AB$1,"x",H49:AB49,"SIM")>0,G49) -> FALSE | AE49: =COUNTIFS(H49:AB49,"SIM") -> 0
A50: Exportação de Despesa de Viagem | B50: 4.3 Exportação de Viagem | C50: *Qualifica | D50: 0.625 | E50: 0 | F50: 0 | H50: =$H$41 -> NÃO | I50: NÃO | J50: NÃO | K50: NÃO | L50: NÃO | M50: NÃO | N50: NÃO | O50: NÃO | P50: NÃO | Q50: NÃO | R50: NÃO | S50: NÃO | T50: NÃO | U50: NÃO | V50: NÃO | W50: SIM | X50: NÃO | Y50: NÃO | Z50: NÃO | AA50: NÃO | AB50: NÃO | AC50: =IF(COUNTIFS($H$1:$AB$1,"x",H50:AB50,"SIM")>0,(D50+E50+F50),0) -> 0 | AD50: =IF(COUNTIFS($H$1:$AB$1,"x",H50:AB50,"SIM")>0,G50) -> FALSE | AE50: =COUNTIFS(H50:AB50,"SIM") -> 1
B51: 4.4 Rastreador Veículo | C51: *Qualifica | H51: =$H$41 -> NÃO | I51: NÃO | J51: NÃO | K51: NÃO | L51: NÃO | M51: NÃO | N51: NÃO | O51: NÃO | P51: NÃO | Q51: NÃO | R51: NÃO | S51: NÃO | T51: NÃO | U51: NÃO | V51: NÃO | W51: NÃO | X51: NÃO | Y51: NÃO | Z51: NÃO | AA51: NÃO | AB51: NÃO | AC51: =IF(COUNTIFS($H$1:$AB$1,"x",H51:AB51,"SIM")>0,(D51+E51+F51),0) -> 0 | AD51: =IF(COUNTIFS($H$1:$AB$1,"x",H51:AB51,"SIM")>0,G51) -> FALSE | AE51: =COUNTIFS(H51:AB51,"SIM") -> 0
A52: Cadastro básico - Silo | B52: 1.37 Silo | C52: *Qualifica | G52: 0.0069444444 | H52: =$H$41 -> NÃO | I52: NÃO | J52: NÃO | K52: NÃO | L52: NÃO | M52: NÃO | N52: NÃO | O52: NÃO | P52: NÃO | Q52: NÃO | R52: NÃO | S52: NÃO | T52: NÃO | U52: NÃO | V52: SIM | W52: NÃO | X52: NÃO | Y52: NÃO | Z52: NÃO | AA52: NÃO | AB52: NÃO | AC52: =IF(COUNTIFS($H$1:$AB$1,"x",H52:AB52,"SIM")>0,(D52+E52+F52),0) -> 0 | AD52: =IF(COUNTIFS($H$1:$AB$1,"x",H52:AB52,"SIM")>0,G52) -> 0.0069444444 | AE52: =COUNTIFS(H52:AB52,"SIM") -> 1
B53: 1.39 Preço Produto | C53: *Qualifica | H53: =$H$41 -> NÃO | I53: NÃO | J53: NÃO | K53: NÃO | L53: NÃO | M53: NÃO | N53: NÃO | O53: NÃO | P53: NÃO | Q53: NÃO | R53: NÃO | S53: NÃO | T53: NÃO | U53: NÃO | V53: =$I$63 -> NÃO | W53: NÃO | X53: NÃO | Y53: NÃO | Z53: NÃO | AA53: NÃO | AB53: NÃO | AC53: =IF(COUNTIFS($H$1:$AB$1,"x",H53:AB53,"SIM")>0,(D53+E53+F53),0) -> 0 | AD53: =IF(COUNTIFS($H$1:$AB$1,"x",H53:AB53,"SIM")>0,G53) -> FALSE | AE53: =COUNTIFS(H53:AB53,"SIM") -> 0
B54: 1.60 Segmentação | C54: *Qualifica | H54: =$H$41 -> NÃO | I54: NÃO | J54: NÃO | K54: NÃO | L54: NÃO | M54: NÃO | N54: NÃO | O54: NÃO | P54: NÃO | Q54: NÃO | R54: NÃO | S54: NÃO | T54: NÃO | U54: NÃO | V54: =$I$63 -> NÃO | W54: NÃO | X54: NÃO | Y54: NÃO | Z54: NÃO | AA54: NÃO | AB54: NÃO | AC54: =IF(COUNTIFS($H$1:$AB$1,"x",H54:AB54,"SIM")>0,(D54+E54+F54),0) -> 0 | AD54: =IF(COUNTIFS($H$1:$AB$1,"x",H54:AB54,"SIM")>0,G54) -> FALSE | AE54: =COUNTIFS(H54:AB54,"SIM") -> 0
B55: 3.3 Metas de Venda | C55: *Qualifica | H55: =$H$41 -> NÃO | I55: NÃO | J55: NÃO | K55: NÃO | L55: NÃO | M55: NÃO | N55: NÃO | O55: NÃO | P55: NÃO | Q55: NÃO | R55: NÃO | S55: NÃO | T55: NÃO | U55: NÃO | V55: =$I$63 -> NÃO | W55: NÃO | X55: NÃO | Y55: NÃO | Z55: NÃO | AA55: NÃO | AB55: NÃO | AC55: =IF(COUNTIFS($H$1:$AB$1,"x",H55:AB55,"SIM")>0,(D55+E55+F55),0) -> 0 | AD55: =IF(COUNTIFS($H$1:$AB$1,"x",H55:AB55,"SIM")>0,G55) -> FALSE | AE55: =COUNTIFS(H55:AB55,"SIM") -> 0
A56: Movimentação financeira - Histórico de aquisição de produtos | B56: 3.8 Histórico Aquisição Produtos | C56: *Qualifica | G56: 0.020833333 | H56: =$H$41 -> NÃO | I56: NÃO | J56: NÃO | K56: NÃO | L56: NÃO | M56: NÃO | N56: NÃO | O56: NÃO | P56: NÃO | Q56: NÃO | R56: NÃO | S56: NÃO | T56: NÃO | U56: NÃO | V56: SIM | W56: NÃO | X56: NÃO | Y56: NÃO | Z56: NÃO | AA56: NÃO | AB56: NÃO | AC56: =IF(COUNTIFS($H$1:$AB$1,"x",H56:AB56,"SIM")>0,(D56+E56+F56),0) -> 0 | AD56: =IF(COUNTIFS($H$1:$AB$1,"x",H56:AB56,"SIM")>0,G56) -> 0.020833333 | AE56: =COUNTIFS(H56:AB56,"SIM") -> 1
B57: 3.9 Histórico Produção Entregue | C57: *Qualifica | H57: =$H$41 -> NÃO | I57: NÃO | J57: NÃO | K57: NÃO | L57: NÃO | M57: NÃO | N57: NÃO | O57: NÃO | P57: NÃO | Q57: NÃO | R57: NÃO | S57: NÃO | T57: NÃO | U57: NÃO | V57: =$I$63 -> NÃO | W57: NÃO | X57: NÃO | Y57: NÃO | Z57: NÃO | AA57: NÃO | AB57: NÃO | AC57: =IF(COUNTIFS($H$1:$AB$1,"x",H57:AB57,"SIM")>0,(D57+E57+F57),0) -> 0 | AD57: =IF(COUNTIFS($H$1:$AB$1,"x",H57:AB57,"SIM")>0,G57) -> FALSE | AE57: =COUNTIFS(H57:AB57,"SIM") -> 0
B58: 3.11 PCResumoFinanceiro + 3.12 PCResumoTitulos | C58: *Qualifica | H58: =$H$41 -> NÃO | I58: NÃO | J58: NÃO | K58: NÃO | L58: NÃO | M58: NÃO | N58: NÃO | O58: NÃO | P58: NÃO | Q58: NÃO | R58: NÃO | S58: NÃO | T58: NÃO | U58: NÃO | V58: =$I$63 -> NÃO | W58: NÃO | X58: NÃO | Y58: NÃO | Z58: NÃO | AA58: =$H$62 -> NÃO | AB58: NÃO | AC58: =IF(COUNTIFS($H$1:$AB$1,"x",H58:AB58,"SIM")>0,(D58+E58+F58),0) -> 0 | AD58: =IF(COUNTIFS($H$1:$AB$1,"x",H58:AB58,"SIM")>0,G58) -> FALSE | AE58: =COUNTIFS(H58:AB58,"SIM") -> 0
A59: Movimentação financeira - Títulos | B59: 3.7 Títulos | C59: *Qualifica | D59: 0.25 | G59: 0.013888889 | H59: =$H$41 -> NÃO | I59: NÃO | J59: NÃO | K59: NÃO | L59: NÃO | M59: NÃO | N59: NÃO | O59: NÃO | P59: NÃO | Q59: NÃO | R59: NÃO | S59: NÃO | T59: NÃO | U59: NÃO | V59: NÃO | W59: NÃO | X59: NÃO | Y59: NÃO | Z59: SIM | AA59: =$H$62 -> NÃO | AB59: NÃO | AC59: =IF(COUNTIFS($H$1:$AB$1,"x",H59:AB59,"SIM")>0,(D59+E59+F59),0) -> 0 | AD59: =IF(COUNTIFS($H$1:$AB$1,"x",H59:AB59,"SIM")>0,G59) -> FALSE | AE59: =COUNTIFS(H59:AB59,"SIM") -> 1
B60: 1.35 Banco | C60: *Qualifica | H60: =$H$41 -> NÃO | I60: NÃO | J60: NÃO | K60: NÃO | L60: NÃO | M60: NÃO | N60: NÃO | O60: NÃO | P60: NÃO | Q60: NÃO | R60: NÃO | S60: NÃO | T60: NÃO | U60: NÃO | V60: NÃO | W60: NÃO | X60: NÃO | Y60: NÃO | Z60: NÃO | AA60: =$H$62 -> NÃO | AB60: NÃO | AC60: =IF(COUNTIFS($H$1:$AB$1,"x",H60:AB60,"SIM")>0,(D60+E60+F60),0) -> 0 | AD60: =IF(COUNTIFS($H$1:$AB$1,"x",H60:AB60,"SIM")>0,G60) -> FALSE | AE60: =COUNTIFS(H60:AB60,"SIM") -> 0
A61: Modalidade Recolhimento Funrural | B61: 2.22 Modalidade Recolhimento Funrural | C61: *Qualifica | H61: =$H$41 -> NÃO | I61: NÃO | J61: NÃO | K61: NÃO | L61: NÃO | M61: NÃO | N61: NÃO | O61: NÃO | P61: NÃO | Q61: NÃO | R61: NÃO | S61: NÃO | T61: NÃO | U61: NÃO | V61: NÃO | W61: NÃO | X61: NÃO | Y61: NÃO | Z61: =$I$63 -> NÃO | AA61: =$H$62 -> NÃO | AB61: NÃO | AC61: =IF(COUNTIFS($H$1:$AB$1,"x",H61:AB61,"SIM")>0,(D61+E61+F61),0) -> 0 | AD61: =IF(COUNTIFS($H$1:$AB$1,"x",H61:AB61,"SIM")>0,G61) -> FALSE | AE61: =COUNTIFS(H61:AB61,"SIM") -> 0
A62: Cadastro básico - Limite de crédito parceiro | B62: 1.40 Limite Crédito Parceiro | C62: *Qualifica | D62: 0.020833333 | F62: 0.010416667 | G62: 0.020833333 | H62: =$H$41 -> NÃO | I62: NÃO | J62: NÃO | K62: NÃO | L62: NÃO | M62: NÃO | N62: NÃO | O62: NÃO | P62: NÃO | Q62: NÃO | R62: NÃO | S62: NÃO | T62: NÃO | U62: NÃO | V62: SIM | W62: NÃO | X62: NÃO | Y62: NÃO | Z62: SIM | AA62: =$H$62 -> NÃO | AB62: NÃO | AC62: =IF(COUNTIFS($H$1:$AB$1,"x",H62:AB62,"SIM")>0,(D62+E62+F62),0) -> 0.03125 | AD62: =IF(COUNTIFS($H$1:$AB$1,"x",H62:AB62,"SIM")>0,G62) -> 0.020833333 | AE62: =COUNTIFS(H62:AB62,"SIM") -> 2
A63: Pedido - PVPedidoHistoricoSituacao, PVPedidoItemHistoricoSituacao, PVPedidoItemNotaFiscal | B63: 2.26 PVPedHistSituacao | C63: *Qualifica | G63: 0.020833333 | H63: =$H$41 -> NÃO | I63: NÃO | J63: NÃO | K63: NÃO | L63: NÃO | M63: NÃO | N63: NÃO | O63: NÃO | P63: NÃO | Q63: NÃO | R63: NÃO | S63: NÃO | T63: NÃO | U63: NÃO | V63: SIM | W63: NÃO | X63: NÃO | Y63: NÃO | Z63: NÃO | AA63: NÃO | AB63: NÃO | AC63: =IF(COUNTIFS($H$1:$AB$1,"x",H63:AB63,"SIM")>0,(D63+E63+F63),0) -> 0 | AD63: =IF(COUNTIFS($H$1:$AB$1,"x",H63:AB63,"SIM")>0,G63) -> 0.020833333 | AE63: =COUNTIFS(H63:AB63,"SIM") -> 1
B64: 2.27 PVPedItemHistSituacao | C64: *Qualifica | H64: =$H$41 -> NÃO | I64: NÃO | J64: NÃO | K64: NÃO | L64: NÃO | M64: NÃO | N64: NÃO | O64: NÃO | P64: NÃO | Q64: NÃO | R64: NÃO | S64: NÃO | T64: NÃO | U64: NÃO | V64: SIM | W64: NÃO | X64: NÃO | Y64: NÃO | Z64: =$I$63 -> NÃO | AA64: =$H$62 -> NÃO | AB64: NÃO | AC64: =IF(COUNTIFS($H$1:$AB$1,"x",H64:AB64,"SIM")>0,(D64+E64+F64),0) -> 0 | AD64: =IF(COUNTIFS($H$1:$AB$1,"x",H64:AB64,"SIM")>0,G64) -> 0 | AE64: =COUNTIFS(H64:AB64,"SIM") -> 1
B65: 2.26 PVPedidoItemNotaFiscal | C65: *Qualifica | H65: =$H$41 -> NÃO | I65: NÃO | J65: NÃO | K65: NÃO | L65: NÃO | M65: NÃO | N65: NÃO | O65: NÃO | P65: NÃO | Q65: NÃO | R65: NÃO | S65: NÃO | T65: NÃO | U65: NÃO | V65: SIM | W65: NÃO | X65: NÃO | Y65: NÃO | Z65: =$I$63 -> NÃO | AA65: =$H$62 -> NÃO | AB65: NÃO | AC65: =IF(COUNTIFS($H$1:$AB$1,"x",H65:AB65,"SIM")>0,(D65+E65+F65),0) -> 0 | AD65: =IF(COUNTIFS($H$1:$AB$1,"x",H65:AB65,"SIM")>0,G65) -> 0 | AE65: =COUNTIFS(H65:AB65,"SIM") -> 1
A66: Lançamento de pedido no AGB | B66: 4.0 Exportação de pedido | C66: *Qualifica | D66: 0.625 | F66: 0.45833333 | G66: 0.33333333 | H66: =$H$41 -> NÃO | I66: NÃO | J66: NÃO | K66: NÃO | L66: NÃO | M66: NÃO | N66: NÃO | O66: NÃO | P66: NÃO | Q66: NÃO | R66: NÃO | S66: NÃO | T66: NÃO | U66: NÃO | V66: SIM | W66: NÃO | X66: NÃO | Y66: NÃO | Z66: =$I$63 -> NÃO | AA66: =$H$62 -> NÃO | AB66: NÃO | AC66: =IF(COUNTIFS($H$1:$AB$1,"x",H66:AB66,"SIM")>0,(D66+E66+F66),0) -> 1.0833333 | AD66: =IF(COUNTIFS($H$1:$AB$1,"x",H66:AB66,"SIM")>0,G66) -> 0.33333333 | AE66: =COUNTIFS(H66:AB66,"SIM") -> 1
A67: Lançamento de pedido barter no AGB | B67: 4.1 Exportação de pedido barter | C67: *Qualifica | D67: 0.625 | F67: 0.26041667 | G67: 0.16666667 | H67: =$H$41 -> NÃO | I67: NÃO | J67: NÃO | K67: NÃO | L67: NÃO | M67: NÃO | N67: NÃO | O67: NÃO | P67: NÃO | Q67: NÃO | R67: NÃO | S67: NÃO | T67: NÃO | U67: NÃO | V67: SIM | W67: NÃO | X67: NÃO | Y67: NÃO | Z67: =$I$64 -> NÃO | AA67: =$H$63 -> NÃO | AB67: NÃO | AC67: =IF(COUNTIFS($H$1:$AB$1,"x",H67:AB67,"SIM")>0,(D67+E67+F67),0) -> 0.88541667 | AD67: =IF(COUNTIFS($H$1:$AB$1,"x",H67:AB67,"SIM")>0,G67,0) -> 0.16666667 | AE67: =COUNTIFS(H67:AB67,"SIM") -> 1
A68: Força de venda - PV Tipo documento cobrança | B68: 2.29 PVTipoDocumentoCobranca | C68: Avaliado | D68: 0.020833333 | F68: 0.010416667 | G68: 0.010416667 | H68: =$H$41 -> NÃO | I68: NÃO | J68: NÃO | K68: NÃO | L68: NÃO | M68: NÃO | N68: NÃO | O68: NÃO | P68: NÃO | Q68: NÃO | R68: NÃO | S68: NÃO | T68: NÃO | U68: NÃO | V68: SIM | W68: NÃO | X68: NÃO | Y68: NÃO | Z68: =$I$63 -> NÃO | AA68: =$H$62 -> NÃO | AB68: NÃO | AC68: =IF(COUNTIFS($H$1:$AB$1,"x",H68:AB68,"SIM")>0,(D68+E68+F68),0) -> 0.03125 | AD68: =IF(COUNTIFS($H$1:$AB$1,"x",H68:AB68,"SIM")>0,G68) -> 0.010416667 | AE68: =COUNTIFS(H68:AB68,"SIM") -> 1
A69: Força de venda - PV Tabelas de preço Força de venda - Deleção de PVTabelaPrecoItem | B69: 2.11 PVTabelaPrecoCondicao | C69: Avaliado | D69: 0.29166667 | G69: 0.11805556 | H69: =$H$41 -> NÃO | I69: NÃO | J69: NÃO | K69: NÃO | L69: SIM | M69: NÃO | N69: NÃO | O69: NÃO | P69: NÃO | Q69: NÃO | R69: NÃO | S69: NÃO | T69: NÃO | U69: NÃO | V69: SIM | W69: NÃO | X69: NÃO | Y69: NÃO | Z69: =$I$63 -> NÃO | AA69: =$H$62 -> NÃO | AB69: NÃO | AC69: =IF(COUNTIFS($H$1:$AB$1,"x",H69:AB69,"SIM")>0,(D69+E69+F69),0) -> 0.29166667 | AD69: =IF(COUNTIFS($H$1:$AB$1,"x",H69:AB69,"SIM")>0,G69) -> 0.11805556 | AE69: =COUNTIFS(H69:AB69,"SIM") -> 2
B70: 2.15 PVTabelaPrecoItem | C70: Avaliado | H70: =$H$41 -> NÃO | I70: NÃO | J70: NÃO | K70: NÃO | L70: SIM | M70: NÃO | N70: NÃO | O70: NÃO | P70: NÃO | Q70: NÃO | R70: NÃO | S70: NÃO | T70: NÃO | U70: NÃO | V70: SIM | W70: NÃO | X70: NÃO | Y70: NÃO | Z70: =$I$63 -> NÃO | AA70: =$H$62 -> NÃO | AB70: NÃO | AC70: =IF(COUNTIFS($H$1:$AB$1,"x",H70:AB70,"SIM")>0,(D70+E70+F70),0) -> 0 | AD70: =IF(COUNTIFS($H$1:$AB$1,"x",H70:AB70,"SIM")>0,G70) -> 0 | AE70: =COUNTIFS(H70:AB70,"SIM") -> 2
B71: 2.4 PVTabelaPreco | C71: Avaliado | H71: =$H$41 -> NÃO | I71: NÃO | J71: NÃO | K71: NÃO | L71: SIM | M71: NÃO | N71: NÃO | O71: NÃO | P71: NÃO | Q71: NÃO | R71: NÃO | S71: NÃO | T71: NÃO | U71: NÃO | V71: SIM | W71: NÃO | X71: NÃO | Y71: NÃO | Z71: =$I$63 -> NÃO | AA71: =$H$62 -> NÃO | AB71: NÃO | AC71: =IF(COUNTIFS($H$1:$AB$1,"x",H71:AB71,"SIM")>0,(D71+E71+F71),0) -> 0 | AD71: =IF(COUNTIFS($H$1:$AB$1,"x",H71:AB71,"SIM")>0,G71) -> 0 | AE71: =COUNTIFS(H71:AB71,"SIM") -> 2
B72: 2.16 PVTabelaPrecoItemProjecao | C72: Avaliado | H72: =$H$41 -> NÃO | I72: NÃO | J72: NÃO | K72: NÃO | L72: SIM | M72: NÃO | N72: NÃO | O72: NÃO | P72: NÃO | Q72: NÃO | R72: NÃO | S72: NÃO | T72: NÃO | U72: NÃO | V72: SIM | W72: NÃO | X72: NÃO | Y72: NÃO | Z72: =$I$63 -> NÃO | AA72: =$H$62 -> NÃO | AB72: NÃO | AC72: =IF(COUNTIFS($H$1:$AB$1,"x",H72:AB72,"SIM")>0,(D72+E72+F72),0) -> 0 | AD72: =IF(COUNTIFS($H$1:$AB$1,"x",H72:AB72,"SIM")>0,G72) -> 0 | AE72: =COUNTIFS(H72:AB72,"SIM") -> 2
B73: 2.6 PVTabelaPrecoUsuario | C73: Avaliado | H73: =$H$41 -> NÃO | I73: NÃO | J73: NÃO | K73: NÃO | L73: SIM | M73: NÃO | N73: NÃO | O73: NÃO | P73: NÃO | Q73: NÃO | R73: NÃO | S73: NÃO | T73: NÃO | U73: NÃO | V73: SIM | W73: NÃO | X73: NÃO | Y73: NÃO | Z73: =$I$63 -> NÃO | AA73: =$H$62 -> NÃO | AB73: NÃO | AC73: =IF(COUNTIFS($H$1:$AB$1,"x",H73:AB73,"SIM")>0,(D73+E73+F73),0) -> 0 | AD73: =IF(COUNTIFS($H$1:$AB$1,"x",H73:AB73,"SIM")>0,G73) -> 0 | AE73: =COUNTIFS(H73:AB73,"SIM") -> 2
B74: 2.7 PVTabelaPrecoFilial | C74: Avaliado | H74: =$H$41 -> NÃO | I74: NÃO | J74: NÃO | K74: NÃO | L74: SIM | M74: NÃO | N74: NÃO | O74: NÃO | P74: NÃO | Q74: NÃO | R74: NÃO | S74: NÃO | T74: NÃO | U74: NÃO | V74: SIM | W74: NÃO | X74: NÃO | Y74: NÃO | Z74: =$I$63 -> NÃO | AA74: =$H$62 -> NÃO | AB74: NÃO | AC74: =IF(COUNTIFS($H$1:$AB$1,"x",H74:AB74,"SIM")>0,(D74+E74+F74),0) -> 0 | AD74: =IF(COUNTIFS($H$1:$AB$1,"x",H74:AB74,"SIM")>0,G74) -> 0 | AE74: =COUNTIFS(H74:AB74,"SIM") -> 2
B75: 2.7 PVTabelaPrecoTipoParceiro | C75: Avaliado | H75: =$H$41 -> NÃO | I75: NÃO | J75: NÃO | K75: NÃO | L75: SIM | M75: NÃO | N75: NÃO | O75: NÃO | P75: NÃO | Q75: NÃO | R75: NÃO | S75: NÃO | T75: NÃO | U75: NÃO | V75: SIM | W75: NÃO | X75: NÃO | Y75: NÃO | Z75: =$I$63 -> NÃO | AA75: =$H$62 -> NÃO | AB75: NÃO | AC75: =IF(COUNTIFS($H$1:$AB$1,"x",H75:AB75,"SIM")>0,(D75+E75+F75),0) -> 0 | AD75: =IF(COUNTIFS($H$1:$AB$1,"x",H75:AB75,"SIM")>0,G75) -> 0 | AE75: =COUNTIFS(H75:AB75,"SIM") -> 2
B76: 2.7 PVTabelaPrecoSafra | C76: Avaliado | G76: 0 | H76: =$H$41 -> NÃO | I76: NÃO | J76: NÃO | K76: NÃO | L76: SIM | M76: NÃO | N76: NÃO | O76: NÃO | P76: NÃO | Q76: NÃO | R76: NÃO | S76: NÃO | T76: NÃO | U76: NÃO | V76: SIM | W76: NÃO | X76: NÃO | Y76: NÃO | Z76: =$I$63 -> NÃO | AA76: =$H$62 -> NÃO | AB76: NÃO | AC76: =IF(COUNTIFS($H$1:$AB$1,"x",H76:AB76,"SIM")>0,(D76+E76+F76),0) -> 0 | AD76: =IF(COUNTIFS($H$1:$AB$1,"x",H76:AB76,"SIM")>0,G76) -> 0 | AE76: =COUNTIFS(H76:AB76,"SIM") -> 2
A77: Força de venda - PV Tipo de Negociação | B77: 2.18 PVTipoDeNegociacao | C77: Avaliado | G77: 0.017361111 | H77: =$H$41 -> NÃO | I77: NÃO | J77: NÃO | K77: NÃO | L77: SIM | M77: NÃO | N77: NÃO | O77: NÃO | P77: NÃO | Q77: NÃO | R77: NÃO | S77: NÃO | T77: NÃO | U77: NÃO | V77: SIM | W77: NÃO | X77: NÃO | Y77: NÃO | Z77: =$I$63 -> NÃO | AA77: =$H$62 -> NÃO | AB77: NÃO | AC77: =IF(COUNTIFS($H$1:$AB$1,"x",H77:AB77,"SIM")>0,(D77+E77+F77),0) -> 0 | AD77: =IF(COUNTIFS($H$1:$AB$1,"x",H77:AB77,"SIM")>0,G77) -> 0.017361111 | AE77: =COUNTIFS(H77:AB77,"SIM") -> 2
A78: Força de venda - PV Condição de pagamento | B78: 2.10 PVCondicaoPagamento | C78: Avaliado | G78: 0.013888889 | H78: =$H$41 -> NÃO | I78: NÃO | J78: NÃO | K78: NÃO | L78: SIM | M78: NÃO | N78: NÃO | O78: NÃO | P78: NÃO | Q78: NÃO | R78: NÃO | S78: NÃO | T78: NÃO | U78: NÃO | V78: SIM | W78: NÃO | X78: NÃO | Y78: NÃO | Z78: =$I$63 -> NÃO | AA78: =$H$62 -> NÃO | AB78: NÃO | AC78: =IF(COUNTIFS($H$1:$AB$1,"x",H78:AB78,"SIM")>0,(D78+E78+F78),0) -> 0 | AD78: =IF(COUNTIFS($H$1:$AB$1,"x",H78:AB78,"SIM")>0,G78) -> 0.013888889 | AE78: =COUNTIFS(H78:AB78,"SIM") -> 2
A79: Força de venda - PV Condição de pagamento tipo documento cobrança | B79: 2,2 PVCondicaoPagamentoTipoDocumentoCobranca | C79: Avaliado | G79: 0.013888889 | H79: =$H$41 -> NÃO | I79: NÃO | J79: NÃO | K79: NÃO | L79: SIM | M79: NÃO | N79: NÃO | O79: NÃO | P79: NÃO | Q79: NÃO | R79: NÃO | S79: NÃO | T79: NÃO | U79: NÃO | V79: SIM | W79: NÃO | X79: NÃO | Y79: NÃO | Z79: =$I$63 -> NÃO | AA79: =$H$62 -> NÃO | AB79: NÃO | AC79: =IF(COUNTIFS($H$1:$AB$1,"x",H79:AB79,"SIM")>0,(D79+E79+F79),0) -> 0 | AD79: =IF(COUNTIFS($H$1:$AB$1,"x",H79:AB79,"SIM")>0,G79) -> 0.013888889 | AE79: =COUNTIFS(H79:AB79,"SIM") -> 2
A80: Força de venda - Cotação PTAX | B80: CotacaoPTAX | C80: Avaliado | G80: 0.013888889 | H80: =$H$41 -> NÃO | I80: NÃO | J80: NÃO | K80: NÃO | L80: SIM | M80: NÃO | N80: NÃO | O80: NÃO | P80: NÃO | Q80: NÃO | R80: NÃO | S80: NÃO | T80: NÃO | U80: NÃO | V80: SIM | W80: NÃO | X80: NÃO | Y80: NÃO | Z80: =$I$63 -> NÃO | AA80: =$H$62 -> NÃO | AB80: NÃO | AC80: =IF(COUNTIFS($H$1:$AB$1,"x",H80:AB80,"SIM")>0,(D80+E80+F80),0) -> 0 | AD80: =IF(COUNTIFS($H$1:$AB$1,"x",H80:AB80,"SIM")>0,G80) -> 0.013888889 | AE80: =COUNTIFS(H80:AB80,"SIM") -> 2
A81: Cadastro básico - Pessoa física complementar | B81: PessoaFisicaComplementar | C81: Avaliado | G81: 0.013888889 | H81: =$H$41 -> NÃO | I81: NÃO | J81: NÃO | K81: NÃO | L81: =$H$62 -> NÃO | M81: NÃO | N81: NÃO | O81: NÃO | P81: NÃO | Q81: NÃO | R81: NÃO | S81: NÃO | T81: NÃO | U81: NÃO | V81: SIM | W81: NÃO | X81: NÃO | Y81: NÃO | Z81: =$I$63 -> NÃO | AA81: =$H$62 -> NÃO | AB81: NÃO | AC81: =IF(COUNTIFS($H$1:$AB$1,"x",H81:AB81,"SIM")>0,(D81+E81+F81),0) -> 0 | AD81: =IF(COUNTIFS($H$1:$AB$1,"x",H81:AB81,"SIM")>0,G81) -> 0.013888889 | AE81: =COUNTIFS(H81:AB81,"SIM") -> 1
A82: Cadastro básico - Cônjuge | B82: Conjuge | C82: Avaliado | G82: 0.013888889 | H82: =$H$41 -> NÃO | I82: NÃO | J82: NÃO | K82: NÃO | L82: =$H$62 -> NÃO | M82: NÃO | N82: NÃO | O82: NÃO | P82: NÃO | Q82: NÃO | R82: NÃO | S82: NÃO | T82: NÃO | U82: NÃO | V82: SIM | W82: NÃO | X82: NÃO | Y82: NÃO | Z82: =$I$63 -> NÃO | AA82: =$H$62 -> NÃO | AB82: NÃO | AC82: =IF(COUNTIFS($H$1:$AB$1,"x",H82:AB82,"SIM")>0,(D82+E82+F82),0) -> 0 | AD82: =IF(COUNTIFS($H$1:$AB$1,"x",H82:AB82,"SIM")>0,G82) -> 0.013888889 | AE82: =COUNTIFS(H82:AB82,"SIM") -> 1
A83: Cadastro básico - Classificação de produto | B83: ClassificacaoProduto | C83: Avaliado | G83: 0.013888889 | H83: =$H$41 -> NÃO | I83: NÃO | J83: NÃO | K83: NÃO | L83: =$H$62 -> NÃO | M83: NÃO | N83: NÃO | O83: NÃO | P83: NÃO | Q83: NÃO | R83: NÃO | S83: NÃO | T83: NÃO | U83: NÃO | V83: SIM | W83: NÃO | X83: NÃO | Y83: NÃO | Z83: =$I$63 -> NÃO | AA83: =$H$62 -> NÃO | AB83: NÃO | AC83: =IF(COUNTIFS($H$1:$AB$1,"x",H83:AB83,"SIM")>0,(D83+E83+F83),0) -> 0 | AD83: =IF(COUNTIFS($H$1:$AB$1,"x",H83:AB83,"SIM")>0,G83) -> 0.013888889 | AE83: =COUNTIFS(H83:AB83,"SIM") -> 1
B84: 2.17 PVCondicaoPagamentoParcela | C84: Avaliado | H84: =$H$41 -> NÃO | I84: NÃO | J84: NÃO | K84: NÃO | L84: =$H$62 -> NÃO | M84: NÃO | N84: NÃO | O84: NÃO | P84: NÃO | Q84: NÃO | R84: NÃO | S84: NÃO | T84: NÃO | U84: NÃO | V84: NÃO | W84: NÃO | X84: NÃO | Y84: NÃO | Z84: =$I$63 -> NÃO | AA84: =$H$62 -> NÃO | AB84: NÃO | AC84: =IF(COUNTIFS($H$1:$AB$1,"x",H84:AB84,"SIM")>0,(D84+E84+F84),0) -> 0 | AD84: =IF(COUNTIFS($H$1:$AB$1,"x",H84:AB84,"SIM")>0,G84) -> FALSE | AE84: =COUNTIFS(H84:AB84,"SIM") -> 0
B85: 2.23 PVTabelaPrecoItemCondicao | C85: Avaliado | H85: =$H$41 -> NÃO | I85: NÃO | J85: NÃO | K85: NÃO | L85: =$H$62 -> NÃO | M85: NÃO | N85: NÃO | O85: NÃO | P85: NÃO | Q85: NÃO | R85: NÃO | S85: NÃO | T85: NÃO | U85: NÃO | V85: NÃO | W85: NÃO | X85: NÃO | Y85: NÃO | Z85: =$I$63 -> NÃO | AA85: =$H$62 -> NÃO | AB85: NÃO | AC85: =IF(COUNTIFS($H$1:$AB$1,"x",H85:AB85,"SIM")>0,(D85+E85+F85),0) -> 0 | AD85: =IF(COUNTIFS($H$1:$AB$1,"x",H85:AB85,"SIM")>0,G85) -> FALSE | AE85: =COUNTIFS(H85:AB85,"SIM") -> 0
B86: 2.25 Condição de Pagamento Safra | C86: Avaliado | H86: =$H$41 -> NÃO | I86: NÃO | J86: NÃO | K86: NÃO | L86: =$H$62 -> NÃO | M86: NÃO | N86: NÃO | O86: NÃO | P86: NÃO | Q86: NÃO | R86: NÃO | S86: NÃO | T86: NÃO | U86: NÃO | V86: NÃO | W86: NÃO | X86: NÃO | Y86: NÃO | Z86: =$I$63 -> NÃO | AA86: =$H$62 -> NÃO | AB86: NÃO | AC86: =IF(COUNTIFS($H$1:$AB$1,"x",H86:AB86,"SIM")>0,(D86+E86+F86),0) -> 0 | AD86: =IF(COUNTIFS($H$1:$AB$1,"x",H86:AB86,"SIM")>0,G86) -> FALSE | AE86: =COUNTIFS(H86:AB86,"SIM") -> 0
B87: 2.30 PVExcecaoCondicaoPagamento | C87: Avaliado | H87: =$H$41 -> NÃO | I87: NÃO | J87: NÃO | K87: NÃO | L87: =$H$62 -> NÃO | M87: NÃO | N87: NÃO | O87: NÃO | P87: NÃO | Q87: NÃO | R87: NÃO | S87: NÃO | T87: NÃO | U87: NÃO | V87: NÃO | W87: NÃO | X87: NÃO | Y87: NÃO | Z87: =$I$63 -> NÃO | AA87: =$H$62 -> NÃO | AB87: NÃO | AC87: =IF(COUNTIFS($H$1:$AB$1,"x",H87:AB87,"SIM")>0,(D87+E87+F87),0) -> 0 | AD87: =IF(COUNTIFS($H$1:$AB$1,"x",H87:AB87,"SIM")>0,G87) -> FALSE | AE87: =COUNTIFS(H87:AB87,"SIM") -> 0
B88: 2.31 PVExcecaoCondicaoPagamentoClasseProduto | C88: Avaliado | H88: =$H$41 -> NÃO | I88: NÃO | J88: NÃO | K88: NÃO | L88: =$H$62 -> NÃO | M88: NÃO | N88: NÃO | O88: NÃO | P88: NÃO | Q88: NÃO | R88: NÃO | S88: NÃO | T88: NÃO | U88: NÃO | V88: NÃO | W88: NÃO | X88: NÃO | Y88: NÃO | Z88: =$I$63 -> NÃO | AA88: =$H$62 -> NÃO | AB88: NÃO | AC88: =IF(COUNTIFS($H$1:$AB$1,"x",H88:AB88,"SIM")>0,(D88+E88+F88),0) -> 0 | AD88: =IF(COUNTIFS($H$1:$AB$1,"x",H88:AB88,"SIM")>0,G88) -> FALSE | AE88: =COUNTIFS(H88:AB88,"SIM") -> 0
B89: 2.32 PVExcecaoCondicaoPagamentoProduto | C89: Avaliado | H89: =$H$41 -> NÃO | I89: NÃO | J89: NÃO | K89: NÃO | L89: =$H$62 -> NÃO | M89: NÃO | N89: NÃO | O89: NÃO | P89: NÃO | Q89: NÃO | R89: NÃO | S89: NÃO | T89: NÃO | U89: NÃO | V89: NÃO | W89: NÃO | X89: NÃO | Y89: NÃO | Z89: =$I$63 -> NÃO | AA89: =$H$62 -> NÃO | AB89: NÃO | AC89: =IF(COUNTIFS($H$1:$AB$1,"x",H89:AB89,"SIM")>0,(D89+E89+F89),0) -> 0 | AD89: =IF(COUNTIFS($H$1:$AB$1,"x",H89:AB89,"SIM")>0,G89) -> FALSE | AE89: =COUNTIFS(H89:AB89,"SIM") -> 0
B90: 2.33 TabelaDePrecoExcecaoClasseDeProduto | C90: Avaliado | H90: =$H$41 -> NÃO | I90: NÃO | J90: NÃO | K90: NÃO | L90: =$H$62 -> NÃO | M90: NÃO | N90: NÃO | O90: NÃO | P90: NÃO | Q90: NÃO | R90: NÃO | S90: NÃO | T90: NÃO | U90: NÃO | V90: NÃO | W90: NÃO | X90: NÃO | Y90: NÃO | Z90: =$I$63 -> NÃO | AA90: =$H$62 -> NÃO | AB90: NÃO | AC90: =IF(COUNTIFS($H$1:$AB$1,"x",H90:AB90,"SIM")>0,(D90+E90+F90),0) -> 0 | AD90: =IF(COUNTIFS($H$1:$AB$1,"x",H90:AB90,"SIM")>0,G90) -> FALSE | AE90: =COUNTIFS(H90:AB90,"SIM") -> 0
B91: 2.13 PVExcecaoTabelaPreco | C91: Avaliado | H91: =$H$41 -> NÃO | I91: NÃO | J91: NÃO | K91: NÃO | L91: =$H$62 -> NÃO | M91: NÃO | N91: NÃO | O91: NÃO | P91: NÃO | Q91: NÃO | R91: NÃO | S91: NÃO | T91: NÃO | U91: NÃO | V91: NÃO | W91: NÃO | X91: NÃO | Y91: NÃO | Z91: =$I$63 -> NÃO | AA91: =$H$62 -> NÃO | AB91: NÃO | AC91: =IF(COUNTIFS($H$1:$AB$1,"x",H91:AB91,"SIM")>0,(D91+E91+F91),0) -> 0 | AD91: =IF(COUNTIFS($H$1:$AB$1,"x",H91:AB91,"SIM")>0,G91) -> FALSE | AE91: =COUNTIFS(H91:AB91,"SIM") -> 0
B92: 2.14 PVExcecaoTabelaPrecoItem | C92: Avaliado | H92: =$H$41 -> NÃO | I92: NÃO | J92: NÃO | K92: NÃO | L92: =$H$62 -> NÃO | M92: NÃO | N92: NÃO | O92: NÃO | P92: NÃO | Q92: NÃO | R92: NÃO | S92: NÃO | T92: NÃO | U92: NÃO | V92: NÃO | W92: NÃO | X92: NÃO | Y92: NÃO | Z92: =$I$63 -> NÃO | AA92: =$H$62 -> NÃO | AB92: NÃO | AC92: =IF(COUNTIFS($H$1:$AB$1,"x",H92:AB92,"SIM")>0,(D92+E92+F92),0) -> 0 | AD92: =IF(COUNTIFS($H$1:$AB$1,"x",H92:AB92,"SIM")>0,G92) -> FALSE | AE92: =COUNTIFS(H92:AB92,"SIM") -> 0
B93: 2.8 PVTabelaPrecoLocalFaturamento | C93: Avaliado | H93: =$H$41 -> NÃO | I93: NÃO | J93: NÃO | K93: NÃO | L93: =$H$62 -> NÃO | M93: NÃO | N93: NÃO | O93: NÃO | P93: NÃO | Q93: NÃO | R93: NÃO | S93: NÃO | T93: NÃO | U93: NÃO | V93: NÃO | W93: NÃO | X93: NÃO | Y93: NÃO | Z93: =$I$63 -> NÃO | AA93: =$H$62 -> NÃO | AB93: NÃO | AC93: =IF(COUNTIFS($H$1:$AB$1,"x",H93:AB93,"SIM")>0,(D93+E93+F93),0) -> 0 | AD93: =IF(COUNTIFS($H$1:$AB$1,"x",H93:AB93,"SIM")>0,G93) -> FALSE | AE93: =COUNTIFS(H93:AB93,"SIM") -> 0
B94: 2.9 PVTabelaPrecoUFDestino | C94: Avaliado | H94: =$H$41 -> NÃO | I94: NÃO | J94: NÃO | K94: NÃO | L94: =$H$62 -> NÃO | M94: NÃO | N94: NÃO | O94: NÃO | P94: NÃO | Q94: NÃO | R94: NÃO | S94: NÃO | T94: NÃO | U94: NÃO | V94: NÃO | W94: NÃO | X94: NÃO | Y94: NÃO | Z94: =$I$63 -> NÃO | AA94: =$H$62 -> NÃO | AB94: NÃO | AC94: =IF(COUNTIFS($H$1:$AB$1,"x",H94:AB94,"SIM")>0,(D94+E94+F94),0) -> 0 | AD94: =IF(COUNTIFS($H$1:$AB$1,"x",H94:AB94,"SIM")>0,G94) -> FALSE | AE94: =COUNTIFS(H94:AB94,"SIM") -> 0
B95: 2.36 PVCampanhaTrocaFilial | C95: Avaliado | H95: =$H$41 -> NÃO | I95: NÃO | J95: NÃO | K95: NÃO | L95: =$H$62 -> NÃO | M95: NÃO | N95: NÃO | O95: NÃO | P95: NÃO | Q95: NÃO | R95: NÃO | S95: NÃO | T95: NÃO | U95: NÃO | V95: NÃO | W95: NÃO | X95: NÃO | Y95: NÃO | Z95: =$I$63 -> NÃO | AA95: =$H$62 -> NÃO | AB95: NÃO | AC95: =IF(COUNTIFS($H$1:$AB$1,"x",H95:AB95,"SIM")>0,(D95+E95+F95),0) -> 0 | AD95: =IF(COUNTIFS($H$1:$AB$1,"x",H95:AB95,"SIM")>0,G95) -> FALSE | AE95: =COUNTIFS(H95:AB95,"SIM") -> 0
... B111: 5.0 Integrar Gestão de Eventos | C111: Avaliado | H111: =$H$41 -> NÃO | I111: NÃO | J111: NÃO | K111: NÃO | L111: =$H$62 -> NÃO | M111: NÃO | N111: NÃO | O111: NÃO | P111: NÃO | Q111: NÃO | R111: NÃO | S111: NÃO | T111: NÃO | U111: NÃO | V111: NÃO | W111: NÃO | X111: NÃO | Y111: NÃO | Z111: =$I$63 -> NÃO | AA111: =$H$62 -> NÃO | AB111: NÃO | AC111: =IF(COUNTIFS($H$1:$AB$1,"x",H111:AB111,"SIM")>0,(D111+E111+F111),0) -> 0 | AD111: =IF(COUNTIFS($H$1:$AB$1,"x",H111:AB111,"SIM")>0,G111) -> FALSE | AE111: =COUNTIFS(H111:AB111,"SIM") -> 0
D112: =SUM(D3:D111) -> 4.1527778 | E112: =SUM(E3:E111) -> 0 | F112: =SUM(F3:F111) -> 0.77083333 | G112: =SUM(G3:G111) -> 1.4340278 | AC112: =SUM(AC3:AC111) -> 3.6875 | AD112: =SUM(AD3:AD111) -> 1.1597222
A116: Tipos de integração | B116: horas
A117: Estimativa de horas geral API padrão | B117: 11.958333 | C117: está sendo usada
A118: Estimativa de horas validação de dados API padrão | B118: 9.375 | C118: não estamos usando
...

Sheet Valor
A1: Lista de ERPs de Terceiro | D1: Tipos de Integração ERP | F1: Regra para treinamentos | G1: Parametro | H1: Nº de Consultores
A2: ALIARE - SOLUTION | D2: API padrão ERP | F2: Até 24 pessoas por turma | G2: 24 | H2: 1
A3: CIGAM | D3: =IF(Resumo!C5="ALIARE - AGB","Integração (antiga)","API customizada ERP ") -> API customizada ERP | F3: 25 ou mais usuários por turma | G3: 25 | H3: 2
A4: DATAPAR | D4: Sem integração
A5: MICROSFOT DINAMICS
A6: SANKHYA
A7: SAP 4H
A8: SAP B1
A9: SAP R3
A10: TOTVS - DATASUL
A11: TOTVS - PROTHEUS
A12: TOTVS - PROTHEUS 9 <
A13: VIASOFT
A14: OUTROS

Sheet AGBCLOVER-Listagem dos fluxos
A1: FLUXOS DE INTEGRAÇÃO | B1: Dividido | C1: Obrigatório? | D1: Vai Integrar? (S/N) | E1: TABELA | F1: QTD. REGISTROS PARA CARGA INICIAL DE DADOS | G1: Observação
A2: Cadastro básico - Classe de produto | B2: Não | C2: X | D2: =IF(AND(Funcionalidades!$A$4="X", Funcionalidades!$D$55="X"), "SIM", "NÃO") -> SIM | E2: Local (Endereços) | G2: AGB: Soma da quantida de Parceiros e Propriedades Simer: Quantidade de Locais ERP Terceiros: Quantidade que virá para Local no Clover
A3: Cadastro básico - Cônjuge | B3: Não | D3: =IF(AND(Funcionalidades!$A$4="X", Funcionalidades!$D$20="X"), "SIM", "NÃO") -> NÃO | E3: produto | F3: 0
A4: Cadastro básico - Cultura | B4: Não | C4: X | D4: =IF(AND(Funcionalidades!$A$4="X", Funcionalidades!$D$11="X"), "SIM", "NÃO") -> SIM | E4: tabela de preço | F4: 0
A5: Cadastro básico - Empresa | B5: Não | C5: X | D5: =IF(AND(Funcionalidades!$A$4="X", Funcionalidades!$D$4="X"), "SIM", "NÃO") -> SIM | E5: notas da empresa | F5: 0
A6: Cadastro básico - Estoque | B6: Não | C6: X | D6: =IF(AND(Funcionalidades!$A$4="X", Funcionalidades!$D$166="X"), "SIM", "NÃO") -> SIM | E6: pedido em carteira | F6: 0
A7: Cadastro básico - Estoque Ciclo | D7: =IF(AND(Funcionalidades!$A$4="X", Funcionalidades!$D$165="X"), "SIM", "NÃO") -> SIM | E7: titulos em aberto | F7: 0
A8: Cadastro básico - Fornecedor | B8: Não | D8: =IF(AND(Funcionalidades!$A$4="X", Funcionalidades!$D$167="X"), "SIM", "NÃO") -> SIM
A9: Cadastro básico - Limite de crédito parceiro | B9: Não | D9: SIM | E9: ATENÇÃO: Não atualize a planilha do Sharepoint. Baixe uma cópia em seu computador
A10: Cadastro básico - Limite de crédito safra | B10: Não | D10: =IF(AND(Funcionalidades!$A$4="X", Funcionalidades!$D$167="X"), "SIM", "NÃO") -> SIM
A11: Cadastro básico - Local (Propriedade) – Parte 1 | B11: Sim | C11: X | D11: =IF(AND(Funcionalidades!$A$4="X", Funcionalidades!$D$27="X"), "SIM", "NÃO") -> SIM | E11: SOMATÓRIA DE NÚMERO DE REGISTROS PARA CARGA INICIAL | G11: Fator de Complexidade Agrupada | H11: Regra
A12: Cadastro básico - País, Estado e Cidade | B12: Não | C12: X | D12: =IF(AND(Funcionalidades!$A$4="X", Funcionalidades!$D$7="X"), "SIM", "NÃO") -> SIM | E12: Cadastros básicos e força de vendas | F12: =SUM(F2:F4) -> 0 | G12: =IF(F12<10000,0,IF(AND(F12>=10000,F12<50000),0.1,IF(AND(F12>=50000,F12<150000),0.2,IF(F12>=150000,9999,1)))) -> 0 | H12: Se < 10k então *1, se entre 10k e 50k então *1,1, se entre 50k e 150k então *1,2, se > 150k então CONSULTAR TIME DE INTEGRAÇÃO
A13: Cadastro básico - Parceiro tipo parceiro | B13: Não | C13: X | D13: =IF(AND(Funcionalidades!$A$4="X", Funcionalidades!$D$21="X"), "SIM", "NÃO") -> NÃO | E13: Movimentação financeira | F13: =SUM(F5:F7) -> 0 | G13: =IF(F13<50000,0,IF(AND(F13>=50000,F13<150000),0.1,IF(AND(F13>=150000,F13<500000),0.2,IF(F13>=500000,9999,1)))) -> 0 | H13: Se < 50k então *1, se entre 50k e 150k então *1,1, se entre 150k e 500k então *1,2, se > 500k então CONSULTAR TIME DE INTEGRAÇÃO
A14: Cadastro básico - Parceiro, Local (Empresa), Filial e Local (Parceiro) – Parte 1 | B14: Sim | C14: X | D14: =IF(AND(Funcionalidades!$A$4="X", Funcionalidades!$D$16="X"), "SIM", "NÃO") -> SIM | E14: TOTAL | G14: =1+G13+G12 -> 1
A15: Cadastro básico - Pessoa física complementar | B15: Não | D15: =IF(AND(Funcionalidades!$A$4="X", Funcionalidades!$D$16="X"), "SIM", "NÃO") -> SIM
A16: Cadastro básico - Produto e produto classe | B16: Não | C16: X | D16: =IF(AND(Funcionalidades!$A$4="X", Funcionalidades!$D$55="X"), "SIM", "NÃO") -> SIM
A17: Cadastro básico - Propriedade, Vínculo imobiliário, Arrendamento e Posse – Parte 1 | B17: Sim | D17: =IF(AND(Funcionalidades!$A$4="X", Funcionalidades!$D$15="X"), "SIM", "NÃO") -> SIM
A18: Cadastro básico – Atualizar dados das propriedades no ERP | B18: Não | D18: NÃO
A19: Cadastro básico - Região | B19: Não | C19: X | D19: =IF(AND(Funcionalidades!$A$4="X", Funcionalidades!$D$14="X"), "SIM", "NÃO") -> SIM
A20: Cadastro básico - Região local | B20: Não | C20: X | D20: =IF(AND(Funcionalidades!$A$4="X", Funcionalidades!$D$14="X"), "SIM", "NÃO") -> SIM
A21: Cadastro básico - Região local - Vínculo vendedor <> cliente | B21: Não | D21: =IF(AND(Funcionalidades!$A$4="X", Funcionalidades!$D$14="X"), "SIM", "NÃO") -> SIM
A22: Cadastro básico - Registrante | B22: Não | D22: =IF(AND(Funcionalidades!$A$4="X", Funcionalidades!$D$167="X"), "SIM", "NÃO") -> SIM
A23: Cadastro básico - Safra | B23: Não | C23: X | D23: =IF(AND(Funcionalidades!$A$4="X", Funcionalidades!$D$10="X"), "SIM", "NÃO") -> SIM
A24: Cadastro básico - Silo | B24: Não | D24: =IF(AND(Funcionalidades!$A$143="X", Funcionalidades!$D$162="X"), "SIM", "NÃO") -> NÃO
A25: Cadastro básico - Tipo parceiro | B25: Não | C25: X | D25: =IF(AND(Funcionalidades!$A$4="X", Funcionalidades!$D$21="X"), "SIM", "NÃO") -> NÃO
A26: Cadastro básico - Unidade de medida | B26: Não | C26: X | D26: =IF(AND(Funcionalidades!$A$4="X", Funcionalidades!$D$9="X"), "SIM", "NÃO") -> SIM
A27: Cadastro básico - Usuário empresa, Usuario filial e Usuario parceiro | B27: Não | C27: X | D27: =IF(AND(Funcionalidades!$A$4="X", Funcionalidades!$D$4="X", Funcionalidades!$D$16="X"), "SIM", "NÃO") -> SIM
A28: Cadastro básico - Usuário região | B28: Não | D28: =IF(AND(Funcionalidades!$A$4="X", Funcionalidades!$D$42="X"), "SIM", "NÃO") -> SIM
A29: Cadastro básico - Usuários | B29: Não | C29: X | D29: =IF(AND(Funcionalidades!$A$4="X", Funcionalidades!$D$36="X"), "SIM", "NÃO") -> SIM
A30: Cadastro básico - Veiculo | B30: Não | D30: =IF(AND(Funcionalidades!$A$194="X", Funcionalidades!$D$197="X"), "SIM", "NÃO") -> NÃO
A31: Cadastro básico - Modalidade Recolhimento Funrural | B31: Não | D31: =IF(AND(Funcionalidades!$A$143="X", Funcionalidades!$D$163="X"), "SIM", "NÃO") -> NÃO
A32: Cadastro básico - PV Receituario Agronomico | B32: Não | D32: NÃO
A33: Força de venda - Encerrar Vigência de PVTabelaPrecoItem | B33: Não | C33: X | D33: =IF(AND(Funcionalidades!$A$143="X", Funcionalidades!$D$154="X"), "SIM", "NÃO") -> NÃO
A34: Força de venda - PV Condição de pagamento | B34: Não | C34: X | D34: =IF(AND(Funcionalidades!$A$143="X", Funcionalidades!$D$152="X"), "SIM", "NÃO") -> NÃO
A35: Força de venda - PV Condição de pagamento tipo documento cobrança | B35: Não | C35: X | D35: =IF(AND(Funcionalidades!$A$143="X", Funcionalidades!$D$153="X"), "SIM", "NÃO") -> NÃO
A36: Força de venda - PV Tabelas de preço | B36: Não | C36: X | D36: =IF(AND(Funcionalidades!$A$143="X", Funcionalidades!$D$154="X"), "SIM", "NÃO") -> NÃO
A37: Força de venda - PV Tipo documento cobrança | B37: Não | C37: X | D37: =IF(AND(Funcionalidades!$A$143="X", Funcionalidades!$D$151="X"), "SIM", "NÃO") -> NÃO
A38: Movimentação financeira - Faturamento mensal | B38: Sim | D38: =IF(AND(Funcionalidades!$A$127="X", OR(Funcionalidades!$D$138="X", Funcionalidades!$D$139="X")), "SIM", "NÃO") -> NÃO
A39: Movimentação financeira - Local nota fiscal - Desfazimento de entrega futura | B39: Não | D39: =IF(AND(Funcionalidades!$A$101="X", Funcionalidades!$D$109="X"), "SIM", "NÃO") -> NÃO
A40: Movimentação financeira - Local nota fiscal - Notas da empresa | B40: Não | D40: =IF(AND(Funcionalidades!$A$101="X", Funcionalidades!$D$109="X"), "SIM", "NÃO") -> NÃO
A41: Movimentação financeira - Local nota fiscal - Notas de terceiro | B41: Não | D41: =IF(AND(Funcionalidades!$A$101="X", Funcionalidades!$D$109="X"), "SIM", "NÃO") -> NÃO
A42: Movimentação financeira - Títulos | B42: Não | D42: =IF(AND(Funcionalidades!$A$143="X", Funcionalidades!$D$168="X"), "SIM", "NÃO") -> SIM
A43: Exportação de pedidos - Lançamento de pedido no AGB | B43: Não | C43: X | D43: =IF(AND(Funcionalidades!$A$143="X", Funcionalidades!$D$146="X"), "SIM", "NÃO") -> SIM
A44: Exportação de pedidos - PVPedidoHistoricoSituacao, PVPedidoItemHistoricoSituacao, PVPedidoItemNotaFiscal | B44: Não | D44: =IF(AND(Funcionalidades!$A$143="X", Funcionalidades!$D$149="X"), "SIM", "NÃO") -> NÃO
A45: Exportação de pedidos - Lançamento de pedido Barter | B45: Não | D45: =IF(AND(Funcionalidades!$A$143="X", Funcionalidades!$D$164="X"), "SIM", "NÃO") -> NÃO

Sheet AGBCLOVER-Variáveis Al. Integra
A1: CATEGORIA | B1: FLUXO | C1: VARIÁVEL | D1: COMO PREENCHER? | E1: OBRIGATÓRIO? | F1: VALOR
A2: Cadastro básico | B2: Parceiro, Local (Empresa), Filial e Local (Parceiro) | C2: Integrar parceiro superior | D2: Informar “S” para integrar e “N” para não integrar, precisa ser validado com o cliente, pois isso afeta alguns processos dentro do clover. | E2: Não, se não preenche, será considerado a opção "NÃO".
C3: Considerar o bloqueio por crédito | D3: Informar "S" para bloquear os parceiros pelo crédito e "N" para não bloquear, mas precisa validar o processo do cliente, isso afeta na hora de emitir um pedido no Clover, caso ele esteja bloqueado. | E3: Não, se não preenche, será considerado a opção "NÃO".
C4: Enviar os fornecedores | D4: Informar "S" para enviar os parceiros com a flag de fornecedor para o Clover. | E4: Não, se não preenche, será considerado a opção "NÃO".
C5: Categoria de fornecedores validos | D5: Caso seja escolhido enviar os parceiros fornecedores deverá ser informado se são todas as categorias de fornecedores validos os se serão todos. | E5: Não, se não preenche, será considerado a opção "NÃO".
C6: Usar endereço de cobrança para o parceiro como local | D6: Informar "S" para enviar o endereço de cobrança no cadastro de local. | E6: Não, se não preenche, será considerado a opção "NÃO".
C7: Matrizes e filiais válidas | D7: Informar código das empresas (matrizes e filiais) que devem ser consideradas na integração. Se informar esse filtro, não deve ser informado o filtro abaixo com sentido contrário (Matrizes e filiais inválidas). Nesse formato, se o cliente cadastrar uma nova empresa, o cadastro da filial e seus respectivos parceiros e locais não serão levados automaticamente ao Clover, sendo necessário solicitar carga de dados via ticket. | E7: Não, se não preenche, todos serão considerados.
C8: Matrizes e filiais inválidas | D8: Informar código das empresas (matrizes e filiais) que devem ser desconsideradas da integração. Se informar esse filtro, não deve ser informado o filtro acima com sentido contrário (Matrizes e filiais válidas). Criamos esta possibilidade de 'empresas para desconsiderar' a fim de tratar automaticamente o caso onde o cliente inclui uma nova empresa e deseja levar os dados automaticamente para o Clover. | E8: Não, se não preenche, todos serão considerados.
C9: Matriz principal | D9: Informar o código de uma única matriz principal. | E9: Sim
B10: Empresa
C11: Matrizes válidas | D11: Informar o código das matrizes válidas para integração. No CLOVER CRM estas matrizes serão consideradas como EMPRESA | E11: Não, se não preenche, todos serão considerados.
B12: Classe de produto | C12: Grupos de produto válidos | D12: Informar somente os códigos de grupos de produto escolhidos pelo cliente. | E12: Não, se não preenche, todos serão considerados.
C13: SubGrupos válidos | D13: Informar somente os códigos dos grupos concatenados com os códigos de subgrupos escolhidos pelo cliente. Exemplo ‘1#1’ ou ‘1#*’ para todos os subgrupos do grupo selecionado. | E13: Não, se não preenche, todos serão considerados.
C14: Utiliza principio ativo ou classificação produto como produto superior? | D14: Informar "P" caso o cliente trabalhe com produto superior, e será cadastrado uma classe de produto fixo chamada "Principio Ativo" Informar "C" caso o cliente trabalhe com produto superior, e será cadastrado uma classe de produto fixo chamada "Classificação Produto" Informar "N" caso o cliente não trabalhe com nenhuma das opções. | E14: Não, se não preenche, será considerado "N"
B15: Usuário | C15: Grupos de usuário válidos | D15: Informar somente os códigos de grupos de usuário escolhidos pelo cliente. | E15: Não, se não preenche, todos serão considerados.
C16: Cargos válidos | D16: Informar somente os códigos de cargos de usuário escolhidos pelo cliente. | E16: Não, se não preenche, todos serão considerados.
C17: Departamentos válidos | D17: Informar somente os códigos de departamentos de usuário escolhidos pelo cliente. | E17: Não, se não preenche, todos serão considerados.
C18: Senha Padrão | D18: Informar a senha padrão utilizada pelo cliente em novos usuários do Clover. | E18: Não, se não preenche, será definido a senha 123456.
C19: Considerar apenas vendedores | D19: Informar se deve ser considerado apenas vendedores como usuários. | E19: Não, se não preenche, todos serão considerados.
C20: Categoria de vendedores válidos | D20: Informar somente os códigos de categoria de vendedores escolhidos pelo cliente. | E20: Não, se não preenche, todos serão considerados.
C21: Utiliza autenticação WSO2? | D21: Informar se o cliente utiliza autenticação WSO2, S ou N. | E21: Não, se não preenche, será considerado a opção "NÃO".
B22: Estoque | C22: Considera estoque por ciclo | D22: Informar se o cliente utiliza estoque por ciclo, SIM ou NÃO. | E22: Não, se não preenche, será considerado a opção "NÃO".
C23: Considerar fisicoDisponivelFaturamento | D23: Informar se o cliente utiliza o estoque fisico por "fisicoDisponivelFaturamento", SIM ou NÃO. | E23: Não, se não preenche, será considerado a opção "NÃO".
B24: Cultura | C24: Culturas válidas | D24: Informar somente os códigos das culturas escolhidas pelo cliente. | E24: Não, se não preenche, todos serão considerados.
B25: Safra | C25: Culturas de hortifrúti válidas | D25: Informar somente os códigos das culturas de hortifruti válidas pra integração. | E25: Somente se o cliente trabalha com hortifrúti.
C26: Data de ínicio do ciclo | D26: Informar uma data de corte para integração dos ciclos. | E26: Sim
B27: Tipo Parceiro | C27: Categorias de clientes válidas | D27: Informar o código das categorias dos clientes que são válidas para integração. | E27: Não, se não preenche, todos serão considerados.
B28: Silo | C28: Depósitos válidos | D28: Informar o código dos depósitos válidos para integração. | E28: Não, se não preenche, todos serão considerados. | G28: PREENCHER APENAS SE O CLIENTE CONTEMPLA FLUXO DE SILO
B29: Região | C29: Empresas válidas | D29: Caso atípico onde o cliente deseja integrar região (cadastro de pessoa no ERP) de empresas específicas. Basta informar o código das empresas separado por vírgula. | E29: Não, se não preenche, todos serão considerados.
B30: Região Local | C30: Considerar Segundo Vendedor | D30: Informar se o cliente deseja considerar o Segundo Vendedor vinculado à Propriedade para integrar na carteira. | E30: Não, se não preenche, será considerado a opção "NÃO".
B31: Propriedades, Vinc. Imobiliário, Posse e Arrendamento | C31: Considerar áreas zeradas (Valor padrão igual a 1) | D31: Informar se o cliente deseja enviar as propriedades com áera igual a 0, visto que o Clover não aceita o valor zero na área o campo será preenchido como 1. | E31: Não, se não preenchido será considerado a opção "Não".
B32: Limite de crédido por parceiro | C32: Considera Limite Condicionado (Limite + Limite Garantia) | D32: Informar se o cliente quer que some o valor do limite de garantia no valor do limite principal, caso não marque será enviado como 'N'. | E32: Não, se não preenchido será considerado a opção "Não".
A33: Força de Venda | B33: PV Tipo Documento Cobrança | C33: Formas de pagamento válidas | D33: Informar somente os códigos das formas de pagamento escolhidas pelo cliente. O AGB possui as seguintes formas de pagamentos fixas: 01 – Dinheiro | 02 - Cartão de Crédito | 03 – Duplicata | 04 – Cheque | 05 - Dinheiro / Cartão de Crédito | 06 - Dinheiro / Cheque | 07 - Dinheiro / Duplicata | 08 - Cheque / Duplicata | 09 – Carnê | 10 – Boleto | 11 - Cartão de Débito | 99 - Outros | E33: Não, se não preenche, todos serão considerados.
B34: PV Tabela de preço | C34: Indexadores válidos | D34: Informar somente os códigos dos indexadores escolhidos pelo cliente. | E34: Não, se não preenche, todos serão considerados.
C35: Tabelas válidas | D35: Informar somente os códigos das tabelas de preço escolhidas pelo cliente. | E35: Não, se não preenche, todos serão considerados.
C36: Utiliza validade da tabela como vencimento limite da item projeção? | D36: Informar "S" para considerar a validade da tabela de preço na vencimento data limite do item projeção do Clover. Informar "N" para o método padrão, que considera vencimento máximo ou vencimento data limite da base fixa por grupo. | E36: Não, se não preenche, será considerado a opção "NÃO".
C37: Código do tipo de desconto padrão (Clover) | D37: Informar o código do tipo de desconto padrão para as tabelas de preço no Clover. | E37: Não, se não preenche, será enviado "1" padrão.
B38: PV Condição Pagamento | C38: Condições válidas | D38: Informar os códigos das condições escolhidas pelo cliente. | E38: Não, se não preenche, todos serão considerados.
C39: Ajustar configurações para cálculo da data base? | D39: Informar "S" caso precise configurar o calculo da data base da condição via integração | E39: Não, se não preenche, será considerado a opção "SIM".
A40: Exportação de pedido | B40: Lançamento de pedido no AGB | C40: Considera mais de um deposito | D40: Informar se o cliente usa depósitos diferentes por filial, caso seja valido informar como “S”, E informar quais são os depósitos por filial, lembrando que tem que ser apenas 1 por filial, pois será tratado em uma equivalência esses dados. | E40: Não, se não preenche, será considerado a opção "NÃO".
C41: Utiliza série por tipo operação? | D41: Informar "S" se será feito o de/para de série por operação | E41: Não, se não preenche, será considerado a opção "NÃO".
C42: Operações por série | D42: Caso tenha o de/para de operação e série, informar a operação e a série separada por "#". EX: "20#1" | E42: Não, se não preenche, será considerado a opção "NÃO".
C43: Será enviado as datas detalhadas? | D43: Informar "S" para enviar as datas detalhas para a tela de calendarização do ERP. | E43: Não, se não preenche, será considerado a opção "NÃO".
C44: Será enviado o pré-financeiro? | D44: Informar "S" para enviar as parcelas para o pré-financeiro da tela de pedido. | E44: Não, se não preenche, será considerado a opção "NÃO".
C45: Será enviado pedidos de venda direta? | D45: Informar "S" para enviar o tipo do faturamento do tipo 2 (De terceiro) e o código da revenda. OBS: É preciso que seja enviado os parceiros fornecedores para tabela de parceiro, e é obriatório que o cliente vincule a região com o parceiro revenda de forma manual. | E45: Não, se não preenche, será considerado a opção "NÃO".
C46: Usar chave do parceiro vendedor vinculado ao usuário? | D46: Informar "S" para indicar que deve ser buscada a chave do parceiro vinculada ao usuário (usuarioparceiro). Essa função é utilizada quando o cliente cadastra usuários manualmente no Clover. Nesses casos, o usuário não possui chaveERP. Para que seja possível enviar o código do vendedor (Pessoal no ERP), o cliente deve manter o vínculo do usuarioparceiro com o parceiro criado a partir da entidade Pessoal, que possui a chaveERP identificada pela tag "VEND#". | E46: Não, se não preenche, será considerado a opção "NÃO".
C47: Deposito padrão | D47: Informar o código do depósito que será utilizado para integrar os pedidos de venda no ERP. | E47: Sim
C48: Utiliza valor unitário liquido da tabela de preço | D48: Preencher SIM ou NÃO: SIM = Será enviado o valor unitário da tabela de preço com o desconto/acrescimo separado. NÃO = Envia direto o valor liquido sem desconto/acrescimo. | E48: Não, se não preenche, será considerado a opção "SIM".
A49: Movimentação Financeira | B49: Faturamento Mensal | C49: Data de corte | D49: Informar a data de corte para considerar apenas pedidos emitidos a partir dessa data. | E49: Sim | G49: PREENCHER APENAS SE O CLIENTE CONTEMPLA FLUXOS DE MOVIMENTAÇÃO FINANCEIRA
C50: Indexador do dólar | D50: Informar o código do indexador de dólar. | E50: Sim
C51: Operações | D51: Informar código das operações que devem ser consideradas. | E51: Não, se não preenche, todos serão considerados.
B52: Local Nota Fiscal (notas da empresa) | C52: Data de corte | D52: Informar a data de corte para considerar apenas notas emitidas a partir dessa data. | E52: Sim
C53: Considerar desconto da oferta no valor total? | D53: Preencher SIM ou NÃO: SIM = Será enviado o valor da nota considerando o desconto o desconto da oferta. NÃO = Envia direto o valor sem considerar o desconto da oferta. | E53: Não, se não preenche, será considerado a opção "NÃO".
C54: Código param. função do tipo de operação | D54: Informar o código do parametrizador de função dos tipos de operação que deve ser considerado para notas da empresa. | E54: Sim
B55: Local Nota Fiscal (notas de terceiros) | C55: Data de corte | D55: Informar a data de corte para considerar apenas notas recebidas a partir dessa data. | E55: Sim
C56: Código param. função do tipo de operação | D56: Informar o código do parametrizador de função dos tipos de operação que deve ser considerado para notas de terceiros. | E56: Sim
B57: Local Nota Fiscal (desfazimento entrega futura) | C57: Código param. função do tipo de operação | D57: Informar o código do parametrizador de função dos tipos de operação que deve ser considerado para desfazimentos de entrega futura. | E57: Sim
B58: Títulos | C58: Data de corte | D58: Informar a data de corte para considerar apenas títulos emitidos a partir dessa data. | E58: Sim
A59: Configuração de e-mail | B59: Fluxo Geral de Integração / Exportação | C59: Cliente deseja receber e-mail do resumo de integração e pedido? | D59: Preencher SIM ou NÃO: Informar se o cliente deseja receber e-mail de resumo da integração de dados. Caso SIM, deve ser preenchido os dados de SMTP abaixo. | E59: Não, se não preenche, será considerado a opção "NÃO".
C60: Enviar e-mail somente quando houver erros? | D60: Preencher SIM ou NÃO: Caso a opção anterior seja "SIM", deseja receber o e-mail somente quando houver erros? | E60: Não, se não preenche, não será enviado e-mail. | G60: PREENCHER APENAS SE O CLIENTE DESEJA O ENVIO DE E-MAIL
A61: Dados SMTP | B61: Fluxo Geral de Integração / Exportação | C61: Usuário | D61: Informar o Usuário do SMTP. | E61: Não, se não preenche, não será enviado e-mail.
C62: Senha | D62: Informar a Senha do SMTP. | E62: Não, se não preenche, não será enviado e-mail.
C63: Host | D63: Informar o Host do SMTP. | E63: Não, se não preenche, não será enviado e-mail.
C64: Porta | D64: Informar a Porta do SMTP. | E64: Não, se não preenche, não será enviado e-mail.
C65: SSL / TLS | D65: Preencher SIM ou NÃO: Informar se utiliza SSL / TLS. | E65: Não, se não preenche, não será enviado e-mail.
C66: E-mails para recebimento de notificações da integração | D66: Informe os e-mails que receberão os resumos referentes às execuções dos fluxos orquestradores da integração e da exportação de pedidos. | E66: Não, se não preenche, não será enviado e-mail.
A75: CONTROLE DE VERSÃO - DESTINADO A INFORMAR ALTERAÇÃO NOS DADOS PREENCHIDOS PELOS CONSULTORES DO CLOVER CRM
A76: DATA | B76: RESPONSÁVEL | C76: VERSÃO | D76: ALTERAÇÕES
A98: CONTROLE DE VERSÃO - DESTINADO A INFORMAR ALTERAÇÕES NA ESTRUTURA DO DOCUMENTO FEITO PELA ALIARE INTEGRA
A99: DATA | B99: RESPONSÁVEL | C99: VERSÃO | D99: ALTERAÇÕES

Sheet SIMERCLOVER-Listagem dos fluxos
A1: FLUXOS | B1: Obrigatório | C1: Vai Integrar ? (S/N) | D1: Consideração Clover | H1: TABELA | I1: QTD. REGISTROS
A2: 1 - País | B2: Sim | H2: pessoa
A3: 2 - Unidade Federativa | B3: Sim | H3: local
A4: 3 - Cidade | B4: Sim | H4: produto
A5: 4 - Unidade de medida | B5: Não | H5: pedido
A6: 5 - Parceiro, Pessoa Física e Jurídica | B6: Sim | H6: documentos de faturamento
A7: 5.1 - Pessoa Física | B7: Sim
A8: 5.2 - Pessoa Jurídica | B8: Sim
A9: 6 - Propriedade | B9: Não
A10: 7 - Local | B10: Sim | H10: ATENÇÃO: Não atualize a planilha do Sharepoint. Baixe uma cópia em seu computador
A11: 8 - Filial | B11: Sim
A12: 9 - Empresa | B12: Sim
A13: 10 - Classe de produto | B13: Sim
A14: 11 - Registrante | B14: Não
A15: 12 - Produto | B15: Sim
A16: 13 - Produto Classe | B16: Sim
A17: 14 - Veículo | B17: Não
A18: 15 - Centro de custo | B18: Não | D18: Depende se vai utilizar centro de custo
A19: 16 - Cônjuge | B19: Não
A20: 17 - Cultura | B20: Sim
A21: 18 - Despesa | B21: Não
A22: 19 - Banco Cooperativa | B22: Não
A23: 20 - Agência | B23: Não
A24: 21 - PV Moeda | B24: Sim
A25: 22 - Usuário, usuário filial, usuário empresa | B25: Sim
A26: 23 - Região, usuário parceiro, usuário região | B26: Sim
A27: 24 - Vinculo Imobiliário, Posse e Arrendamento (propriedade) | B27: Não
A28: 25 - Região local | B28: Sim
A29: 26 - Safra | B29: Sim
A30: 27 - Tipo parceiro | B30: Sim
... A35: 30 - Faturamento mensal | B35: Não
A36: 31 - Limite Crédito Parceiro e Safra | B36: Não | D36: Depende se vai acompanhar o limite de crédito
A37: 32 - Local nota fiscal | B37: Não
A38: 33 - Modalidade Recolhimento Funrural | B38: Não | D38: Depende se vai utilizar importo no pedido de troca
A39: 34 - PV Pedido Histórico Situação | B39: Sim
A40: 35 - PV Pedido Item Histórico Situação | B40: Sim
A41: 36 - PV Pedido Item Nota Fiscal | B41: Sim
A42: 37 - PV Tabela Preço | B42: Sim
A43: 38 - PV Tabela Preço Item e PV Tabela Preço Item Vigência | B43: Sim | D43: Depende do tipo de preço praticado
A44: 39 - PV Tabela Preço Condição | B44: Sim | D44: Depende do tipo de preço praticado
A45: 40 - PV Tabela Preço Filial | B45: Sim | D45: Depende do tipo de preço praticado
A46: 41 - PV Tabela Preço Item Condição | B46: Sim | D46: Depende do tipo de preço praticado
A47: 42 - PV Tabela Preço Item Projeção | B47: Sim | D47: Depende do tipo de preço praticado
A48: 43 - PV Tabela Preço Safra | B48: Sim | D48: Depende do tipo de preço praticado
A49: 44 - PV Tabela Preço UF Destino | B49: Sim | D49: Depende do tipo de preço praticado
A50: 45 - PV Tipo de documento de cobrança | B50: Sim
A51: 46 - PV Tipo de negociação | B51: Sim
A52: 47 - Títulos | B52: Não
A53: 48 - Exportação do pedido de venda | B53: Sim
A54: 49 - PV Campanha de oferta | B54: Não | D54: OBS: Fluxo está em Desenvolvimento/Teste na Bom Jesus
A55: 50 - Registrante Marca | B55: Não
A56: 51 - Parceiro Tipo Parceiro | B56: Sim
A57: 52 - Atualiza coordenadas da propriedade no Simer | B57: Não
A58: 52 - Campanha de troca | B58: Não | D58: OBS: Fluxo está em Desenvolvimento/Teste na Bom Jesus

Sheet SIMERCLOV-Variáveis Al. Integra
A1: FLUXO | B1: VARIÁVEL/FILTRO | C1: VALOR | D1: COMO PREENCHER?
A2: 5 - Parceiro, Pessoa Física e Jurídica | B2: Classificação Tipo Pessoa | D2: Informar os códigos das classificações válidas separadas por vírgula (ex: 1, 2, 3). OBRIGATÓRIO. Para integrar somente o que é útil, como também reduzir o tamanho da carga inicial.
B3: Matriz principal | D3: Informar o código da matriz principal. OBRIGATÓRIO. Para migrar registro de parceiro padrão do Clover com chaveERP ALIARE#INTEGRA para o ID da matriz principal.
A4: 8 - Filial | B4: Filiais válidas | D4: Informar os códigos das filiais válidas separadas por vírgula (ex: 1, 2, 3). Se não preencher, todas serão consideradas.
A5: 9 - Empresa | B5: Empresas válidas | D5: Informar os códigos das empresas válidas separadas por vírgula (ex: 1, 2, 3). Se não preencher, todas serão consideradas.
B6: Matriz principal | D6: Informar o código da matriz principal. OBRIGATÓRIO. Para migrar registro de empresa padrão do Clover com chaveERP ALIARE#INTEGRA para o ID da matriz principal.
A7: 10 - Classe de produto | B7: Contas de estoque válidas | D7: Informar os IDs das contas estoque válidas separadas por vírgula (ex: 1, 2, 3). Se não preencher, todas serão consideradas.
A8: 12 - Produto | B8: Tipos de produtos válidos | D8: Informar os IDs dos tipos de produtos válidos separados por vírgula (ex: 1, 2, 3). Se não preencher, todas serão consideradas.
B9: Grupos de produto válidos | D9: Informar os IDs dos grupos válidos separadas por vírgula (ex: 1, 2, 3). Se não preencher, todas serão consideradas.
A10: 17 - Cultura | B10: Culturas válidas | D10: Informar os códigos das culturas válidas separadas por vírgula (ex: 1, 2, 3). Se não preencher, todas serão consideradas.
A11: 22 - Usuário, usuário filial, usuário empresa | B11: Departamentos válidos | D11: Informar os códigos dos departamentos válidos separadas por vírgula (ex: 1, 2, 3). Se não preencher, todas serão consideradas.
A12: 23 - Região, usuário parceiro, usuário região | B12: Categorias de vendedores válidos
A13: 26 - Safra | B13: Data de início da vigência | D13: Informar a data de corte para o inicio de vigência das safras (ex: 01/01/2023). OBRIGATÓRIO.
B14: Safras válidas | D14: Informar os códigos das safras válidas separadas por vírgula (ex: 1, 2, 3). Se não preencher, todas serão consideradas.
A15: 28 - Condição de pagamento | B15: Condições válidas | D15: Informar os códigos das condições válidas separadas por vírgula (ex: 1, 2, 3). Se não preencher, todas serão consideradas.
A16: 32 - Local nota fiscal | B16: Ano de corte | D16: Informar o ano de corte (ex: 2023). Se não preencher, todos serão considerados.
B17: Operações internas válidas | D17: Informar o ID Simer das operações internas que devem ser consideradas para integração de Local Nota Fiscal. OBRIGATÓRIO.
A18: 37 - PV Tabela Preço | B18: Tabelas válidas | D18: Informar os códigos das tabelas válidas separadas por vírgula (ex: 1, 2, 3). Se não preencher, todas serão consideradas.
B19: Utiliza barter? | D19: Informar "S" caso seja necessário integrar tabelas barter, se não, informar "N". Se não preencher, será preenchido com "S" para integrar todas tabelas.
A20: 45 - PV Tipo de documento de cobrança | B20: Tipos de cobrança válidos | D20: Informar os códigos dos tipos de cobrança separados por vírgula (ex: 1, 2, 3). Se não preencher, todas serão consideradas.
A21: 30 - Faturamento mensal | B21: Desconsidera Operações Internas | D21: Informar separadas por vírgula (ex: 1, 2, 3), os IDs das operações internas que precisam ser desconsideradas do relatório de pedido em aberto. Se não preencher, todas serão consideradas.
